Workbook
Name 被评估单位: 设定信息!$B$6
Name 评估基准日: 设定信息!$B$7

Sheet 目录
A2: 0-其他方法结论 | C2: 0-其他方法结论 | L2: 23 | M2: 9
A3: 1-汇总表 | C3: 资产评估结果汇总表 | L3: 31 | M3: 7
A4: 2-分类汇总 | C4: 资产评估结果分类汇总表 | L4: 65 | M4: 7
A5: 3-流动资产汇总 | C5: 流动资产评估汇总表 | L5: 26 | M5: 7
A6: 3-辅-流动资产汇总 | C6: 流动资产余额评估汇总表 | L6: 30 | M6: 7
A7: 3-1货币资金汇总表 | C7: 货币资金评估汇总表 | L7: 23 | M7: 8
A8: 3-1-1现金 | C8: 货币资金—现金评估明细表 | L8: 5 | M8: 10
A9: 3-1-2银行存款 | C9: 货币资金—银行存款评估明细表 | L9: 5 | M9: 11
A10: 3-1-3其他货币资金 | C10: 货币资金—其他货币资金评估明细表 | L10: 5 | M10: 11
A11: 3-2交易性金融资产汇总 | C11: 交易性金融资产评估汇总表 | L11: 24 | M11: 7
A12: 3-2-1-股票 | C12: 交易性金融资产—股票投资评估明细表 | L12: 5 | M12: 12
A13: 3-2-2-债券 | C13: 交易性金融资产—债券投资评估明细表 | L13: 5 | M13: 12
... A105: 9-非财务信息汇总表 | C105: 非财务信息汇总表 | L105: 100 | M105: 7

Sheet 0-报告用表
F2: 单位：万元 | K2: 单位：元
B3: 项 目 | C3: 账面价值 | D3: 评估价值 | E3: 增值额 | F3: 增值率% | I3: 资产项目 | J3: 账面原值 | K3: 账面净值
C4: A | D4: B | E4: C=B-A | F4: D=C/A×100 | I4: 流动资产 | K4: =IF('2-分类汇总'!E6="","",'2-分类汇总'!E6)
B5: 流动资产 | C5: =IF('1-汇总表'!E7="","",ROUND('1-汇总表'!E7,2)) | D5: =IF('1-汇总表'!F7="","",ROUND('1-汇总表'!F7,2)) | E5: =IF('1-汇总表'!G7="","",ROUND('1-汇总表'!G7,2)) | F5: =IF('1-汇总表'!H7="","",ROUND('1-汇总表'!H7,2)) | I5: 存货 | K5: =IF('2-分类汇总'!E15="","",ROUND('2-分类汇总'!E15,2))
B6: 存货 | C6: =IF('2-分类汇总'!E15="","",ROUND('2-分类汇总'!E15/10000,2)) | D6: =IF('2-分类汇总'!F15="","",ROUND('2-分类汇总'!F15/10000,2)) | E6: =IF('2-分类汇总'!G15="","",ROUND('2-分类汇总'!G15/10000,2)) | F6: =IF('2-分类汇总'!H15="","",ROUND('2-分类汇总'!H15,2)) | I6: 非流动资产 | K6: =IF('2-分类汇总'!E20="","",ROUND('2-分类汇总'!E20,2))
B7: 非流动资产 | C7: =IF('1-汇总表'!E8="","",ROUND('1-汇总表'!E8,2)) | D7: =IF('1-汇总表'!F8="","",ROUND('1-汇总表'!F8,2)) | E7: =IF('1-汇总表'!G8="","",ROUND('1-汇总表'!G8,2)) | F7: =IF('1-汇总表'!H8="","",ROUND('1-汇总表'!H8,2)) | I7: 长期股权投资 | K7: =IF('2-分类汇总'!E24="","",ROUND('2-分类汇总'!E24,2))
B8: 长期股权投资 | C8: =IF('1-汇总表'!E12="","",ROUND('1-汇总表'!E12,2)) | D8: =IF('1-汇总表'!F12="","",ROUND('1-汇总表'!F12,2)) | E8: =IF('1-汇总表'!G12="","",ROUND('1-汇总表'!G12,2)) | F8: =IF('1-汇总表'!H12="","",ROUND('1-汇总表'!H12,2)) | I8: 投资性房地产 | K8: =IF('2-分类汇总'!E27="","",ROUND('2-分类汇总'!E27,2))
B9: 投资性房地产 | C9: =IF('1-汇总表'!E15="","",ROUND('1-汇总表'!E15,2)) | D9: =IF('1-汇总表'!F15="","",ROUND('1-汇总表'!F15,2)) | E9: =IF('1-汇总表'!G15="","",ROUND('1-汇总表'!G15,2)) | F9: =IF('1-汇总表'!H15="","",ROUND('1-汇总表'!H15,2)) | I9: 固定资产 | J9: =IF('4-8固定资产汇总'!E20="","",ROUND('4-8固定资产汇总'!E20,2)) | K9: =IF('2-分类汇总'!E28="","",ROUND('2-分类汇总'!E28,2))
B10: 固定资产 | C10: =IF('1-汇总表'!E16="","",ROUND('1-汇总表'!E16,2)) | D10: =IF('1-汇总表'!F16="","",ROUND('1-汇总表'!F16,2)) | E10: =IF('1-汇总表'!G16="","",ROUND('1-汇总表'!G16,2)) | F10: =IF('1-汇总表'!H16="","",ROUND('1-汇总表'!H16,2)) | I10: 其中：建筑物类 | J10: =IF('4-8固定资产汇总'!E10="","",ROUND('4-8固定资产汇总'!E10,2)) | K10: =IF('4-8固定资产汇总'!F10="","",ROUND('4-8固定资产汇总'!F10,2))
B11: 其中：建筑物类 | C11: =IF('4-8固定资产汇总'!F10="","",ROUND('4-8固定资产汇总'!F10/10000,2)) | D11: =IF('4-8固定资产汇总'!H10="","",ROUND('4-8固定资产汇总'!H10/10000,2)) | E11: =IF('4-8固定资产汇总'!J10="","",ROUND('4-8固定资产汇总'!J10/10000,2)) | F11: =IF('4-8固定资产汇总'!L9="","",ROUND('4-8固定资产汇总'!L9,2)) | I11: 设备类 | J11: =IF('4-8固定资产汇总'!E16="","",ROUND('4-8固定资产汇总'!E16,2)) | K11: =IF('4-8固定资产汇总'!F16="","",ROUND('4-8固定资产汇总'!F16,2))
B12: 设备类 | C12: =IF('4-8固定资产汇总'!F16="","",ROUND('4-8固定资产汇总'!F16/10000,2)) | D12: =IF('4-8固定资产汇总'!H16="","",ROUND('4-8固定资产汇总'!H16/10000,2)) | E12: =IF('4-8固定资产汇总'!J16="","",ROUND('4-8固定资产汇总'!J16/10000,2)) | F12: =IF('4-8固定资产汇总'!L16="","",ROUND('4-8固定资产汇总'!L16,2)) | I12: 在建工程 | K12: =IF('2-分类汇总'!E29="","",ROUND('2-分类汇总'!E29,2))
B13: 在建工程 | C13: =IF('1-汇总表'!E17="","",ROUND('1-汇总表'!E17,2)) | D13: =IF('1-汇总表'!F17="","",ROUND('1-汇总表'!F17,2)) | E13: =IF('1-汇总表'!G17="","",ROUND('1-汇总表'!G17,2)) | F13: =IF('1-汇总表'!H17="","",ROUND('1-汇总表'!H17,2)) | I13: 无形资产 | K13: =IF('2-分类汇总'!E33="","",ROUND('2-分类汇总'!E33,2))
B14: 无形资产 | C14: =IF('1-汇总表'!E21="","",ROUND('1-汇总表'!E21,2)) | D14: =IF('1-汇总表'!F21="","",ROUND('1-汇总表'!F21,2)) | E14: =IF('1-汇总表'!G21="","",ROUND('1-汇总表'!G21,2)) | F14: =IF('1-汇总表'!H21="","",ROUND('1-汇总表'!H21,2)) | I14: 其中：土地使用权 | J14: =IF('4-13-1无形-土地'!L30="","",ROUND('4-13-1无形-土地'!L30,2)) | K14: =IF('4-13无形资产汇总'!E6="","",ROUND('4-13无形资产汇总'!E6,2))
B15: 其中：土地使用权 | C15: =IF('4-13无形资产汇总'!E6="","",ROUND('4-13无形资产汇总'!E6/10000,2)) | D15: =IF('4-13无形资产汇总'!F6="","",ROUND('4-13无形资产汇总'!F6/10000,2)) | E15: =IF('4-13无形资产汇总'!G6="","",ROUND('4-13无形资产汇总'!G6/10000,2)) | F15: =IF('4-13无形资产汇总'!H6="","",ROUND('4-13无形资产汇总'!H6,2)) | I15: 长期待摊费用 | K15: =IF('2-分类汇总'!E36="","",ROUND('2-分类汇总'!E36,2))
B16: 长期待摊费用 | C16: =IF('1-汇总表'!E24="","",ROUND('1-汇总表'!E24,2)) | D16: =IF('1-汇总表'!F24="","",ROUND('1-汇总表'!F24,2)) | E16: =IF('1-汇总表'!G24="","",ROUND('1-汇总表'!G24,2)) | F16: =IF('1-汇总表'!H24="","",ROUND('1-汇总表'!H24,2)) | I16: 递延所得税资产 | K16: =IF('2-分类汇总'!E37="","",ROUND('2-分类汇总'!E37,2))
B17: 递延所得税资产 | C17: =IF('1-汇总表'!E25="","",ROUND('1-汇总表'!E25,2)) | D17: =IF('1-汇总表'!F25="","",ROUND('1-汇总表'!F25,2)) | E17: =IF('1-汇总表'!G25="","",ROUND('1-汇总表'!G25,2)) | F17: =IF('1-汇总表'!H25="","",ROUND('1-汇总表'!H25,2)) | I17: 其他非流动资产 | K17: =IF('2-分类汇总'!E38="","",ROUND('2-分类汇总'!E38,2))
B18: 其他非流动资产 | C18: =IF('1-汇总表'!E26="","",ROUND('1-汇总表'!E26,2)) | D18: =IF('1-汇总表'!F26="","",ROUND('1-汇总表'!F26,2)) | E18: =IF('1-汇总表'!G26="","",ROUND('1-汇总表'!G26,2)) | F18: =IF('1-汇总表'!H26="","",ROUND('1-汇总表'!H26,2)) | I18: 资产总计 | K18: =IF('2-分类汇总'!E39="","",ROUND('2-分类汇总'!E39,2))
B19: 资产总计 | C19: =IF('1-汇总表'!E27="","",ROUND('1-汇总表'!E27,2)) | D19: =IF('1-汇总表'!F27="","",ROUND('1-汇总表'!F27,2)) | E19: =IF('1-汇总表'!G27="","",ROUND('1-汇总表'!G27,2)) | F19: =IF('1-汇总表'!H27="","",ROUND('1-汇总表'!H27,2)) | I19: 流动负债 | K19: =IF('2-分类汇总'!E40="","",ROUND('2-分类汇总'!E40,2))
B20: 流动负债 | C20: =IF('1-汇总表'!E28="","",ROUND('1-汇总表'!E28,2)) | D20: =IF('1-汇总表'!F28="","",ROUND('1-汇总表'!F28,2)) | E20: =IF('1-汇总表'!G28="","",ROUND('1-汇总表'!G28,2)) | F20: =IF('1-汇总表'!H28="","",ROUND('1-汇总表'!H28,2)) | I20: 非流动负债 | K20: =IF('2-分类汇总'!E54="","",ROUND('2-分类汇总'!E54,2))
B21: 非流动负债 | C21: =IF('1-汇总表'!E29="","",ROUND('1-汇总表'!E29,2)) | D21: =IF('1-汇总表'!F29="","",ROUND('1-汇总表'!F29,2)) | E21: =IF('1-汇总表'!G29="","",ROUND('1-汇总表'!G29,2)) | F21: =IF('1-汇总表'!H29="","",ROUND('1-汇总表'!H29,2)) | I21: 负债合计 | K21: =IF('2-分类汇总'!E64="","",ROUND('2-分类汇总'!E64,2))
B22: 负债合计 | C22: =IF('1-汇总表'!E30="","",ROUND('1-汇总表'!E30,2)) | D22: =IF('1-汇总表'!F30="","",ROUND('1-汇总表'!F30,2)) | E22: =IF('1-汇总表'!G30="","",ROUND('1-汇总表'!G30,2)) | F22: =IF('1-汇总表'!H30="","",ROUND('1-汇总表'!H30,2)) | I22: 所有者权益(净资产) | K22: =IF('2-分类汇总'!E65="","",ROUND('2-分类汇总'!E65,2))
B23: 所有者权益(净资产) | C23: =IF('1-汇总表'!E31="","",ROUND('1-汇总表'!E31,2)) | D23: =IF('1-汇总表'!F31="","",ROUND('1-汇总表'!F31,2)) | E23: =IF('1-汇总表'!G31="","",ROUND('1-汇总表'!G31,2)) | F23: =IF('1-汇总表'!H31="","",ROUND('1-汇总表'!H31,2))
I24: 注：非流动资产只列示了常用科目，可根据实际情况增加。

Sheet 公式数据表
A4: 账龄设置
B5: 账龄 | C5: D值
C6: 下限 | D6: 上限 | G6: D=（评估基准日-发生日期）/365
B7: 1年以内 | C7: 0 | D7: 1
B8: 1～2年 | C8: 1 | D8: 2
B9: 2～3年 | C9: 2 | D9: 3
B10: 3年以上 | C10: 3

Sheet 设置
D2: 左页脚信息
C3: =设定信息!$A$6&"填表人：" | D3: 张三
C4: 填表日期： | D4: 44617
D7: 右页脚信息
A8: 序号 | B8: 选定 | C8: 表页名称 | D8: 评估专业人员姓名
A9: 1 | B9: √ | C9: 1-汇总表
A10: 2 | B10: √ | C10: 2-分类汇总
A11: 3 | B11: √ | C11: 3-流动资产汇总
A12: 3-1 | B12: √ | C12: 3-1货币资金汇总表
A13: 3-1-1 | B13: √ | C13: 3-1-1现金
A14: 3-1-2 | B14: √ | C14: 3-1-2银行存款
A15: 3-1-3 | B15: √ | C15: 3-1-3其他货币资金
A16: 3-2 | B16: √ | C16: 3-2交易性金融资产汇总
A17: 3-2-1 | B17: √ | C17: 3-2-1-股票 | D17: 张三 李四
A18: 3-2-2 | B18: √ | C18: 3-2-2-债券 | D18: 张三 李四
A19: 3-2-3 | B19: √ | C19: 3-2-3-基金 | D19: 张三 李四
A20: 3-3 | B20: √ | C20: 3-3衍生金融资产 | D20: 张三 李四
A21: 3-4 | B21: √ | C21: 3-4应收票据 | D21: 张三 李四
A22: 3-5 | B22: √ | C22: 3-5应收账款 | D22: 张三 李四
A23: 3-6 | B23: √ | C23: 3-6应收款项融资 | D23: 张三 李四
A24: 3-7 | B24: √ | C24: 3-7预付款项 | D24: 张三 李四
A25: 3-8 | B25: √ | C25: 3-8其他应收款汇总 | D25: 张三 李四
A26: 3-8-1 | B26: √ | C26: 3-8-1应收利息 | D26: 张三 李四
A27: 3-8-2 | B27: √ | C27: 3-8-2应收股利 | D27: 张三 李四
A28: 3-8-3 | B28: √ | C28: 3-8-3其他应收款 | D28: 张三 李四
... A35: 3-9-6 | B35: √ | C35: 3-9-6在产品（自制半成品） | D35: 张三 李四
A36: 3-9-7 | B36: √ | C36: 3-9-7发出商品
A37: 3-9-8 | B37: √ | C37: 3-9-8在用周转材料
A38: 3-9-9 | B38: √ | C38: 3-9-9合同履约成本
A39: 3-10 | B39: √ | C39: 3-10合同资产
A40: 3-11 | B40: √ | C40: 3-11持有待售资产
A41: 3-12 | B41: √ | C41: 3-12一年到期非流动资产
A42: 3-13 | B42: √ | C42: 3-13其他流动资产
A43: 4 | B43: √ | C43: 4-非流动资产汇总
A44: 4-1 | B44: √ | C44: 4-1债权投资
A45: 4-2 | B45: √ | C45: 4-2其他债权投资
A46: 4-3 | B46: √ | C46: 4-3长期应收
A47: 4-4 | B47: √ | C47: 4-4股权投资
... A108: 6-9 | B108: √ | C108: 6-9其他非流动负债

Sheet 0-其他方法结论
D2: 请输入
C4: 合并报表归属于母公司的净资产 | E4: 万元
C5: 收益法评估结果 | E5: 万元
C6: 市场法评估结果 | E6: 万元
C7: 结论方法 | D7: 收益法
C8: 未作为结论方法 | D8: 资产基础法
C9: 评估结果及增减值率
C10: 项目 | D10: 账面价值(万元） | E10: 评估结果(万元） | F10: 增值额(万元） | G10: 增值率% | H10: 评估值结果大写 | I10: 评估方法名称 | J10: 增值/减值
D11: A | E11: B | F11: C=B-A | G11: D=C/A×100
A12: 1 | B12: 资产结果 | C12: 资产基础法 | D12: ='1-汇总表'!E31 | E12: ='1-汇总表'!F31 | F12: =E12-D12 | G12: =IF(D12=0,"",ROUND(F12/D12*100,2)) | H12: =IF(E12<0,"负"&NUMBERSTRING(ABS(E12)*10000,2),NUMBERSTRING(ABS(E12)*10000,2)) | I12: =C12 | J12: =IF(F12>0.001,"评估增值",IF(F12<-0.001,"评估减值","无评估增减值"))
A13: 2 | B13: 收益结果 | C13: 收益法 | D13: =$D$12 | E13: =D5 | F13: =E13-D13 | G13: =IF(D13=0,"",ROUND(F13/D13*100,2)) | H13: =IF(E13<0,"负"&NUMBERSTRING(ABS(E13)*10000,2),NUMBERSTRING(ABS(E13)*10000,2)) | I13: =C13 | J13: =IF(F13>0.001,"评估增值",IF(F13<-0.001,"评估减值","无评估增减值"))
A14: 3 | B14: 市场结果 | C14: 市场法 | D14: =$D$12 | E14: =D6 | F14: =E14-D14 | G14: =IF(D14=0,"",ROUND(F14/D14*100,2)) | H14: =IF(E14<0,"负"&NUMBERSTRING(ABS(E14)*10000,2),NUMBERSTRING(ABS(E14)*10000,2)) | I14: =C14 | J14: =IF(F14>0.001,"评估增值",IF(F14<-0.001,"评估减值","评估无增减值"))
A15: 4 | B15: 成本结果 | C15: 成本法 | D15: =$D$12 | E15: =E12 | F15: =E15-D15 | G15: =IF(D15=0,"",ROUND(F15/D15*100,2)) | H15: =IF(E15<0,"负"&NUMBERSTRING(ABS(E15)*10000,2),NUMBERSTRING(ABS(E15)*10000,2)) | I15: =C15 | J15: =IF(F15>0.001,"评估增值",IF(F15<-0.001,"评估减值","评估无增减值"))
A16: 5 | B16: 不适用 | C16: 不适用 | I16: =C16
A17: 6 | B17: 最终结果 | C17: 最终结果 | D17: =INDEX(D12:D16,MATCH(D7,C12:C16,0)) | E17: =INDEX(E12:E16,MATCH(D7,C12:C16,0)) | F17: =E17-D17 | G17: =IF(D17=0,"",ROUND(F17/D17*100,2)) | H17: =IF(E17<0,"负"&NUMBERSTRING(ABS(E17)*10000,2),NUMBERSTRING(ABS(E17)*10000,2)) | I17: =D7 | J17: =IF(F17>0.001,"评估增值",IF(F17<-0.001,"评估减值","评估无增减值"))
A18: 7 | B18: 未用结果 | C18: 未采用结果 | D18: =INDEX(D12:D16,MATCH(D8,C12:C16,0)) | E18: =INDEX(E12:E16,MATCH(D8,C12:C16,0)) | F18: =E18-D18 | G18: =IF(D18=0,"",ROUND(F18/D18*100,2)) | H18: =IF(E18<0,"负"&NUMBERSTRING(ABS(E18)*10000,2),NUMBERSTRING(ABS(E18)*10000,2)) | I18: =D8 | J18: =IF(F18>0.001,"评估增值",IF(F18<-0.001,"评估减值","评估无增减值"))
A19: 8 | B19: 合表增减 | C19: 与合并报表比较 | D19: =D4 | E19: =E17 | F19: =E19-D19 | G19: =IF(D19=0,"",ROUND(F19/D19*100,2)) | H19: =IF(E19<0,"负"&NUMBERSTRING(ABS(E19)*10000,2),NUMBERSTRING(ABS(E19)*10000,2)) | I19: =D7 | J19: =IF(F19>0.001,"评估增值",IF(F19<-0.001,"评估减值","评估无增减值"))
C21: 不同方法的对比结果
C22: 方法比较 | D22: =C7 | E22: =C8 | F22: 差异绝对值（万元） | G22: 差异率%
A23: 9 | B23: 差异对比 | C23: 不同方法的对比 | D23: =INDEX(E12:E16,MATCH(D7,C12:C16,0)) | E23: =INDEX(E12:E16,MATCH(D8,C12:C16,0)) | F23: =ABS(D23-E23) | G23: =IF(E13=0,"",ROUND(F23/MAX(D23,E23)*100,2))

Sheet 设定信息
A1: TYPG-XT-ZPX-3.4.56
A5: 基本信息：
A6: 被评估单位 | B6: 浙江ABC有限责任公司
A7: 评估基准日 | B7: 44926
A8: 除“1-汇总表”金额单位 | B8: 人民币元
A9: “1-汇总表”金额单位 | B9: 人民币万元
A11: 审计机构名称 | B11: XX会计师事务所
A12: 审计报告文号 | B12: 审〔2023〕XXX号
A13: 审计报告意见类型 | B13: 标准的无保留意见
A14: 审计报告名称 | B14: XX公司审计报告
A15: 审计报告出具日期 | B15: 44949
A25: 填表注意事项：
A26: 1.请注意粘帖明细表时，用选择性粘帖，否则单元格格式将被修改。
A27: 2.若增减行数，打印前请注意使表格满页。
A28: 3.打印前请增加页脚信息，页脚评估人员应包含两位签字评估师+其他参与操作人员。
A29: 4.用不到的表页，应隐藏，不能删除。

Sheet 1-汇总表
B1: 资产评估结果汇总表
B2: ='2-分类汇总'!B2
H3: 表1
B4: ='2-分类汇总'!B4 | H4: =RIGHT(设定信息!A9,4)&"："&设定信息!B9
B5: 项 目 | E5: 账面价值 | F5: 评估价值 | G5: 增值额 | H5: 增值率％
E6: A | F6: B | G6: C=B-A | H6: D=C/A×100
B7: 1 | C7: 流资汇总 | D7: 流动资产 | E7: =ROUND('3-流动资产汇总'!E26/10000,2) | F7: =ROUND('3-流动资产汇总'!F26/10000,2) | G7: =IF((F7-E7)=0,"",(F7-E7)) | H7: =IF(OR(E7=0,E7="",G7=""),"",IF(E7<0,-G7/E7*100,G7/E7*100))
B8: 2 | C8: 非资汇总 | D8: 非流动资产 | E8: =ROUND('4-非流动资产汇总'!E27/10000,2) | F8: =ROUND('4-非流动资产汇总'!F27/10000,2) | G8: =IF((F8-E8)=0,"",(F8-E8)) | H8: =IF(OR(E8=0,E8="",G8=""),"",IF(E8<0,-G8/E8*100,G8/E8*100))
B9: 3 | C9: 债权投资 | D9: 其中：债权投资 | E9: =ROUND('4-非流动资产汇总'!E6/10000,2) | F9: =ROUND('4-非流动资产汇总'!F6/10000,2) | G9: =IF((F9-E9)=0,"",(F9-E9)) | H9: =IF(OR(E9=0,E9="",G9=""),"",IF(E9<0,-G9/E9*100,G9/E9*100))
B10: 4 | C10: 其他债权 | D10: 其他债权投资 | E10: =ROUND('4-非流动资产汇总'!E7/10000,2) | F10: =ROUND('4-非流动资产汇总'!F7/10000,2) | G10: =IF((F10-E10)=0,"",(F10-E10)) | H10: =IF(OR(E10=0,E10="",G10=""),"",IF(E10<0,-G10/E10*100,G10/E10*100))
B11: 5 | C11: 长期应收 | D11: 长期应收款 | E11: =ROUND('4-非流动资产汇总'!E8/10000,2) | F11: =ROUND('4-非流动资产汇总'!F8/10000,2) | G11: =IF((F11-E11)=0,"",(F11-E11)) | H11: =IF(OR(E11=0,E11="",G11=""),"",IF(E11<0,-G11/E11*100,G11/E11*100))
B12: 6 | C12: 长期股权 | D12: 长期股权投资 | E12: =ROUND('4-非流动资产汇总'!E9/10000,2) | F12: =ROUND('4-非流动资产汇总'!F9/10000,2) | G12: =IF((F12-E12)=0,"",(F12-E12)) | H12: =IF(OR(E12=0,E12="",G12=""),"",IF(E12<0,-G12/E12*100,G12/E12*100))
B13: 7 | C13: 其他权投 | D13: 其他权益工具投资 | E13: =ROUND('4-非流动资产汇总'!E10/10000,2) | F13: =ROUND('4-非流动资产汇总'!F10/10000,2) | G13: =IF((F13-E13)=0,"",(F13-E13)) | H13: =IF(OR(E13=0,E13="",G13=""),"",IF(E13<0,-G13/E13*100,G13/E13*100))
B14: 8 | C14: 其他非金 | D14: 其他非流动金融资产 | E14: =ROUND('4-非流动资产汇总'!E11/10000,2) | F14: =ROUND('4-非流动资产汇总'!F11/10000,2) | G14: =IF((F14-E14)=0,"",(F14-E14)) | H14: =IF(OR(E14=0,E14="",G14=""),"",IF(E14<0,-G14/E14*100,G14/E14*100))
B15: 9 | C15: 投房汇总 | D15: 投资性房地产 | E15: =ROUND('4-非流动资产汇总'!E12/10000,2) | F15: =ROUND('4-非流动资产汇总'!F12/10000,2) | G15: =IF((F15-E15)=0,"",(F15-E15)) | H15: =IF(OR(E15=0,E15="",G15=""),"",IF(E15<0,-G15/E15*100,G15/E15*100))
B16: 10 | C16: 固资汇总 | D16: 固定资产 | E16: =ROUND('4-非流动资产汇总'!E13/10000,2) | F16: =ROUND('4-非流动资产汇总'!F13/10000,2) | G16: =IF((F16-E16)=0,"",(F16-E16)) | H16: =IF(OR(E16=0,E16="",G16=""),"",IF(E16<0,-G16/E16*100,G16/E16*100))
B17: 11 | C17: 在建汇总 | D17: 在建工程 | E17: =ROUND('4-非流动资产汇总'!E14/10000,2) | F17: =ROUND('4-非流动资产汇总'!F14/10000,2) | G17: =IF((F17-E17)=0,"",(F17-E17)) | H17: =IF(OR(E17=0,E17="",G17=""),"",IF(E17<0,-G17/E17*100,G17/E17*100))
B18: 12 | C18: 生物资产 | D18: 生产性生物资产 | E18: =ROUND('4-非流动资产汇总'!E15/10000,2) | F18: =ROUND('4-非流动资产汇总'!F15/10000,2) | G18: =IF((F18-E18)=0,"",(F18-E18)) | H18: =IF(OR(E18=0,E18="",G18=""),"",IF(E18<0,-G18/E18*100,G18/E18*100))
B19: 13 | C19: 油气资产 | D19: 油气资产 | E19: =ROUND('4-非流动资产汇总'!E16/10000,2) | F19: =ROUND('4-非流动资产汇总'!F16/10000,2) | G19: =IF((F19-E19)=0,"",(F19-E19)) | H19: =IF(OR(E19=0,E19="",G19=""),"",IF(E19<0,-G19/E19*100,G19/E19*100))
B20: 14 | C20: 使用资产 | D20: 使用权资产 | E20: =ROUND('4-非流动资产汇总'!E17/10000,2) | F20: =ROUND('4-非流动资产汇总'!F17/10000,2) | G20: =IF((F20-E20)=0,"",(F20-E20)) | H20: =IF(OR(E20=0,E20="",G20=""),"",IF(E20<0,-G20/E20*100,G20/E20*100))
... B26: 20 | C26: 其他非资 | D26: 其他非流动资产 | E26: =ROUND('4-非流动资产汇总'!E23/10000,2) | F26: =ROUND('4-非流动资产汇总'!F23/10000,2) | G26: =IF((F26-E26)=0,"",(F26-E26)) | H26: =IF(OR(E26=0,E26="",G26=""),"",IF(E26<0,-G26/E26*100,G26/E26*100))
B27: 21 | C27: 资产总计 | D27: 资产总计 | E27: =SUM(E7:E8) | F27: =SUM(F7:F8) | G27: =IF((F27-E27)=0,"",(F27-E27)) | H27: =IF(OR(E27=0,E27="",G27=""),"",IF(E27<0,-G27/E27*100,G27/E27*100))
B28: 22 | C28: 流债汇总 | D28: 流动负债 | E28: =ROUND('5-流动负债汇总'!E27/10000,2) | F28: =ROUND('5-流动负债汇总'!F27/10000,2) | G28: =IF((F28-E28)=0,"",(F28-E28)) | H28: =IF(OR(E28=0,E28="",G28=""),"",IF(E28<0,-G28/E28*100,G28/E28*100))
B29: 23 | C29: 非债汇总 | D29: 非流动负债 | E29: =ROUND('6-非流动负债汇总'!E27/10000,2) | F29: =ROUND('6-非流动负债汇总'!F27/10000,2) | G29: =IF((F29-E29)=0,"",(F29-E29)) | H29: =IF(OR(E29=0,E29="",G29=""),"",IF(E29<0,-G29/E29*100,G29/E29*100))
B30: 24 | C30: 负债总计 | D30: 负债合计 | E30: =SUM(E28:E29) | F30: =SUM(F28:F29) | G30: =IF((F30-E30)=0,"",(F30-E30)) | H30: =IF(OR(E30=0,E30="",G30=""),"",IF(E30<0,-G30/E30*100,G30/E30*100))
A31: 合计1 | B31: 25 | C31: 股东权益 | D31: 净资产（所有者权益） | E31: =E27-E30 | F31: =F27-F30 | G31: =IF((F31-E31)=0,"",(F31-E31)) | H31: =IF(OR(E31=0,E31="",G31=""),"",IF(E31<0,-G31/E31*100,G31/E31*100))
E33: =IF(ABS(E27-E30-E31)<0.001,"","不平") | F33: =IF(ABS(F27-F30-F31)<0.001,"","不平") | H33: 评估机构：天源资产评估有限公司
D34: 校验 | E34: =IF(AND('2-分类汇总'!E39/10000-E27>-0.01,'2-分类汇总'!E39/10000-E27<0.01),"无误","合计有误") | F34: =IF(AND('2-分类汇总'!F39/10000-F27>-0.01,'2-分类汇总'!F39/10000-F27<0.01),"无误","合计有误")
E35: =IF(AND('2-分类汇总'!E65/10000-E31>-0.01,'2-分类汇总'!E65/10000-E31<0.01),"无误","合计有误") | F35: =IF(AND('2-分类汇总'!F65/10000-F31>-0.01,'2-分类汇总'!F65/10000-F31<0.01),"无误","合计有误")
E36: =IF(AND((E8-SUM(E9:E26))>-0.01,(E8-SUM(E9:E26))<0.01),"无误","合计有误") | F36: =IF(AND((F8-SUM(F9:F26))>-0.01,(F8-SUM(F9:F26))<0.01),"无误","合计有误")

Sheet 2-分类汇总
B1: 资产评估结果分类汇总表
B2: =设定信息!A7&"："&TEXT(评估基准日,"yyyy年m月d日")
H3: 表2
B4: =设定信息!A6&"："&设定信息!B6 | H4: =RIGHT(设定信息!A8,4)&"："&设定信息!B8
B5: 序号 | C5: 项目编号 | D5: 科目名称 | E5: 账面价值 | F5: 评估价值 | G5: 增值额 | H5: 增值率% | I5: 报表金额 | J5: 校验 | K5: 科目链接
B6: 1 | C6: 流资汇总 | D6: 一、流动资产合计 | E6: =SUM(E7:E19) | F6: =SUM(F7:F19) | G6: =F6-E6 | H6: =IF(E6=0,"",IF(E6<0,-G6/E6*100,G6/E6*100)) | I6: =SUM(I7:I19) | J6: =E6-I6
B7: 2 | C7: 货币汇总 | D7: 货币资金 | E7: ='3-流动资产汇总'!E6 | F7: ='3-流动资产汇总'!F6 | G7: =F7-E7 | H7: =IF(E7=0,"",IF(E7<0,-G7/E7*100,G7/E7*100)) | J7: =E7-I7 | K7: =HYPERLINK("#\"3-1货币资金汇总表\"!A1","货币资金")
B8: 3 | C8: 交融汇总 | D8: 交易性金融资产 | E8: ='3-流动资产汇总'!E7 | F8: ='3-流动资产汇总'!F7 | G8: =F8-E8 | H8: =IF(E8=0,"",IF(E8<0,-G8/E8*100,G8/E8*100)) | J8: =E8-I8 | K8: =HYPERLINK("#\"3-2交易性金融资产汇总\"!A1","交易性金融资产")
B9: 4 | C9: 衍金资产 | D9: 衍生金融资产 | E9: ='3-流动资产汇总'!E8 | F9: ='3-流动资产汇总'!F8 | G9: =F9-E9 | H9: =IF(E9=0,"",IF(E9<0,-G9/E9*100,G9/E9*100)) | J9: =E9-I9 | K9: =HYPERLINK("#\"3-3衍生金融资产\"!A1","衍生金融资产")
B10: 5 | C10: 应收票据 | D10: 应收票据 | E10: ='3-流动资产汇总'!E9 | F10: ='3-流动资产汇总'!F9 | G10: =F10-E10 | H10: =IF(E10=0,"",IF(E10<0,-G10/E10*100,G10/E10*100)) | J10: =E10-I10 | K10: =HYPERLINK("#\"3-4应收票据\"!A1","应收票据")
B11: 6 | C11: 应收账款 | D11: 应收账款 | E11: ='3-流动资产汇总'!E10 | F11: ='3-流动资产汇总'!F10 | G11: =F11-E11 | H11: =IF(E11=0,"",IF(E11<0,-G11/E11*100,G11/E11*100)) | J11: =E11-I11 | K11: =HYPERLINK("#\"3-5应收账款\"!A1","应收账款")
B12: 7 | C12: 应收融资 | D12: 应收款项融资 | E12: ='3-流动资产汇总'!E11 | F12: ='3-流动资产汇总'!F11 | G12: =F12-E12 | H12: =IF(E12=0,"",IF(E12<0,-G12/E12*100,G12/E12*100)) | J12: =E12-I12 | K12: =HYPERLINK("#\"3-6应收款项融资\"!A1","应收款项融资")
B13: 8 | C13: 预付账款 | D13: 预付款项 | E13: ='3-流动资产汇总'!E12 | F13: ='3-流动资产汇总'!F12 | G13: =F13-E13 | H13: =IF(E13=0,"",IF(E13<0,-G13/E13*100,G13/E13*100)) | J13: =E13-I13 | K13: =HYPERLINK("#\"3-7预付款项\"!A1","预付款项")
B14: 9 | C14: 其收汇总 | D14: 其他应收款 | E14: ='3-流动资产汇总'!E13 | F14: ='3-流动资产汇总'!F13 | G14: =F14-E14 | H14: =IF(E14=0,"",IF(E14<0,-G14/E14*100,G14/E14*100)) | J14: =E14-I14 | K14: =HYPERLINK("#\"3-8其他应收款汇总\"!A1","其他应收款")
B15: 10 | C15: 存货汇总 | D15: 存货 | E15: ='3-流动资产汇总'!E14 | F15: ='3-流动资产汇总'!F14 | G15: =F15-E15 | H15: =IF(E15=0,"",IF(E15<0,-G15/E15*100,G15/E15*100)) | J15: =E15-I15 | K15: =HYPERLINK("#\"3-9存货汇总\"!A1","存货")
B16: 11 | C16: 合同资产 | D16: 合同资产 | E16: ='3-流动资产汇总'!E15 | F16: ='3-流动资产汇总'!F15 | G16: =F16-E16 | H16: =IF(E16=0,"",IF(E16<0,-G16/E16*100,G16/E16*100)) | J16: =E16-I16 | K16: =HYPERLINK("#\"3-10合同资产\"!A1","合同资产")
B17: 12 | C17: 持有代资 | D17: 持有待售资产 | E17: ='3-流动资产汇总'!E16 | F17: ='3-流动资产汇总'!F16 | G17: =F17-E17 | H17: =IF(E17=0,"",IF(E17<0,-G17/E17*100,G17/E17*100)) | J17: =E17-I17 | K17: =HYPERLINK("#\"3-11持有待售资产\"!A1","持有待售资产")
B18: 13 | C18: 到期非流 | D18: 一年内到期的非流动资产 | E18: ='3-流动资产汇总'!E17 | F18: ='3-流动资产汇总'!F17 | G18: =F18-E18 | H18: =IF(E18=0,"",IF(E18<0,-G18/E18*100,G18/E18*100)) | J18: =E18-I18 | K18: =HYPERLINK("#\"3-12一年到期非流动资产\"!A1","一年内到期的非流动资产")
B19: 14 | C19: 其他流资 | D19: 其他流动资产 | E19: ='3-流动资产汇总'!E18 | F19: ='3-流动资产汇总'!F18 | G19: =F19-E19 | H19: =IF(E19=0,"",IF(E19<0,-G19/E19*100,G19/E19*100)) | J19: =E19-I19 | K19: =HYPERLINK("#\"3-13其他流动资产\"!A1","其他流动资产")
B20: 15 | C20: 非资汇总 | D20: 二、非流动资产合计 | E20: =SUM(E21:E38) | F20: =SUM(F21:F38) | G20: =F20-E20 | H20: =IF(E20=0,"",IF(E20<0,-G20/E20*100,G20/E20*100)) | I20: =SUM(I21:I38) | J20: =E20-I20
B21: 16 | C21: 债权投资 | D21: 债权投资 | E21: ='4-非流动资产汇总'!E6 | F21: ='4-非流动资产汇总'!F6 | G21: =F21-E21 | H21: =IF(E21=0,"",IF(E21<0,-G21/E21*100,G21/E21*100)) | J21: =E21-I21 | K21: =HYPERLINK("#\"4-1债权投资\"!A1","债权投资")
B22: 17 | C22: 其他债权 | D22: 其他债权投资 | E22: ='4-非流动资产汇总'!E7 | F22: ='4-非流动资产汇总'!F7 | G22: =F22-E22 | H22: =IF(E22=0,"",IF(E22<0,-G22/E22*100,G22/E22*100)) | J22: =E22-I22 | K22: =HYPERLINK("#\"4-2其他债权投资\"!A1","其他债权投资")
B23: 18 | C23: 长期应收 | D23: 长期应收款 | E23: ='4-非流动资产汇总'!E8 | F23: ='4-非流动资产汇总'!F8 | G23: =F23-E23 | H23: =IF(E23=0,"",IF(E23<0,-G23/E23*100,G23/E23*100)) | J23: =E23-I23 | K23: =HYPERLINK("#\"4-3长期应收\"!A1","长期应收款")
B24: 19 | C24: 长期股权 | D24: 长期股权投资 | E24: ='4-非流动资产汇总'!E9 | F24: ='4-非流动资产汇总'!F9 | G24: =F24-E24 | H24: =IF(E24=0,"",IF(E24<0,-G24/E24*100,G24/E24*100)) | J24: =E24-I24 | K24: =HYPERLINK("#\"4-4股权投资\"!A1","长期股权投资")
B25: 20 | C25: 其他权投 | D25: 其他权益工具投资 | E25: ='4-非流动资产汇总'!E10 | F25: ='4-非流动资产汇总'!F10 | G25: =F25-E25 | H25: =IF(E25=0,"",IF(E25<0,-G25/E25*100,G25/E25*100)) | J25: =E25-I25 | K25: =HYPERLINK("#\"4-5其他权益工具投资\"!A1","其他权益工具投资")
B26: 21 | C26: 其他非金 | D26: 其他非流动金融资产 | E26: ='4-非流动资产汇总'!E11 | F26: ='4-非流动资产汇总'!F11 | G26: =F26-E26 | H26: =IF(E26=0,"",IF(E26<0,-G26/E26*100,G26/E26*100)) | J26: =E26-I26 | K26: =HYPERLINK("#\"4-6其他非流动金融资产汇总\"!A1","其他非流动金融资产")
B27: 22 | C27: 投房汇总 | D27: 投资性房地产 | E27: ='4-非流动资产汇总'!E12 | F27: ='4-非流动资产汇总'!F12 | G27: =F27-E27 | H27: =IF(E27=0,"",IF(E27<0,-G27/E27*100,G27/E27*100)) | J27: =E27-I27 | K27: =HYPERLINK("#\"4-7投资性房地产汇总\"!A1","投资性房地产")
B28: 23 | C28: 固资汇总 | D28: 固定资产 | E28: ='4-非流动资产汇总'!E13 | F28: ='4-非流动资产汇总'!F13 | G28: =F28-E28 | H28: =IF(E28=0,"",IF(E28<0,-G28/E28*100,G28/E28*100)) | J28: =E28-I28 | K28: =HYPERLINK("#\"4-8固定资产汇总\"!A1","固定资产")
B29: 24 | C29: 在建汇总 | D29: 在建工程 | E29: ='4-非流动资产汇总'!E14 | F29: ='4-非流动资产汇总'!F14 | G29: =F29-E29 | H29: =IF(E29=0,"",IF(E29<0,-G29/E29*100,G29/E29*100)) | J29: =E29-I29 | K29: =HYPERLINK("#\"4-9在建工程汇总\"!A1","在建工程")
B30: 25 | C30: 生物资产 | D30: 生产性生物资产 | E30: ='4-非流动资产汇总'!E15 | F30: ='4-非流动资产汇总'!F15 | G30: =F30-E30 | H30: =IF(E30=0,"",IF(E30<0,-G30/E30*100,G30/E30*100)) | J30: =E30-I30 | K30: =HYPERLINK("#\"4-10生产性生物资产\"!A1","生产性生物资产")
B31: 26 | C31: 油气资产 | D31: 油气资产 | E31: ='4-非流动资产汇总'!E16 | F31: ='4-非流动资产汇总'!F16 | G31: =F31-E31 | H31: =IF(E31=0,"",IF(E31<0,-G31/E31*100,G31/E31*100)) | J31: =E31-I31 | K31: =HYPERLINK("#\"4-11油气资产\"!A1","油气资产")
B32: 27 | C32: 使用资产 | D32: 使用权资产 | E32: ='4-非流动资产汇总'!E17 | F32: ='4-非流动资产汇总'!F17 | G32: =F32-E32 | H32: =IF(E32=0,"",IF(E32<0,-G32/E32*100,G32/E32*100)) | J32: =E32-I32 | K32: =HYPERLINK("#\"4-12使用权资产\"!A1","使用权资产")
B33: 28 | C33: 无形汇总 | D33: 无形资产 | E33: ='4-非流动资产汇总'!E18 | F33: ='4-非流动资产汇总'!F18 | G33: =F33-E33 | H33: =IF(E33=0,"",IF(E33<0,-G33/E33*100,G33/E33*100)) | J33: =E33-I33 | K33: =HYPERLINK("#\"4-13无形资产汇总\"!A1","无形资产")
B34: 29 | C34: 开发支出 | D34: 开发支出 | E34: ='4-非流动资产汇总'!E19 | F34: ='4-非流动资产汇总'!F19 | G34: =F34-E34 | H34: =IF(E34=0,"",IF(E34<0,-G34/E34*100,G34/E34*100)) | J34: =E34-I34 | K34: =HYPERLINK("#\"4-14开发支出\"!A1","开发支出")
B35: 30 | C35: 商誉资产 | D35: 商誉 | E35: ='4-非流动资产汇总'!E20 | F35: ='4-非流动资产汇总'!F20 | G35: =F35-E35 | H35: =IF(E35=0,"",IF(E35<0,-G35/E35*100,G35/E35*100)) | J35: =E35-I35 | K35: =HYPERLINK("#\"4-15商誉\"!A1","商誉")
B36: 31 | C36: 长期待摊 | D36: 长期待摊费用 | E36: ='4-非流动资产汇总'!E21 | F36: ='4-非流动资产汇总'!F21 | G36: =F36-E36 | H36: =IF(E36=0,"",IF(E36<0,-G36/E36*100,G36/E36*100)) | J36: =E36-I36 | K36: =HYPERLINK("#\"4-16长期待摊费用\"!A1","长期待摊费用")
B37: 32 | C37: 递延资产 | D37: 递延所得税资产 | E37: ='4-非流动资产汇总'!E22 | F37: ='4-非流动资产汇总'!F22 | G37: =F37-E37 | H37: =IF(E37=0,"",IF(E37<0,-G37/E37*100,G37/E37*100)) | J37: =E37-I37 | K37: =HYPERLINK("#\"4-17递延所得税资产\"!A1","递延所得税资产")
B38: 33 | C38: 其他非资 | D38: 其他非流动资产 | E38: ='4-非流动资产汇总'!E23 | F38: ='4-非流动资产汇总'!F23 | G38: =F38-E38 | H38: =IF(E38=0,"",IF(E38<0,-G38/E38*100,G38/E38*100)) | J38: =E38-I38 | K38: =HYPERLINK("#\"4-18其他非流动资产\"!A1","其他非流动资产")
B39: 34 | C39: 资产总计 | D39: 三、资产总计 | E39: =E6+E20 | F39: =F6+F20 | G39: =F39-E39 | H39: =IF(E39=0,"",IF(E39<0,-G39/E39*100,G39/E39*100)) | I39: =I6+I20 | J39: =E39-I39
B40: 35 | C40: 流债汇总 | D40: 四、流动负债合计 | E40: =SUM(E41:E53) | F40: =SUM(F41:F53) | G40: =F40-E40 | H40: =IF(E40=0,"",IF(E40<0,-G40/E40*100,G40/E40*100)) | I40: =SUM(I41:I53) | J40: =E40-I40
B41: 36 | C41: 短期借款 | D41: 短期借款 | E41: ='5-流动负债汇总'!E6 | F41: ='5-流动负债汇总'!F6 | G41: =F41-E41 | H41: =IF(E41=0,"",IF(E41<0,-G41/E41*100,G41/E41*100)) | J41: =E41-I41 | K41: =HYPERLINK("#\"5-1短期借款\"!A1","短期借款")
B42: 37 | C42: 交融负债 | D42: 交易性金融负债 | E42: ='5-流动负债汇总'!E7 | F42: ='5-流动负债汇总'!F7 | G42: =F42-E42 | H42: =IF(E42=0,"",IF(E42<0,-G42/E42*100,G42/E42*100)) | J42: =E42-I42 | K42: =HYPERLINK("#\"5-2交易性金融负债\"!A1","交易性金融负债")
B43: 38 | C43: 衍金负债 | D43: 衍生金融负债 | E43: ='5-流动负债汇总'!E8 | F43: ='5-流动负债汇总'!F8 | G43: =F43-E43 | H43: =IF(E43=0,"",IF(E43<0,-G43/E43*100,G43/E43*100)) | J43: =E43-I43 | K43: =HYPERLINK("#\"5-3衍生金融负债\"!A1","衍生金融负债")
B44: 39 | C44: 应付票据 | D44: 应付票据 | E44: ='5-流动负债汇总'!E9 | F44: ='5-流动负债汇总'!F9 | G44: =F44-E44 | H44: =IF(E44=0,"",IF(E44<0,-G44/E44*100,G44/E44*100)) | J44: =E44-I44 | K44: =HYPERLINK("#\"5-4应付票据\"!A1","应付票据")
B45: 40 | C45: 应付账款 | D45: 应付账款 | E45: ='5-流动负债汇总'!E10 | F45: ='5-流动负债汇总'!F10 | G45: =F45-E45 | H45: =IF(E45=0,"",IF(E45<0,-G45/E45*100,G45/E45*100)) | J45: =E45-I45 | K45: =HYPERLINK("#\"5-5应付账款\"!A1","应付账款")
B46: 41 | C46: 预收账款 | D46: 预收款项 | E46: ='5-流动负债汇总'!E11 | F46: ='5-流动负债汇总'!F11 | G46: =F46-E46 | H46: =IF(E46=0,"",IF(E46<0,-G46/E46*100,G46/E46*100)) | J46: =E46-I46 | K46: =HYPERLINK("#\"5-6预收款项\"!A1","预收款项")
B47: 42 | C47: 合同负债 | D47: 合同负债 | E47: ='5-流动负债汇总'!E12 | F47: ='5-流动负债汇总'!F12 | G47: =F47-E47 | H47: =IF(E47=0,"",IF(E47<0,-G47/E47*100,G47/E47*100)) | J47: =E47-I47 | K47: =HYPERLINK("#\"5-7合同负债\"!A1","合同负债")
B48: 43 | C48: 应付薪酬 | D48: 应付职工薪酬 | E48: ='5-流动负债汇总'!E13 | F48: ='5-流动负债汇总'!F13 | G48: =F48-E48 | H48: =IF(E48=0,"",IF(E48<0,-G48/E48*100,G48/E48*100)) | J48: =E48-I48 | K48: =HYPERLINK("#\"5-8应付职工薪酬\"!A1","应付职工薪酬")
B49: 44 | C49: 应交税费 | D49: 应交税费 | E49: ='5-流动负债汇总'!E14 | F49: ='5-流动负债汇总'!F14 | G49: =F49-E49 | H49: =IF(E49=0,"",IF(E49<0,-G49/E49*100,G49/E49*100)) | J49: =E49-I49 | K49: =HYPERLINK("#\"5-9应交税费\"!A1","应交税费")
B50: 45 | C50: 其付汇总 | D50: 其他应付款 | E50: ='5-流动负债汇总'!E15 | F50: ='5-流动负债汇总'!F15 | G50: =F50-E50 | H50: =IF(E50=0,"",IF(E50<0,-G50/E50*100,G50/E50*100)) | J50: =E50-I50 | K50: =HYPERLINK("#\"5-10其他应付款汇总表\"!A1","其他应付款")
B51: 46 | C51: 持有待债 | D51: 持有待售负债 | E51: ='5-流动负债汇总'!E16 | F51: ='5-流动负债汇总'!F16 | G51: =F51-E51 | H51: =IF(E51=0,"",IF(E51<0,-G51/E51*100,G51/E51*100)) | J51: =E51-I51 | K51: =HYPERLINK("#\"5-11持有待售负债\"!A1","持有待售负债")
B52: 47 | C52: 到期非债 | D52: 一年内到期的非流动负债 | E52: ='5-流动负债汇总'!E17 | F52: ='5-流动负债汇总'!F17 | G52: =F52-E52 | H52: =IF(E52=0,"",IF(E52<0,-G52/E52*100,G52/E52*100)) | J52: =E52-I52 | K52: =HYPERLINK("#\"5-12一年到期非流动负债\"!A1","一年内到期的非流动负债")
B53: 48 | C53: 其他流债 | D53: 其他流动负债 | E53: ='5-流动负债汇总'!E18 | F53: ='5-流动负债汇总'!F18 | G53: =F53-E53 | H53: =IF(E53=0,"",IF(E53<0,-G53/E53*100,G53/E53*100)) | J53: =E53-I53 | K53: =HYPERLINK("#\"5-13其他流动负债\"!A1","其他流动负债")
B54: 49 | C54: 非债汇总 | D54: 五、非流动负债合计 | E54: =SUM(E55:E63) | F54: =SUM(F55:F63) | G54: =F54-E54 | H54: =IF(E54=0,"",IF(E54<0,-G54/E54*100,G54/E54*100)) | I54: =SUM(I55:I63) | J54: =E54-I54
B55: 50 | C55: 长期借款 | D55: 长期借款 | E55: ='6-非流动负债汇总'!E6 | F55: ='6-非流动负债汇总'!F6 | G55: =F55-E55 | H55: =IF(E55=0,"",IF(E55<0,-G55/E55*100,G55/E55*100)) | J55: =E55-I55 | K55: =HYPERLINK("#\"6-1长期借款\"!A1","长期借款")
B56: 51 | C56: 应付债券 | D56: 应付债券 | E56: ='6-非流动负债汇总'!E7 | F56: ='6-非流动负债汇总'!F7 | G56: =F56-E56 | H56: =IF(E56=0,"",IF(E56<0,-G56/E56*100,G56/E56*100)) | J56: =E56-I56 | K56: =HYPERLINK("#\"6-2应付债券\"!A1","应付债券")
B57: 52 | C57: 租赁负债 | D57: 租赁负债 | E57: ='6-非流动负债汇总'!E8 | F57: ='6-非流动负债汇总'!F8 | G57: =F57-E57 | H57: =IF(E57=0,"",IF(E57<0,-G57/E57*100,G57/E57*100)) | J57: =E57-I57 | K57: =HYPERLINK("#\"6-3租赁负债\"!A1","租赁负债")
B58: 53 | C58: 长期应付 | D58: 长期应付款 | E58: ='6-非流动负债汇总'!E9 | F58: ='6-非流动负债汇总'!F9 | G58: =F58-E58 | H58: =IF(E58=0,"",IF(E58<0,-G58/E58*100,G58/E58*100)) | J58: =E58-I58 | K58: =HYPERLINK("#\"6-4长期应付款\"!A1","长期应付款")
B59: 54 | C59: 专项应付 | D59: 长期应付职工薪酬 | E59: ='6-非流动负债汇总'!E10 | F59: ='6-非流动负债汇总'!F10 | G59: =F59-E59 | H59: =IF(E59=0,"",IF(E59<0,-G59/E59*100,G59/E59*100)) | J59: =E59-I59 | K59: =HYPERLINK("#\"6-5长期应付职工薪酬\"!A1","长期应付职工薪酬")
B60: 55 | C60: 预计负债 | D60: 预计负债 | E60: ='6-非流动负债汇总'!E11 | F60: ='6-非流动负债汇总'!F11 | G60: =F60-E60 | H60: =IF(E60=0,"",IF(E60<0,-G60/E60*100,G60/E60*100)) | J60: =E60-I60 | K60: =HYPERLINK("#\"6-6预计负债\"!A1","预计负债")
B61: 56 | C61: 递延收益 | D61: 递延收益 | E61: ='6-非流动负债汇总'!E12 | F61: ='6-非流动负债汇总'!F12 | G61: =F61-E61 | H61: =IF(E61=0,"",IF(E61<0,-G61/E61*100,G61/E61*100)) | J61: =E61-I61 | K61: =HYPERLINK("#\"6-7递延收益\"!A1","递延收益")
B62: 57 | C62: 递延负债 | D62: 递延所得税负债 | E62: ='6-非流动负债汇总'!E13 | F62: ='6-非流动负债汇总'!F13 | G62: =F62-E62 | H62: =IF(E62=0,"",IF(E62<0,-G62/E62*100,G62/E62*100)) | J62: =E62-I62 | K62: =HYPERLINK("#\"6-8递延所得税负债\"!A1","递延所得税负债")
B63: 58 | C63: 其他非债 | D63: 其他非流动负债 | E63: ='6-非流动负债汇总'!E14 | F63: ='6-非流动负债汇总'!F14 | G63: =F63-E63 | H63: =IF(E63=0,"",IF(E63<0,-G63/E63*100,G63/E63*100)) | J63: =E63-I63 | K63: =HYPERLINK("#\"6-9其他非流动负债\"!A1","其他非流动负债")
B64: 59 | C64: 负债总计 | D64: 六、负债总计 | E64: =E40+E54 | F64: =F40+F54 | G64: =F64-E64 | H64: =IF(E64=0,"",IF(E64<0,-G64/E64*100,G64/E64*100)) | I64: =I40+I54 | J64: =E64-I64
A65: 合计1 | B65: 60 | C65: 股东权益 | D65: 七、净资产（所有者权益） | E65: =E39-E64 | F65: =F39-F64 | G65: =F65-E65 | H65: =IF(E65=0,"",IF(E65<0,-G65/E65*100,G65/E65*100)) | I65: =I39-I64 | J65: =E65-I65
H66: 评估机构：天源资产评估有限公司
H68: 报表净资产
H69: 校验 | I69: =IF(I68=0,"",IF(ABS(I65-I68)<0.005,"一致","差异:"&TEXT(I65-I68,"#,##0.00")))

Sheet 3-流动资产汇总
B1: 流动资产评估汇总表
B2: ='2-分类汇总'!B2
H3: 表3
B4: ='2-分类汇总'!B4 | H4: ='2-分类汇总'!H4
B5: 编号 | C5: 项目编号 | D5: 科目名称 | E5: 账面价值 | F5: 评估价值 | G5: 增值额 | H5: 增值率%
B6: 3-1 | C6: 货币汇总 | D6: 货币资金 | E6: ='3-1货币资金汇总表'!E23 | F6: ='3-1货币资金汇总表'!F23 | G6: =F6-E6 | H6: =IF(E6=0,"",G6/E6*100)
B7: 3-2 | C7: 交融汇总 | D7: 交易性金融资产 | E7: ='3-2交易性金融资产汇总'!E24 | F7: ='3-2交易性金融资产汇总'!F24 | G7: =F7-E7 | H7: =IF(E7=0,"",G7/E7*100)
B8: 3-3 | C8: 衍金资产 | D8: 衍生金融资产 | E8: ='3-3衍生金融资产'!F27 | F8: ='3-3衍生金融资产'!G27 | G8: =F8-E8 | H8: =IF(E8=0,"",G8/E8*100)
B9: 3-4 | C9: 应收票据 | D9: 应收票据 | E9: ='3-4应收票据'!G29 | F9: ='3-4应收票据'!H29 | G9: =F9-E9 | H9: =IF(E9=0,"",G9/E9*100)
B10: 3-5 | C10: 应收账款 | D10: 应收账款 | E10: ='3-5应收账款'!J29 | F10: ='3-5应收账款'!K29 | G10: =F10-E10 | H10: =IF(E10=0,"",G10/E10*100)
B11: 3-6 | C11: 应收融资 | D11: 应收款项融资 | E11: ='3-6应收款项融资'!J29 | F11: ='3-6应收款项融资'!K29 | G11: =F11-E11 | H11: =IF(E11=0,"",G11/E11*100)
B12: 3-7 | C12: 预付账款 | D12: 预付款项 | E12: ='3-7预付款项'!J28 | F12: ='3-7预付款项'!K28 | G12: =F12-E12 | H12: =IF(E12=0,"",G12/E12*100)
B13: 3-8 | C13: 其他应收 | D13: 其他应收款 | E13: ='3-8其他应收款汇总'!E25 | F13: ='3-8其他应收款汇总'!F25 | G13: =F13-E13 | H13: =IF(E13=0,"",G13/E13*100)
B14: 3-9 | C14: 存货汇总 | D14: 存货 | E14: ='3-9存货汇总'!E23 | F14: ='3-9存货汇总'!F23 | G14: =F14-E14 | H14: =IF(E14=0,"",G14/E14*100)
B15: 3-10 | C15: 合同资产 | D15: 合同资产 | E15: ='3-10合同资产'!F29 | F15: ='3-10合同资产'!G29 | G15: =F15-E15 | H15: =IF(E15=0,"",G15/E15*100)
B16: 3-11 | C16: 持有待资 | D16: 持有待售资产 | E16: ='3-11持有待售资产'!I30 | F16: ='3-11持有待售资产'!J30 | G16: =F16-E16 | H16: =IF(E16=0,"",G16/E16*100)
B17: 3-12 | C17: 到期非流 | D17: 一年内到期的非流动资产 | E17: ='3-12一年到期非流动资产'!F28 | F17: ='3-12一年到期非流动资产'!G28 | G17: =F17-E17 | H17: =IF(E17=0,"",G17/E17*100)
B18: 3-13 | C18: 其他流资 | D18: 其他流动资产 | E18: ='3-13其他流动资产'!G28 | F18: ='3-13其他流动资产'!H28 | G18: =F18-E18 | H18: =IF(E18=0,"",G18/E18*100)
A26: 合计1 | C26: 流资汇总 | D26: 流动资产合计 | E26: =SUM(E6:E25) | F26: =SUM(F6:F25) | G26: =F26-E26 | H26: =IF(E26=0,"",G26/E26*100)

Sheet 3-1货币资金汇总表
B1: 货币资金评估汇总表
B2: ='2-分类汇总'!B2
H3: 表3-1
B4: ='2-分类汇总'!B4 | I4: ='2-分类汇总'!H4
B5: 编号 | C5: 项目编号 | D5: 科目名称 | E5: 账面价值 | F5: 评估价值 | G5: 增值额 | H5: 增值率% | I5: 备注
B6: 3-1-1 | C6: 货币现金 | D6: 现金 | E6: ='3-1-1现金'!G27 | F6: ='3-1-1现金'!H27 | G6: =F6-E6 | H6: =IF(E6=0,"",G6/E6*100)
B7: 3-1-2 | C7: 货币银行 | D7: 银行存款 | E7: ='3-1-2银行存款'!H29 | F7: ='3-1-2银行存款'!I29 | G7: =F7-E7 | H7: =IF(E7=0,"",G7/E7*100)
B8: 3-1-3 | C8: 其他货币 | D8: 其他货币资金 | E8: ='3-1-3其他货币资金'!H31 | F8: ='3-1-3其他货币资金'!I31 | G8: =F8-E8 | H8: =IF(E8=0,"",G8/E8*100)
A23: 合计1 | C23: 货币汇总 | D23: 合 计 | E23: =SUM(E6:E22) | F23: =SUM(F6:F22) | G23: =F23-E23 | H23: =IF(E23=0,"",G23/E23*100)

Sheet 3-1-1现金
A1: 表头区域 | B1: 货币资金—现金评估明细表
A2: 表头区域 | B2: ='2-分类汇总'!B2
A3: 表头区域 | J3: 表3-1-1
A4: 表头区域 | B4: ='2-分类汇总'!B4 | K4: ='2-分类汇总'!H4
A5: 检索表头 | B5: 序号 | C5: 存放部门（单位) | D5: 币种 | E5: 外币账面金额 | F5: 评估基准日汇率 | G5: 账面价值 | H5: 评估价值 | I5: 增值额 | J5: 增值率% | K5: 备注
I6: =H6-G6 | J6: =IF(G6=0,"",I6/G6*100)
I7: =H7-G7 | J7: =IF(G7=0,"",I7/G7*100)
I8: =H8-G8 | J8: =IF(G8=0,"",I8/G8*100)
I9: =H9-G9 | J9: =IF(G9=0,"",I9/G9*100)
I10: =H10-G10 | J10: =IF(G10=0,"",I10/G10*100)
I11: =H11-G11 | J11: =IF(G11=0,"",I11/G11*100)
I12: =H12-G12 | J12: =IF(G12=0,"",I12/G12*100)
I13: =H13-G13 | J13: =IF(G13=0,"",I13/G13*100)
I14: =H14-G14 | J14: =IF(G14=0,"",I14/G14*100)
I15: =H15-G15 | J15: =IF(G15=0,"",I15/G15*100)
I16: =H16-G16 | J16: =IF(G16=0,"",I16/G16*100)
I17: =H17-G17 | J17: =IF(G17=0,"",I17/G17*100)
... I26: =H26-G26 | J26: =IF(G26=0,"",I26/G26*100)
A27: 合计1 | B27: 合 计 | G27: =ROUND(SUM(G6:G26),2) | H27: =ROUND(SUM(H6:H26),2) | I27: =H27-G27 | J27: =IF(G27=0,"",I27/G27*100)

Sheet 3-1-2银行存款
A1: 表头区域 | B1: 货币资金—银行存款评估明细表
A2: 表头区域 | B2: ='2-分类汇总'!B2
A3: 表头区域 | K3: 表3-1-2
A4: 表头区域 | B4: ='2-分类汇总'!B4 | L4: ='2-分类汇总'!H4
A5: 检索表头 | B5: 序号 | C5: 开户银行 | D5: 账号 | E5: 币种 | F5: 外币账面金额 | G5: 评估基准日汇率 | H5: 账面价值 | I5: 评估价值 | J5: 增值额 | K5: 增值率% | L5: 备注
J6: =I6-H6 | K6: =IF(H6=0,"",J6/H6*100)
J7: =I7-H7 | K7: =IF(H7=0,"",J7/H7*100)
J8: =I8-H8 | K8: =IF(H8=0,"",J8/H8*100)
J9: =I9-H9 | K9: =IF(H9=0,"",J9/H9*100)
J10: =I10-H10 | K10: =IF(H10=0,"",J10/H10*100)
J11: =I11-H11 | K11: =IF(H11=0,"",J11/H11*100)
J12: =I12-H12 | K12: =IF(H12=0,"",J12/H12*100)
J13: =I13-H13 | K13: =IF(H13=0,"",J13/H13*100)
J14: =I14-H14 | K14: =IF(H14=0,"",J14/H14*100)
J15: =I15-H15 | K15: =IF(H15=0,"",J15/H15*100)
J16: =I16-H16 | K16: =IF(H16=0,"",J16/H16*100)
J17: =I17-H17 | K17: =IF(H17=0,"",J17/H17*100)
... J28: =I28-H28 | K28: =IF(H28=0,"",J28/H28*100)
A29: 合计1 | B29: 合 计 | H29: =ROUND(SUM(H6:H28),2) | I29: =ROUND(SUM(I6:I28),2) | J29: =I29-H29 | K29: =IF(H29=0,"",J29/H29*100)

Sheet 3-1-3其他货币资金
A1: 表头区域 | B1: 货币资金—其他货币资金评估明细表
A2: 表头区域 | B2: ='2-分类汇总'!B2
A3: 表头区域 | L3: 表3-1-3
A4: 表头区域 | B4: ='2-分类汇总'!B4 | L4: ='2-分类汇总'!H4
A5: 检索表头 | B5: 序号 | C5: 名称及内容 | D5: 用途 | E5: 币种 | F5: 外币账面金额 | G5: 评估基准日汇率 | H5: 账面价值 | I5: 评估价值 | J5: 增值额 | K5: 增值率% | L5: 备注
J6: =I6-H6 | K6: =IF(H6=0,"",J6/H6*100)
J7: =I7-H7 | K7: =IF(H7=0,"",J7/H7*100)
J8: =I8-H8 | K8: =IF(H8=0,"",J8/H8*100)
J9: =I9-H9 | K9: =IF(H9=0,"",J9/H9*100)
J10: =I10-H10 | K10: =IF(H10=0,"",J10/H10*100)
J11: =I11-H11 | K11: =IF(H11=0,"",J11/H11*100)
J12: =I12-H12 | K12: =IF(H12=0,"",J12/H12*100)
J13: =I13-H13 | K13: =IF(H13=0,"",J13/H13*100)
J14: =I14-H14 | K14: =IF(H14=0,"",J14/H14*100)
J15: =I15-H15 | K15: =IF(H15=0,"",J15/H15*100)
J16: =I16-H16 | K16: =IF(H16=0,"",J16/H16*100)
J17: =I17-H17 | K17: =IF(H17=0,"",J17/H17*100)
... J30: =I30-H30 | K30: =IF(H30=0,"",J30/H30*100)
A31: 合计1 | B31: 合 计 | H31: =ROUND(SUM(H6:H30),2) | I31: =ROUND(SUM(I6:I30),2) | J31: =I31-H31 | K31: =IF(H31=0,"",J31/H31*100)

Sheet 3-2交易性金融资产汇总
B1: 交易性金融资产评估汇总表
B2: ='2-分类汇总'!B2
H3: 表3-2
B4: ='2-分类汇总'!B4 | H4: ='2-分类汇总'!H4
B5: 编号 | C5: 项目编号 | D5: 科目名称 | E5: 账面价值 | F5: 评估价值 | G5: 增值额 | H5: 增值率%
B6: 3-2-1 | C6: 交融股票 | D6: 交易性金融资产-股票投资 | E6: ='3-2-1-股票'!H29 | F6: ='3-2-1-股票'!J29 | G6: =F6-E6 | H6: =IF(E6=0,"",G6/E6*100)
B7: 3-2-2 | C7: 交融债券 | D7: 交易性金融资产-债券投资 | E7: ='3-2-2-债券'!I29 | F7: ='3-2-2-债券'!J29 | G7: =F7-E7 | H7: =IF(E7=0,"",G7/E7*100)
B8: 3-2-3 | C8: 交融基金 | D8: 交易性金融资产-基金投资 | E8: ='3-2-3-基金'!H31 | F8: ='3-2-3-基金'!J31 | G8: =F8-E8 | H8: =IF(E8=0,"",G8/E8*100)
A24: 合计1 | C24: 交融汇总 | D24: 合 计 | E24: =SUM(E6:E23) | F24: =SUM(F6:F23) | G24: =F24-E24 | H24: =IF(E24=0,"",G24/E24*100)

Sheet 3-2-1-股票
A1: 表头区域 | B1: 交易性金融资产—股票投资评估明细表
A2: 表头区域 | B2: ='2-分类汇总'!B2
A3: 表头区域 | L3: 表3-2-1
A4: 表头区域 | B4: ='2-分类汇总'!B4 | M4: ='2-分类汇总'!H4
A5: 检索表头 | B5: 序号 | C5: 被投资单位名称 | D5: 股票名称 | E5: 投资日期 | F5: 持股数量 | G5: 成 本 | H5: 账面价值 | I5: 基准日收盘价元/股 | J5: 评估价值 | K5: 增值额 | L5: 增值率% | M5: 备注
K6: =J6-H6 | L6: =IF(H6=0,"",K6/H6*100)
K7: =J7-H7 | L7: =IF(H7=0,"",K7/H7*100)
K8: =J8-H8 | L8: =IF(H8=0,"",K8/H8*100)
K9: =J9-H9 | L9: =IF(H9=0,"",K9/H9*100)
K10: =J10-H10 | L10: =IF(H10=0,"",K10/H10*100)
K11: =J11-H11 | L11: =IF(H11=0,"",K11/H11*100)
K12: =J12-H12 | L12: =IF(H12=0,"",K12/H12*100)
K13: =J13-H13 | L13: =IF(H13=0,"",K13/H13*100)
K14: =J14-H14 | L14: =IF(H14=0,"",K14/H14*100)
K15: =J15-H15 | L15: =IF(H15=0,"",K15/H15*100)
K16: =J16-H16 | L16: =IF(H16=0,"",K16/H16*100)
K17: =J17-H17 | L17: =IF(H17=0,"",K17/H17*100)
... K28: =J28-H28 | L28: =IF(H28=0,"",K28/H28*100)
A29: 合计1 | B29: 合 计 | G29: =ROUND(SUM(G6:G28),2) | H29: =ROUND(SUM(H6:H28),2) | J29: =ROUND(SUM(J6:J28),2) | K29: =J29-H29 | L29: =IF(H29=0,"",K29/H29*100)

Sheet 3-2-2-债券
A1: 表头区域 | B1: 交易性金融资产—债券投资评估明细表
A2: 表头区域 | B2: ='2-分类汇总'!B2
A3: 表头区域 | L3: 表3-2-2
A4: 表头区域 | B4: ='2-分类汇总'!B4 | M4: ='2-分类汇总'!H4
A5: 检索表头 | B5: 序号 | C5: 被投资单位名称 | D5: 债券名称 | E5: 发行日期 | F5: 投资日期 | G5: 票面利率% | H5: 成本 | I5: 账面价值 | J5: 评估价值 | K5: 增值额 | L5: 增值率% | M5: 备注
K6: =J6-I6 | L6: =IF(I6=0,"",K6/I6*100)
K7: =J7-I7 | L7: =IF(I7=0,"",K7/I7*100)
K8: =J8-I8 | L8: =IF(I8=0,"",K8/I8*100)
K9: =J9-I9 | L9: =IF(I9=0,"",K9/I9*100)
K10: =J10-I10 | L10: =IF(I10=0,"",K10/I10*100)
K11: =J11-I11 | L11: =IF(I11=0,"",K11/I11*100)
K12: =J12-I12 | L12: =IF(I12=0,"",K12/I12*100)
K13: =J13-I13 | L13: =IF(I13=0,"",K13/I13*100)
K14: =J14-I14 | L14: =IF(I14=0,"",K14/I14*100)
K15: =J15-I15 | L15: =IF(I15=0,"",K15/I15*100)
K16: =J16-I16 | L16: =IF(I16=0,"",K16/I16*100)
K17: =J17-I17 | L17: =IF(I17=0,"",K17/I17*100)
... K28: =J28-I28 | L28: =IF(I28=0,"",K28/I28*100)
A29: 合计1 | B29: 合 计 | I29: =ROUND(SUM(I6:I28),2) | J29: =ROUND(SUM(J6:J28),2) | K29: =J29-I29 | L29: =IF(I29=0,"",K29/I29*100)

Sheet 3-2-3-基金
A1: 表头区域 | B1: 交易性金融资产—基金投资评估明细表
A2: 表头区域 | B2: ='2-分类汇总'!B2
A3: 表头区域 | L3: 表3-2-3
A4: 表头区域 | B4: ='2-分类汇总'!B4 | M4: ='2-分类汇总'!H4
A5: 检索表头 | B5: 序号 | C5: 基金发行单位 | D5: 基金名称 | E5: 基金类型 | F5: 投资日期 | G5: 成本 | H5: 账面价值 | I5: 基准日净值/份 | J5: 评估价值 | K5: 增值额 | L5: 增值率% | M5: 备注
K6: =J6-H6 | L6: =IF(H6=0,"",K6/H6*100)
K7: =J7-H7 | L7: =IF(H7=0,"",K7/H7*100)
K8: =J8-H8 | L8: =IF(H8=0,"",K8/H8*100)
K9: =J9-H9 | L9: =IF(H9=0,"",K9/H9*100)
K10: =J10-H10 | L10: =IF(H10=0,"",K10/H10*100)
K11: =J11-H11 | L11: =IF(H11=0,"",K11/H11*100)
K12: =J12-H12 | L12: =IF(H12=0,"",K12/H12*100)
K13: =J13-H13 | L13: =IF(H13=0,"",K13/H13*100)
K14: =J14-H14 | L14: =IF(H14=0,"",K14/H14*100)
K15: =J15-H15 | L15: =IF(H15=0,"",K15/H15*100)
K16: =J16-H16 | L16: =IF(H16=0,"",K16/H16*100)
K17: =J17-H17 | L17: =IF(H17=0,"",K17/H17*100)
... K30: =J30-H30 | L30: =IF(H30=0,"",K30/H30*100)
A31: 合计1 | B31: 合 计 | H31: =ROUND(SUM(H6:H30),2) | J31: =ROUND(SUM(J6:J30),2) | K31: =J31-H31 | L31: =IF(H31=0,"",K31/H31*100)

Sheet 3-3衍生金融资产
A1: 表头区域 | B1: 衍生金融资产评估明细表
A2: 表头区域 | B2: ='2-分类汇总'!B2
A3: 表头区域 | J3: 表3-3
A4: 表头区域 | B4: ='2-分类汇总'!B4 | J4: ='2-分类汇总'!H4
A5: 检索表头 | B5: 序号 | C5: 被投资项目名称 | D5: 投资日期 | E5: 成本 | F5: 账面价值 | G5: 评估价值 | H5: 增值额 | I5: 增值率% | J5: 备注
H6: =G6-F6 | I6: =IF(F6=0,"",H6/F6*100)
H7: =G7-F7 | I7: =IF(F7=0,"",H7/F7*100)
H8: =G8-F8 | I8: =IF(F8=0,"",H8/F8*100)
H9: =G9-F9 | I9: =IF(F9=0,"",H9/F9*100)
H10: =G10-F10 | I10: =IF(F10=0,"",H10/F10*100)
H11: =G11-F11 | I11: =IF(F11=0,"",H11/F11*100)
H12: =G12-F12 | I12: =IF(F12=0,"",H12/F12*100)
H13: =G13-F13 | I13: =IF(F13=0,"",H13/F13*100)
H14: =G14-F14 | I14: =IF(F14=0,"",H14/F14*100)
H15: =G15-F15 | I15: =IF(F15=0,"",H15/F15*100)
H16: =G16-F16 | I16: =IF(F16=0,"",H16/F16*100)
H17: =G17-F17 | I17: =IF(F17=0,"",H17/F17*100)
... H26: =G26-F26 | I26: =IF(F26=0,"",H26/F26*100)
A27: 合计1 | B27: 合 计 | E27: =SUM(E6:E26) | F27: =SUM(F6:F26) | G27: =SUM(G6:G26) | H27: =G27-F27 | I27: =IF(F27=0,"",H27/F27*100)

Sheet 3-4应收票据
A1: 表头区域 | B1: 应收票据评估明细表
A2: 表头区域 | B2: ='2-分类汇总'!B2
A3: 表头区域 | K3: 表3-4
A4: 表头区域 | B4: ='2-分类汇总'!B4 | K4: ='2-分类汇总'!H4
A5: 检索表头 | B5: 序号 | C5: 户名（结算对象) | D5: 出票日期 | E5: 到期日期 | F5: 票面利率% | G5: 账面价值 | H5: 评估价值 | I5: 增值额 | J5: 增值率% | K5: 备注
I6: =H6-G6 | J6: =IF(G6=0,"",I6/G6*100)
I7: =H7-G7 | J7: =IF(G7=0,"",I7/G7*100)
I8: =H8-G8 | J8: =IF(G8=0,"",I8/G8*100)
I9: =H9-G9 | J9: =IF(G9=0,"",I9/G9*100)
I10: =H10-G10 | J10: =IF(G10=0,"",I10/G10*100)
I11: =H11-G11 | J11: =IF(G11=0,"",I11/G11*100)
I12: =H12-G12 | J12: =IF(G12=0,"",I12/G12*100)
I13: =H13-G13 | J13: =IF(G13=0,"",I13/G13*100)
I14: =H14-G14 | J14: =IF(G14=0,"",I14/G14*100)
I15: =H15-G15 | J15: =IF(G15=0,"",I15/G15*100)
I16: =H16-G16 | J16: =IF(G16=0,"",I16/G16*100)
I17: =H17-G17 | J17: =IF(G17=0,"",I17/G17*100)
... I25: =H25-G25 | J25: =IF(G25=0,"",I25/G25*100)
A26: 合计1 | B26: 合 计 | G26: =ROUND(SUM(G6:G25),2) | H26: =ROUND(SUM(H6:H25),2) | I26: =H26-G26 | J26: =IF(G26=0,"",I26/G26*100)
A27: 坏账准备 | B27: 减：应收票据坏账准备 | I27: =H27-G27 | J27: =IF(G27=0,"",I27/G27*100)
A28: 预计损失 | B28: 减：应收票据预计损失 | I28: =H28-G28 | J28: =IF(G28=0,"",I28/G28*100)
A29: 合计2 | B29: 合 计 | G29: =ROUND(G26-G27,2) | H29: =ROUND(H26-H28,2) | I29: =H29-G29 | J29: =IF(G29=0,"",I29/G29*100)

Sheet 3-5应收账款
A1: 表头区域 | B1: 应收账款评估明细表
A2: 表头区域 | B2: ='2-分类汇总'!B2
A3: 表头区域 | N3: 表3-5
A4: 表头区域 | B4: ='2-分类汇总'!B4 | N4: ='2-分类汇总'!H4
A5: 检索表头 | B5: 序号 | C5: 欠款单位名称（结算对象) | D5: 业务内容 | E5: 发生日期 | F5: 账龄 | G5: 币种 | H5: 外币账面金额 | I5: 评估基准日汇率 | J5: 账面价值 | K5: 评估价值 | L5: 增值额 | M5: 增值率% | N5: 备注
F6: =IF(E6="","",LOOKUP(DATEDIF(E6,评估基准日,"y"),公式数据表!$C$7:$C$10,公式数据表!$B$7:$B$10)) | L6: =K6-J6 | M6: =IF(J6=0,"",L6/J6*100)
F7: =IF(E7="","",LOOKUP(DATEDIF(E7,评估基准日,"y"),公式数据表!$C$7:$C$10,公式数据表!$B$7:$B$10)) | L7: =K7-J7 | M7: =IF(J7=0,"",L7/J7*100)
F8: =IF(E8="","",LOOKUP(DATEDIF(E8,评估基准日,"y"),公式数据表!$C$7:$C$10,公式数据表!$B$7:$B$10)) | L8: =K8-J8 | M8: =IF(J8=0,"",L8/J8*100)
F9: =IF(E9="","",LOOKUP(DATEDIF(E9,评估基准日,"y"),公式数据表!$C$7:$C$10,公式数据表!$B$7:$B$10)) | L9: =K9-J9 | M9: =IF(J9=0,"",L9/J9*100)
F10: =IF(E10="","",LOOKUP(DATEDIF(E10,评估基准日,"y"),公式数据表!$C$7:$C$10,公式数据表!$B$7:$B$10)) | L10: =K10-J10 | M10: =IF(J10=0,"",L10/J10*100)
F11: =IF(E11="","",LOOKUP(DATEDIF(E11,评估基准日,"y"),公式数据表!$C$7:$C$10,公式数据表!$B$7:$B$10)) | L11: =K11-J11 | M11: =IF(J11=0,"",L11/J11*100)
F12: =IF(E12="","",LOOKUP(DATEDIF(E12,评估基准日,"y"),公式数据表!$C$7:$C$10,公式数据表!$B$7:$B$10)) | L12: =K12-J12 | M12: =IF(J12=0,"",L12/J12*100)
F13: =IF(E13="","",LOOKUP(DATEDIF(E13,评估基准日,"y"),公式数据表!$C$7:$C$10,公式数据表!$B$7:$B$10)) | L13: =K13-J13 | M13: =IF(J13=0,"",L13/J13*100)
F14: =IF(E14="","",LOOKUP(DATEDIF(E14,评估基准日,"y"),公式数据表!$C$7:$C$10,公式数据表!$B$7:$B$10)) | L14: =K14-J14 | M14: =IF(J14=0,"",L14/J14*100)
F15: =IF(E15="","",LOOKUP(DATEDIF(E15,评估基准日,"y"),公式数据表!$C$7:$C$10,公式数据表!$B$7:$B$10)) | L15: =K15-J15 | M15: =IF(J15=0,"",L15/J15*100)
F16: =IF(E16="","",LOOKUP(DATEDIF(E16,评估基准日,"y"),公式数据表!$C$7:$C$10,公式数据表!$B$7:$B$10)) | L16: =K16-J16 | M16: =IF(J16=0,"",L16/J16*100)
F17: =IF(E17="","",LOOKUP(DATEDIF(E17,评估基准日,"y"),公式数据表!$C$7:$C$10,公式数据表!$B$7:$B$10)) | L17: =K17-J17 | M17: =IF(J17=0,"",L17/J17*100)
... F25: =IF(E25="","",LOOKUP(DATEDIF(E25,评估基准日,"y"),公式数据表!$C$7:$C$10,公式数据表!$B$7:$B$10)) | L25: =K25-J25 | M25: =IF(J25=0,"",L25/J25*100)
A26: 合计1 | B26: 合 计 | H26: =ROUND(SUM(H6:H25),2) | J26: =ROUND(SUM(J6:J25),2) | K26: =ROUND(SUM(K6:K25),2) | L26: =K26-J26 | M26: =IF(J26=0,"",L26/J26*100)
A27: 坏账准备 | B27: 减：应收账款坏账准备 | L27: =K27-J27 | M27: =IF(J27=0,"",L27/J27*100)
A28: 预计损失 | B28: 减：应收账款预计损失 | L28: =K28-J28 | M28: =IF(J28=0,"",L28/J28*100)
A29: 合计2 | B29: 合 计 | H29: =ROUND(H26-H27,2) | J29: =ROUND(J26-J27,2) | K29: =ROUND(K26-K28,2) | L29: =K29-J29 | M29: =IF(J29=0,"",L29/J29*100)

Sheet 3-6应收款项融资
A1: 表头区域 | B1: 应收款项融资评估明细表
A2: 表头区域 | B2: ='2-分类汇总'!B2
A3: 表头区域 | N3: 表3-6
A4: 表头区域 | B4: ='2-分类汇总'!B4 | N4: ='2-分类汇总'!H4
A5: 检索表头 | B5: 序号 | C5: 欠款单位名称（结算对象) | D5: 业务内容 | E5: 发生日期 | F5: 账龄 | G5: 币种 | H5: 外币账面金额 | I5: 评估基准日汇率 | J5: 账面价值 | K5: 评估价值 | L5: 增值额 | M5: 增值率% | N5: 备注
F6: =IF(E6="","",LOOKUP(DATEDIF(E6,评估基准日,"y"),公式数据表!$C$7:$C$10,公式数据表!$B$7:$B$10)) | L6: =K6-J6 | M6: =IF(J6=0,"",L6/J6*100)
F7: =IF(E7="","",LOOKUP(DATEDIF(E7,评估基准日,"y"),公式数据表!$C$7:$C$10,公式数据表!$B$7:$B$10)) | L7: =K7-J7 | M7: =IF(J7=0,"",L7/J7*100)
F8: =IF(E8="","",LOOKUP(DATEDIF(E8,评估基准日,"y"),公式数据表!$C$7:$C$10,公式数据表!$B$7:$B$10)) | L8: =K8-J8 | M8: =IF(J8=0,"",L8/J8*100)
F9: =IF(E9="","",LOOKUP(DATEDIF(E9,评估基准日,"y"),公式数据表!$C$7:$C$10,公式数据表!$B$7:$B$10)) | L9: =K9-J9 | M9: =IF(J9=0,"",L9/J9*100)
F10: =IF(E10="","",LOOKUP(DATEDIF(E10,评估基准日,"y"),公式数据表!$C$7:$C$10,公式数据表!$B$7:$B$10)) | L10: =K10-J10 | M10: =IF(J10=0,"",L10/J10*100)
F11: =IF(E11="","",LOOKUP(DATEDIF(E11,评估基准日,"y"),公式数据表!$C$7:$C$10,公式数据表!$B$7:$B$10)) | L11: =K11-J11 | M11: =IF(J11=0,"",L11/J11*100)
F12: =IF(E12="","",LOOKUP(DATEDIF(E12,评估基准日,"y"),公式数据表!$C$7:$C$10,公式数据表!$B$7:$B$10)) | L12: =K12-J12 | M12: =IF(J12=0,"",L12/J12*100)
F13: =IF(E13="","",LOOKUP(DATEDIF(E13,评估基准日,"y"),公式数据表!$C$7:$C$10,公式数据表!$B$7:$B$10)) | L13: =K13-J13 | M13: =IF(J13=0,"",L13/J13*100)
F14: =IF(E14="","",LOOKUP(DATEDIF(E14,评估基准日,"y"),公式数据表!$C$7:$C$10,公式数据表!$B$7:$B$10)) | L14: =K14-J14 | M14: =IF(J14=0,"",L14/J14*100)
F15: =IF(E15="","",LOOKUP(DATEDIF(E15,评估基准日,"y"),公式数据表!$C$7:$C$10,公式数据表!$B$7:$B$10)) | L15: =K15-J15 | M15: =IF(J15=0,"",L15/J15*100)
F16: =IF(E16="","",LOOKUP(DATEDIF(E16,评估基准日,"y"),公式数据表!$C$7:$C$10,公式数据表!$B$7:$B$10)) | L16: =K16-J16 | M16: =IF(J16=0,"",L16/J16*100)
F17: =IF(E17="","",LOOKUP(DATEDIF(E17,评估基准日,"y"),公式数据表!$C$7:$C$10,公式数据表!$B$7:$B$10)) | L17: =K17-J17 | M17: =IF(J17=0,"",L17/J17*100)
... F25: =IF(E25="","",LOOKUP(DATEDIF(E25,评估基准日,"y"),公式数据表!$C$7:$C$10,公式数据表!$B$7:$B$10)) | L25: =K25-J25 | M25: =IF(J25=0,"",L25/J25*100)
A26: 合计1 | B26: 合 计 | H26: =ROUND(SUM(H6:H25),2) | J26: =ROUND(SUM(J6:J25),2) | K26: =ROUND(SUM(K6:K25),2) | L26: =K26-J26 | M26: =IF(J26=0,"",L26/J26*100)
A27: 坏账准备 | B27: 减：应收账款坏账准备 | L27: =K27-J27 | M27: =IF(J27=0,"",L27/J27*100)
A28: 预计损失 | B28: 减：应收账款预计损失 | L28: =K28-J28 | M28: =IF(J28=0,"",L28/J28*100)
A29: 合计2 | B29: 合 计 | H29: =ROUND(H26-H27,2) | J29: =ROUND(J26-J27,2) | K29: =ROUND(K26-K28,2) | L29: =K29-J29 | M29: =IF(J29=0,"",L29/J29*100)

Sheet 3-7预付款项
A1: 表头区域 | B1: 预付款项评估明细表
A2: 表头区域 | B2: ='2-分类汇总'!B2
A3: 表头区域 | N3: 表3-7
A4: 表头区域 | B4: ='2-分类汇总'!B4 | N4: ='2-分类汇总'!H4
A5: 检索表头 | B5: 序号 | C5: 收款单位名称（结算对象) | D5: 业务内容 | E5: 发生日期 | F5: 账龄 | G5: 币种 | H5: 外币账面金额 | I5: 评估基准日汇率 | J5: 账面价值 | K5: 评估价值 | L5: 增值额 | M5: 增值率% | N5: 备注
F6: =IF(E6="","",LOOKUP(DATEDIF(E6,评估基准日,"y"),公式数据表!$C$7:$C$10,公式数据表!$B$7:$B$10)) | L6: =K6-J6 | M6: =IF(J6=0,"",L6/J6*100)
F7: =IF(E7="","",LOOKUP(DATEDIF(E7,评估基准日,"y"),公式数据表!$C$7:$C$10,公式数据表!$B$7:$B$10)) | L7: =K7-J7 | M7: =IF(J7=0,"",L7/J7*100)
F8: =IF(E8="","",LOOKUP(DATEDIF(E8,评估基准日,"y"),公式数据表!$C$7:$C$10,公式数据表!$B$7:$B$10)) | L8: =K8-J8 | M8: =IF(J8=0,"",L8/J8*100)
F9: =IF(E9="","",LOOKUP(DATEDIF(E9,评估基准日,"y"),公式数据表!$C$7:$C$10,公式数据表!$B$7:$B$10)) | L9: =K9-J9 | M9: =IF(J9=0,"",L9/J9*100)
F10: =IF(E10="","",LOOKUP(DATEDIF(E10,评估基准日,"y"),公式数据表!$C$7:$C$10,公式数据表!$B$7:$B$10)) | L10: =K10-J10 | M10: =IF(J10=0,"",L10/J10*100)
F11: =IF(E11="","",LOOKUP(DATEDIF(E11,评估基准日,"y"),公式数据表!$C$7:$C$10,公式数据表!$B$7:$B$10)) | L11: =K11-J11 | M11: =IF(J11=0,"",L11/J11*100)
F12: =IF(E12="","",LOOKUP(DATEDIF(E12,评估基准日,"y"),公式数据表!$C$7:$C$10,公式数据表!$B$7:$B$10)) | L12: =K12-J12 | M12: =IF(J12=0,"",L12/J12*100)
F13: =IF(E13="","",LOOKUP(DATEDIF(E13,评估基准日,"y"),公式数据表!$C$7:$C$10,公式数据表!$B$7:$B$10)) | L13: =K13-J13 | M13: =IF(J13=0,"",L13/J13*100)
F14: =IF(E14="","",LOOKUP(DATEDIF(E14,评估基准日,"y"),公式数据表!$C$7:$C$10,公式数据表!$B$7:$B$10)) | L14: =K14-J14 | M14: =IF(J14=0,"",L14/J14*100)
F15: =IF(E15="","",LOOKUP(DATEDIF(E15,评估基准日,"y"),公式数据表!$C$7:$C$10,公式数据表!$B$7:$B$10)) | L15: =K15-J15 | M15: =IF(J15=0,"",L15/J15*100)
F16: =IF(E16="","",LOOKUP(DATEDIF(E16,评估基准日,"y"),公式数据表!$C$7:$C$10,公式数据表!$B$7:$B$10)) | L16: =K16-J16 | M16: =IF(J16=0,"",L16/J16*100)
F17: =IF(E17="","",LOOKUP(DATEDIF(E17,评估基准日,"y"),公式数据表!$C$7:$C$10,公式数据表!$B$7:$B$10)) | L17: =K17-J17 | M17: =IF(J17=0,"",L17/J17*100)
... F25: =IF(E25="","",LOOKUP(DATEDIF(E25,评估基准日,"y"),公式数据表!$C$7:$C$10,公式数据表!$B$7:$B$10)) | L25: =K25-J25 | M25: =IF(J25=0,"",L25/J25*100)
A26: 合计1 | B26: 合 计 | H26: =ROUND(SUM(H6:H25),2) | J26: =ROUND(SUM(J6:J25),2) | K26: =ROUND(SUM(K6:K25),2) | L26: =K26-J26 | M26: =IF(J26=0,"",L26/J26*100)
A27: 坏账准备 | B27: 减：预付款项坏账准备 | L27: =K27-J27 | M27: =IF(J27=0,"",L27/J27*100)
A28: 合计2 | B28: 合 计 | H28: =ROUND(SUM(H8:H27),2) | J28: =ROUND(J26-J27,2) | K28: =ROUND(K26-K27,2) | L28: =K28-J28 | M28: =IF(J28=0,"",L28/J28*100)

Sheet 3-8其他应收款汇总
B1: 其他应收款评估汇总表
B2: ='2-分类汇总'!B2
H3: 表3-8
B4: ='2-分类汇总'!B4 | H4: ='2-分类汇总'!H4
B5: 编码 | C5: 项目编号 | D5: 科目名称 | E5: 账面价值 | F5: 评估价值 | G5: 增值额 | H5: 增值率%
B6: 3-8-1 | C6: 应收利息 | D6: 其他应收款—应收利息 | E6: ='3-8-1应收利息'!H30 | F6: ='3-8-1应收利息'!I30 | G6: =F6-E6 | H6: =IF(E6=0,"",G6/E6*100)
B7: 3-8-2 | C7: 应收股利 | D7: 其他应收款—应收股利 | E7: ='3-8-2应收股利'!F30 | F7: ='3-8-2应收股利'!G30 | G7: =F7-E7 | H7: =IF(E7=0,"",G7/E7*100)
B8: 3-8-3 | C8: 其他应收 | D8: 其他应收款—其他应收款 | E8: ='3-8-3其他应收款'!J30 | F8: ='3-8-3其他应收款'!K30 | G8: =F8-E8 | H8: =IF(E8=0,"",G8/E8*100)
G10: =F10-E10 | H10: =IF(E10=0,"",G10/E10*100)
G11: =F11-E11 | H11: =IF(E11=0,"",G11/E11*100)
G12: =F12-E12 | H12: =IF(E12=0,"",G12/E12*100)
G13: =F13-E13 | H13: =IF(E13=0,"",G13/E13*100)
G14: =F14-E14 | H14: =IF(E14=0,"",G14/E14*100)
G15: =F15-E15 | H15: =IF(E15=0,"",G15/E15*100)
G16: =F16-E16 | H16: =IF(E16=0,"",G16/E16*100)
G17: =F17-E17 | H17: =IF(E17=0,"",G17/E17*100)
G18: =F18-E18 | H18: =IF(E18=0,"",G18/E18*100)
G19: =F19-E19 | H19: =IF(E19=0,"",G19/E19*100)
G20: =F20-E20 | H20: =IF(E20=0,"",G20/E20*100)
G21: =F21-E21 | H21: =IF(E21=0,"",G21/E21*100)
A25: 合计1 | C25: 其收净额 | D25: 合 计 | E25: =SUM(E6:E24) | F25: =SUM(F6:F24) | G25: =F25-E25 | H25: =IF(E25=0,"",G25/E25*100)

Sheet 3-8-1应收利息
A1: 表头区域 | B1: 其他应收款—应收利息评估明细表
A2: 表头区域 | B2: ='3-8其他应收款汇总'!B2:H2
A3: 表头区域 | L3: 表3-8-1
A4: 表头区域 | B4: ='3-8其他应收款汇总'!B4 | L4: ='2-分类汇总'!H4
A5: 检索表头 | B5: 序号 | C5: 欠款单位名称（结算对象) | D5: 发生日期 | E5: 本金 | F5: 利息所属期间 | G5: 年利息率% | H5: 账面价值 | I5: 评估价值 | J5: 增值额 | K5: 增值率% | L5: 备注
J6: =I6-H6 | K6: =IF(H6=0,"",J6/H6*100)
J7: =I7-H7 | K7: =IF(H7=0,"",J7/H7*100)
J8: =I8-H8 | K8: =IF(H8=0,"",J8/H8*100)
J9: =I9-H9 | K9: =IF(H9=0,"",J9/H9*100)
J10: =I10-H10 | K10: =IF(H10=0,"",J10/H10*100)
J11: =I11-H11 | K11: =IF(H11=0,"",J11/H11*100)
J12: =I12-H12 | K12: =IF(H12=0,"",J12/H12*100)
J13: =I13-H13 | K13: =IF(H13=0,"",J13/H13*100)
J14: =I14-H14 | K14: =IF(H14=0,"",J14/H14*100)
J15: =I15-H15 | K15: =IF(H15=0,"",J15/H15*100)
J16: =I16-H16 | K16: =IF(H16=0,"",J16/H16*100)
J17: =I17-H17 | K17: =IF(H17=0,"",J17/H17*100)
... J29: =I29-H29 | K29: =IF(H29=0,"",J29/H29*100)
A30: 合计1 | B30: 合 计 | E30: =ROUND(SUM(E6:E29),2) | H30: =ROUND(SUM(H6:H29),2) | I30: =ROUND(SUM(I6:I29),2) | J30: =I30-H30 | K30: =IF(H30=0,"",J30/H30*100)

Sheet 3-8-2应收股利
A1: 表头区域 | B1: 其他应收款—应收股利评估明细表
A2: 表头区域 | B2: ='3-8其他应收款汇总'!B2:H2
A3: 表头区域 | J3: 表3-8-2
A4: 表头区域 | B4: ='3-8其他应收款汇总'!B4 | J4: ='2-分类汇总'!H4
A5: 检索表头 | B5: 序号 | C5: 户名（结算对象) | D5: 发生日期 | E5: 股利（利润）所属期间 | F5: 账面价值 | G5: 评估价值 | H5: 增值额 | I5: 增值率% | J5: 备注
H6: =G6-F6 | I6: =IF(F6=0,"",H6/F6*100)
H7: =G7-F7 | I7: =IF(F7=0,"",H7/F7*100)
H8: =G8-F8 | I8: =IF(F8=0,"",H8/F8*100)
H9: =G9-F9 | I9: =IF(F9=0,"",H9/F9*100)
H10: =G10-F10 | I10: =IF(F10=0,"",H10/F10*100)
H11: =G11-F11 | I11: =IF(F11=0,"",H11/F11*100)
H12: =G12-F12 | I12: =IF(F12=0,"",H12/F12*100)
H13: =G13-F13 | I13: =IF(F13=0,"",H13/F13*100)
H14: =G14-F14 | I14: =IF(F14=0,"",H14/F14*100)
H15: =G15-F15 | I15: =IF(F15=0,"",H15/F15*100)
H16: =G16-F16 | I16: =IF(F16=0,"",H16/F16*100)
H17: =G17-F17 | I17: =IF(F17=0,"",H17/F17*100)
... H29: =G29-F29 | I29: =IF(F29=0,"",H29/F29*100)
A30: 合计1 | B30: 合 计 | F30: =ROUND(SUM(F6:F29),2) | G30: =ROUND(SUM(G6:G29),2) | H30: =G30-F30 | I30: =IF(F30=0,"",H30/F30*100)

Sheet 3-8-3其他应收款
A1: 表头区域 | B1: 其他应收款—其他应收款评估明细表
A2: 表头区域 | B2: ='2-分类汇总'!B2
A3: 表头区域 | N3: 表3-8-3
A4: 表头区域 | B4: ='2-分类汇总'!B4 | N4: ='2-分类汇总'!H4
A5: 检索表头 | B5: 序号 | C5: 欠款单位（人）名称（结算对象) | D5: 业务内容 | E5: 发生日期 | F5: 账龄 | G5: 币种 | H5: 外币账面金额 | I5: 评估基准日汇率 | J5: 账面价值 | K5: 评估价值 | L5: 增值额 | M5: 增值率% | N5: 备注
F6: =IF(E6="","",LOOKUP(DATEDIF(E6,评估基准日,"y"),公式数据表!$C$7:$C$10,公式数据表!$B$7:$B$10)) | L6: =K6-J6 | M6: =IF(J6=0,"",L6/J6*100)
F7: =IF(E7="","",LOOKUP(DATEDIF(E7,评估基准日,"y"),公式数据表!$C$7:$C$10,公式数据表!$B$7:$B$10)) | L7: =K7-J7 | M7: =IF(J7=0,"",L7/J7*100)
F8: =IF(E8="","",LOOKUP(DATEDIF(E8,评估基准日,"y"),公式数据表!$C$7:$C$10,公式数据表!$B$7:$B$10)) | L8: =K8-J8 | M8: =IF(J8=0,"",L8/J8*100)
F9: =IF(E9="","",LOOKUP(DATEDIF(E9,评估基准日,"y"),公式数据表!$C$7:$C$10,公式数据表!$B$7:$B$10)) | L9: =K9-J9 | M9: =IF(J9=0,"",L9/J9*100)
F10: =IF(E10="","",LOOKUP(DATEDIF(E10,评估基准日,"y"),公式数据表!$C$7:$C$10,公式数据表!$B$7:$B$10)) | L10: =K10-J10 | M10: =IF(J10=0,"",L10/J10*100)
F11: =IF(E11="","",LOOKUP(DATEDIF(E11,评估基准日,"y"),公式数据表!$C$7:$C$10,公式数据表!$B$7:$B$10)) | L11: =K11-J11 | M11: =IF(J11=0,"",L11/J11*100)
F12: =IF(E12="","",LOOKUP(DATEDIF(E12,评估基准日,"y"),公式数据表!$C$7:$C$10,公式数据表!$B$7:$B$10)) | L12: =K12-J12 | M12: =IF(J12=0,"",L12/J12*100)
F13: =IF(E13="","",LOOKUP(DATEDIF(E13,评估基准日,"y"),公式数据表!$C$7:$C$10,公式数据表!$B$7:$B$10)) | L13: =K13-J13 | M13: =IF(J13=0,"",L13/J13*100)
F14: =IF(E14="","",LOOKUP(DATEDIF(E14,评估基准日,"y"),公式数据表!$C$7:$C$10,公式数据表!$B$7:$B$10)) | L14: =K14-J14 | M14: =IF(J14=0,"",L14/J14*100)
F15: =IF(E15="","",LOOKUP(DATEDIF(E15,评估基准日,"y"),公式数据表!$C$7:$C$10,公式数据表!$B$7:$B$10)) | L15: =K15-J15 | M15: =IF(J15=0,"",L15/J15*100)
F16: =IF(E16="","",LOOKUP(DATEDIF(E16,评估基准日,"y"),公式数据表!$C$7:$C$10,公式数据表!$B$7:$B$10)) | L16: =K16-J16 | M16: =IF(J16=0,"",L16/J16*100)
F17: =IF(E17="","",LOOKUP(DATEDIF(E17,评估基准日,"y"),公式数据表!$C$7:$C$10,公式数据表!$B$7:$B$10)) | L17: =K17-J17 | M17: =IF(J17=0,"",L17/J17*100)
... F26: =IF(E26="","",LOOKUP(DATEDIF(E26,评估基准日,"y"),公式数据表!$C$7:$C$10,公式数据表!$B$7:$B$10)) | L26: =K26-J26 | M26: =IF(J26=0,"",L26/J26*100)
A27: 合计1 | B27: 合 计 | H27: =ROUND(SUM(H6:H26),2) | J27: =ROUND(SUM(J6:J26),2) | K27: =ROUND(SUM(K6:K26),2) | L27: =K27-J27 | M27: =IF(J27=0,"",L27/J27*100)
A28: 坏账准备 | B28: 减：其他应收款坏账准备 | L28: =K28-J28 | M28: =IF(J28=0,"",L28/J28*100)
A29: 预计损失 | B29: 减：其他应收款预计损失 | L29: =K29-J29 | M29: =IF(J29=0,"",L29/J29*100)
A30: 合计2 | B30: 合 计 | H30: =ROUND(H27-H28,2) | J30: =ROUND(J27-J28,2) | K30: =ROUND(K27-K29,2) | L30: =K30-J30 | M30: =IF(J30=0,"",L30/J30*100)

Sheet 3-辅-流动资产汇总
A1: 流动资产余额评估汇总表
A2: ='2-分类汇总'!B2
G3: 表3
A4: ='2-分类汇总'!B4 | G4: ='2-分类汇总'!H4
A5: 编号 | B5: 项目编号 | C5: 科目名称 | D5: 账面价值 | E5: 评估价值 | F5: 增值额 | G5: 增值率%
A6: 3-4-1 | B6: 应票余额 | C6: 应收票据余额 | D6: ='3-4应收票据'!G26 | E6: ='3-4应收票据'!H26 | F6: =E6-D6 | G6: =IF(D6=0,"",F6/D6*100)
A7: 3-5-1 | B7: 应收余额 | C7: 应收账款余额 | D7: ='3-5应收账款'!J26 | E7: ='3-5应收账款'!K26 | F7: =E7-D7 | G7: =IF(D7=0,"",F7/D7*100)
A8: 3-6-1 | B8: 应融余额 | C8: 应收款项融资 | D8: ='3-6应收款项融资'!J26 | E8: ='3-6应收款项融资'!K26 | F8: =E8-D8 | G8: =IF(D8=0,"",F8/D8*100)
A9: 3-7-1 | B9: 预付余额 | C9: 预付账款余额 | D9: ='3-7预付款项'!J26 | E9: ='3-7预付款项'!K26 | F9: =E9-D9 | G9: =IF(D9=0,"",F9/D9*100)
A10: 3-8-1 | B10: 他收余额 | C10: 其他应收款余额 | D10: ='3-8-3其他应收款'!J27 | E10: ='3-8-3其他应收款'!K27 | F10: =E10-D10 | G10: =IF(D10=0,"",F10/D10*100)
A11: 3-9-1 | B11: 存货采购 | C11: 在途物资余额 | D11: ='3-9-1在途物资'!G26 | E11: ='3-9-1在途物资'!J26 | F11: =E11-D11 | G11: =IF(D11=0,"",F11/D11*100)
A12: 3-9-2 | B12: 存货原材 | C12: 原材料余额 | D12: ='3-9-2原材料'!H26 | E12: ='3-9-2原材料'!K26 | F12: =E12-D12 | G12: =IF(D12=0,"",F12/D12*100)
A13: 3-9-3 | B13: 存货在库 | C13: 在库周转材料余额 | D13: ='3-9-3在库周转材料'!H26 | E13: ='3-9-3在库周转材料'!K26 | F13: =E13-D13 | G13: =IF(D13=0,"",F13/D13*100)
A14: 3-9-4 | B14: 存货委加 | C14: 委托加工物资余额 | D14: ='3-9-4委托加工物资'!H26 | E14: ='3-9-4委托加工物资'!K26 | F14: =E14-D14 | G14: =IF(D14=0,"",F14/D14*100)
A15: 3-9-5 | B15: 存货产成 | C15: 产成品（库存商品）余额 | D15: ='3-9-5产成品（库存商品）'!H26 | E15: ='3-9-5产成品（库存商品）'!L26 | F15: =E15-D15 | G15: =IF(D15=0,"",F15/D15*100)
A16: 3-9-6 | B16: 存货在产 | C16: 在产品（自制半成品）余额 | D16: ='3-9-6在产品（自制半成品）'!H26 | E16: ='3-9-6在产品（自制半成品）'!K26 | F16: =E16-D16 | G16: =IF(D16=0,"",F16/D16*100)
A17: 3-9-7 | B17: 存货发出 | C17: 发出商品余额 | D17: ='3-9-7发出商品'!H26 | E17: ='3-9-7发出商品'!K26 | F17: =E17-D17 | G17: =IF(D17=0,"",F17/D17*100)
A18: 3-9-8 | B18: 存货在用 | C18: 在用周转材料余额 | D18: ='3-9-8在用周转材料'!H26 | E18: ='3-9-8在用周转材料'!L26 | F18: =E18-D18 | G18: =IF(D18=0,"",F18/D18*100)
A19: 3-9-9 | B19: 存货履约 | C19: 合同履约成本余额 | D19: ='3-9-9合同履约成本'!E26 | E19: ='3-9-9合同履约成本'!F26 | F19: =E19-D19 | G19: =IF(D19=0,"",F19/D19*100)
A20: 3-10-1 | B20: 合同余额 | C20: 合同资产余额 | D20: ='3-10合同资产'!F26 | E20: ='3-10合同资产'!G26 | F20: =E20-D20 | G20: =IF(D20=0,"",F20/D20*100)
B25: 流余汇总 | C25: 合计 | D25: =SUM(D6:D24) | E25: =SUM(E6:E24) | F25: =E25-D25 | G25: =IF(D25=0,"",F25/D25*100)

Sheet 3-9-辅-存货汇总
A1: 存货评估汇总表
A2: ='2-分类汇总'!B2
I3: 表3-9
A4: ='2-分类汇总'!B4 | I4: ='2-分类汇总'!H4
A5: 编号 | B5: 项目编号 | C5: 科目名称 | D5: 账面余额 | E5: 存货跌价准备 | F5: 账面价值 | G5: 评估价值 | H5: 增值额 | I5: 增值率%
A6: 3-9-1 | B6: 存货采购 | C6: 在途物资 | D6: ='3-9-1在途物资'!G26 | E6: ='3-9-1在途物资'!G27 | F6: ='3-9-1在途物资'!G28 | G6: ='3-9-1在途物资'!J28 | H6: =G6-F6 | I6: =IF(F6=0,"",H6/F6*100)
A7: 3-9-2 | B7: 存货原材 | C7: 原材料 | D7: ='3-9-2原材料'!H26 | E7: ='3-9-2原材料'!H27 | F7: ='3-9-2原材料'!H28 | G7: ='3-9-2原材料'!K28 | H7: =G7-F7 | I7: =IF(F7=0,"",H7/F7*100)
A8: 3-9-3 | B8: 存货在库 | C8: 在库周转材料 | D8: ='3-9-3在库周转材料'!H26 | E8: ='3-9-3在库周转材料'!H27 | F8: ='3-9-3在库周转材料'!H28 | G8: ='3-9-3在库周转材料'!K28 | H8: =G8-F8 | I8: =IF(F8=0,"",H8/F8*100)
A9: 3-9-4 | B9: 存货委加 | C9: 委托加工物资 | D9: ='3-9-4委托加工物资'!H26 | E9: ='3-9-4委托加工物资'!H27 | F9: ='3-9-4委托加工物资'!H28 | G9: ='3-9-4委托加工物资'!K28 | H9: =G9-F9 | I9: =IF(F9=0,"",H9/F9*100)
A10: 3-9-5 | B10: 存货产成 | C10: 产成品（库存商品） | D10: ='3-9-5产成品（库存商品）'!H26 | E10: ='3-9-5产成品（库存商品）'!H27 | F10: ='3-9-5产成品（库存商品）'!H28 | G10: ='3-9-5产成品（库存商品）'!L28 | H10: =G10-F10 | I10: =IF(F10=0,"",H10/F10*100)
A11: 3-9-6 | B11: 存货在产 | C11: 在产品（自制半成品） | D11: ='3-9-6在产品（自制半成品）'!H26 | E11: ='3-9-6在产品（自制半成品）'!H27 | F11: ='3-9-6在产品（自制半成品）'!H28 | G11: ='3-9-6在产品（自制半成品）'!K28 | H11: =G11-F11 | I11: =IF(F11=0,"",H11/F11*100)
A12: 3-9-7 | B12: 存货发出 | C12: 发出商品 | D12: ='3-9-7发出商品'!H26 | E12: ='3-9-7发出商品'!H27 | F12: ='3-9-7发出商品'!H28 | G12: ='3-9-7发出商品'!K28 | H12: =G12-F12 | I12: =IF(F12=0,"",H12/F12*100)
A13: 3-9-8 | B13: 存货在用 | C13: 在用周转材料 | D13: ='3-9-8在用周转材料'!H26 | E13: ='3-9-8在用周转材料'!H27 | F13: ='3-9-8在用周转材料'!H28 | G13: ='3-9-8在用周转材料'!L28 | H13: =G13-F13 | I13: =IF(F13=0,"",H13/F13*100)
A14: 3-9-9 | B14: 存货履约 | C14: 合同履约成本 | D14: ='3-9-9合同履约成本'!E26 | E14: ='3-9-9合同履约成本'!E27 | F14: ='3-9-9合同履约成本'!E28 | G14: ='3-9-9合同履约成本'!F28 | H14: =G14-F14 | I14: =IF(F14=0,"",H14/F14*100)
B23: 存货净额 | C23: 合 计 | D23: =SUM(D6:D14) | E23: =SUM(E6:E14) | F23: =SUM(F6:F14) | G23: =SUM(G6:G14) | H23: =G23-F23 | I23: =IF(F23=0,"",H23/F23*100)
A33: 3-9-1 | B33: 采购跌价 | C33: 材料采购（在途物资） | F33: ='3-9-1在途物资'!G27 | G33: ='3-9-1在途物资'!J27
A34: 3-9-2 | B34: 原材跌价 | C34: 原材料 | F34: ='3-9-2原材料'!H27 | G34: ='3-9-2原材料'!K27
A35: 3-9-3 | B35: 在库跌价 | C35: 在库周转材料 | F35: ='3-9-3在库周转材料'!H27 | G35: ='3-9-3在库周转材料'!K27
A36: 3-9-4 | B36: 委加跌价 | C36: 委托加工物资 | F36: ='3-9-4委托加工物资'!H27 | G36: ='3-9-4委托加工物资'!K27
A37: 3-9-5 | B37: 产成跌价 | C37: 产成品（库存商品） | F37: ='3-9-5产成品（库存商品）'!H27 | G37: ='3-9-5产成品（库存商品）'!L27
A38: 3-9-6 | B38: 在产跌价 | C38: 在产品（自制半成品） | F38: ='3-9-6在产品（自制半成品）'!H27 | G38: ='3-9-6在产品（自制半成品）'!K27
A39: 3-9-7 | B39: 发出跌价 | C39: 发出商品 | F39: ='3-9-7发出商品'!H27 | G39: ='3-9-7发出商品'!K27
A40: 3-9-8 | B40: 在用跌价 | C40: 在用周转材料 | F40: ='3-9-8在用周转材料'!H27 | G40: ='3-9-8在用周转材料'!L27

Sheet 3-9存货汇总
B1: 存货评估汇总表
B2: ='2-分类汇总'!B2
H3: 表3-9
B4: ='2-分类汇总'!B4 | H4: ='2-分类汇总'!H4
B5: 编号 | C5: 项目编号 | D5: 科目名称 | E5: 账面价值 | F5: 评估价值 | G5: 增值额 | H5: 增值率%
B6: 3-9-1 | C6: 存货采购 | D6: 在途物资 | E6: ='3-9-1在途物资'!G28 | F6: ='3-9-1在途物资'!J28 | G6: =F6-E6 | H6: =IF(E6=0,"",G6/E6*100)
B7: 3-9-2 | C7: 存货原材 | D7: 原材料 | E7: ='3-9-2原材料'!H28 | F7: ='3-9-2原材料'!K28 | G7: =F7-E7 | H7: =IF(E7=0,"",G7/E7*100)
B8: 3-9-3 | C8: 存货在库 | D8: 在库周转材料 | E8: ='3-9-3在库周转材料'!H28 | F8: ='3-9-3在库周转材料'!K28 | G8: =F8-E8 | H8: =IF(E8=0,"",G8/E8*100)
B9: 3-9-4 | C9: 存货委加 | D9: 委托加工物资 | E9: ='3-9-4委托加工物资'!H28 | F9: ='3-9-4委托加工物资'!K28 | G9: =F9-E9 | H9: =IF(E9=0,"",G9/E9*100)
B10: 3-9-5 | C10: 存货产成 | D10: 产成品（库存商品） | E10: ='3-9-5产成品（库存商品）'!H28 | F10: ='3-9-5产成品（库存商品）'!L28 | G10: =F10-E10 | H10: =IF(E10=0,"",G10/E10*100)
B11: 3-9-6 | C11: 存货在产 | D11: 在产品（自制半成品） | E11: ='3-9-6在产品（自制半成品）'!H28 | F11: ='3-9-6在产品（自制半成品）'!K28 | G11: =F11-E11 | H11: =IF(E11=0,"",G11/E11*100)
B12: 3-9-7 | C12: 存货发出 | D12: 发出商品 | E12: ='3-9-7发出商品'!H28 | F12: ='3-9-7发出商品'!K28 | G12: =F12-E12 | H12: =IF(E12=0,"",G12/E12*100)
B13: 3-9-8 | C13: 存货在用 | D13: 在用周转材料 | E13: ='3-9-8在用周转材料'!H28 | F13: ='3-9-8在用周转材料'!L28 | G13: =F13-E13 | H13: =IF(E13=0,"",G13/E13*100)
B14: 3-9-9 | C14: 存货履约 | D14: 合同履约成本 | E14: ='3-9-9合同履约成本'!E28 | F14: ='3-9-9合同履约成本'!F28 | G14: =F14-E14 | H14: =IF(E14=0,"",G14/E14*100)
A23: 合计1 | C23: 存货净额 | D23: 合 计 | E23: =SUM(E6:E14) | F23: =SUM(F6:F14) | G23: =F23-E23 | H23: =IF(E23=0,"",G23/E23*100)

Sheet 3-9-1在途物资
A1: 表头区域 | B1: 存货—在途物资评估明细表
A2: 表头区域 | B2: ='2-分类汇总'!B2
A3: 表头区域 | M3: 表3-9-1
A4: 表头区域 | B4: ='2-分类汇总'!B4 | M4: ='2-分类汇总'!H4
A5: 检索表头1 | B5: 序号 | C5: 名称及规格型号 | D5: 计量单位 | E5: 账面价值 | H5: 评估价值 | K5: 增值额 | L5: 增值率% | M5: 备注
A6: 检索表头2 | E6: 数量 | F6: 单价 | G6: 金额 | H6: 实际数量 | I6: 评估单价 | J6: 金额
K7: =J7-G7 | L7: =IF(G7=0,"",K7/G7*100)
K8: =J8-G8 | L8: =IF(G8=0,"",K8/G8*100)
K9: =J9-G9 | L9: =IF(G9=0,"",K9/G9*100)
K10: =J10-G10 | L10: =IF(G10=0,"",K10/G10*100)
K11: =J11-G11 | L11: =IF(G11=0,"",K11/G11*100)
K12: =J12-G12 | L12: =IF(G12=0,"",K12/G12*100)
K13: =J13-G13 | L13: =IF(G13=0,"",K13/G13*100)
K14: =J14-G14 | L14: =IF(G14=0,"",K14/G14*100)
K15: =J15-G15 | L15: =IF(G15=0,"",K15/G15*100)
K16: =J16-G16 | L16: =IF(G16=0,"",K16/G16*100)
K17: =J17-G17 | L17: =IF(G17=0,"",K17/G17*100)
K18: =J18-G18 | L18: =IF(G18=0,"",K18/G18*100)
... K25: =J25-G25 | L25: =IF(G25=0,"",K25/G25*100)
A26: 合计1 | B26: 合 计 | E26: =ROUND(SUM(E7:E25),2) | G26: =ROUND(SUM(G7:G25),2) | H26: =ROUND(SUM(H7:H25),2) | J26: =ROUND(SUM(J7:J25),2) | K26: =J26-G26 | L26: =IF(G26=0,"",K26/G26*100)
A27: 坏账准备 | B27: 减：存货跌价准备 | K27: =J27-G27 | L27: =IF(G27=0,"",K27/G27*100)
A28: 合计2 | B28: 合 计 | E28: =ROUND(E26-E27,2) | G28: =ROUND(G26-G27,2) | H28: =ROUND(H26-H27,2) | J28: =ROUND(J26-J27,2) | K28: =J28-G28 | L28: =IF(G28=0,"",K28/G28*100)

Sheet 3-9-2原材料
A1: 表头区域 | B1: 存货—原材料评估明细表
A2: 表头区域 | B2: ='2-分类汇总'!B2
A3: 表头区域 | N3: 表3-9-2
A4: 表头区域 | B4: ='2-分类汇总'!B4 | N4: ='2-分类汇总'!H4
A5: 检索表头1 | B5: 序号 | C5: 名称及规格型号 | D5: 计量单位 | E5: 存放地点 | F5: 账面价值 | I5: 评估价值 | L5: 增值额 | M5: 增值率% | N5: 备注
A6: 检索表头2 | F6: 数量 | G6: 单价 | H6: 金额 | I6: 实际数量 | J6: 评估单价 | K6: 金额
L7: =K7-H7 | M7: =IF(H7=0,"",L7/H7*100)
L8: =K8-H8 | M8: =IF(H8=0,"",L8/H8*100)
L9: =K9-H9 | M9: =IF(H9=0,"",L9/H9*100)
L10: =K10-H10 | M10: =IF(H10=0,"",L10/H10*100)
L11: =K11-H11 | M11: =IF(H11=0,"",L11/H11*100)
L12: =K12-H12 | M12: =IF(H12=0,"",L12/H12*100)
L13: =K13-H13 | M13: =IF(H13=0,"",L13/H13*100)
L14: =K14-H14 | M14: =IF(H14=0,"",L14/H14*100)
L15: =K15-H15 | M15: =IF(H15=0,"",L15/H15*100)
L16: =K16-H16 | M16: =IF(H16=0,"",L16/H16*100)
L17: =K17-H17 | M17: =IF(H17=0,"",L17/H17*100)
L18: =K18-H18 | M18: =IF(H18=0,"",L18/H18*100)
... L25: =K25-H25 | M25: =IF(H25=0,"",L25/H25*100)
A26: 合计1 | B26: 合 计 | F26: =ROUND(SUM(F7:F25),2) | H26: =ROUND(SUM(H7:H25),2) | I26: =ROUND(SUM(I7:I25),2) | K26: =ROUND(SUM(K7:K25),2) | L26: =K26-H26 | M26: =IF(H26=0,"",L26/H26*100)
A27: 坏账准备 | B27: 减：存货跌价准备 | L27: =K27-H27 | M27: =IF(H27=0,"",L27/H27*100)
A28: 合计2 | B28: 合 计 | F28: =ROUND(F26-F27,2) | H28: =ROUND(H26-H27,2) | I28: =ROUND(I26-I27,2) | K28: =ROUND(K26-K27,2) | L28: =K28-H28 | M28: =IF(H28=0,"",L28/H28*100)

Sheet 3-9-3在库周转材料
A1: 表头区域 | B1: 存货—在库周转材料评估明细表
A2: 表头区域 | B2: ='2-分类汇总'!B2
A3: 表头区域 | N3: 表3-9-3
A4: 表头区域 | B4: ='2-分类汇总'!B4 | N4: ='2-分类汇总'!H4
A5: 检索表头1 | B5: 序号 | C5: 名称及规格型号 | D5: 计量单位 | E5: 存放地点 | F5: 账面价值 | I5: 评估价值 | L5: 增值额 | M5: 增值率% | N5: 备注
A6: 检索表头2 | F6: 数量 | G6: 单价 | H6: 金额 | I6: 实际数量 | J6: 评估单价 | K6: 金额
L7: =K7-H7 | M7: =IF(H7=0,"",L7/H7*100)
L8: =K8-H8 | M8: =IF(H8=0,"",L8/H8*100)
L9: =K9-H9 | M9: =IF(H9=0,"",L9/H9*100)
L10: =K10-H10 | M10: =IF(H10=0,"",L10/H10*100)
L11: =K11-H11 | M11: =IF(H11=0,"",L11/H11*100)
L12: =K12-H12 | M12: =IF(H12=0,"",L12/H12*100)
L13: =K13-H13 | M13: =IF(H13=0,"",L13/H13*100)
L14: =K14-H14 | M14: =IF(H14=0,"",L14/H14*100)
L15: =K15-H15 | M15: =IF(H15=0,"",L15/H15*100)
L16: =K16-H16 | M16: =IF(H16=0,"",L16/H16*100)
L17: =K17-H17 | M17: =IF(H17=0,"",L17/H17*100)
L18: =K18-H18 | M18: =IF(H18=0,"",L18/H18*100)
... L25: =K25-H25 | M25: =IF(H25=0,"",L25/H25*100)
A26: 合计1 | B26: 合计 | F26: =ROUND(SUM(F7:F25),2) | H26: =ROUND(SUM(H7:H25),2) | I26: =ROUND(SUM(I7:I25),2) | K26: =ROUND(SUM(K7:K25),2) | L26: =K26-H26 | M26: =IF(H26=0,"",L26/H26*100)
A27: 坏账准备 | B27: 减：存货跌价准备 | L27: =K27-H27 | M27: =IF(H27=0,"",L27/H27*100)
A28: 合计2 | B28: 合计 | F28: =ROUND(F26-F27,2) | H28: =ROUND(H26-H27,2) | I28: =ROUND(I26-I27,2) | K28: =ROUND(K26-K27,2) | L28: =K28-H28 | M28: =IF(H28=0,"",L28/H28*100)

Sheet 3-9-4委托加工物资
A1: 表头区域 | B1: 存货—委托加工物资评估明细表
A2: 表头区域 | B2: ='2-分类汇总'!B2
A3: 表头区域 | M3: 表3-9-4
A4: 表头区域 | B4: ='2-分类汇总'!B4 | N4: ='2-分类汇总'!H4
A5: 检索表头1 | B5: 序号 | C5: 名称及规格型号 | D5: 加工单位名称 | E5: 计量单位 | F5: 账面价值 | I5: 评估价值 | L5: 增值额 | M5: 增值率% | N5: 备注
A6: 检索表头2 | F6: 数量 | G6: 单价 | H6: 金额 | I6: 实际数量 | J6: 评估单价 | K6: 金额
L7: =K7-H7 | M7: =IF(H7=0,"",L7/H7*100)
L8: =K8-H8 | M8: =IF(H8=0,"",L8/H8*100)
L9: =K9-H9 | M9: =IF(H9=0,"",L9/H9*100)
L10: =K10-H10 | M10: =IF(H10=0,"",L10/H10*100)
L11: =K11-H11 | M11: =IF(H11=0,"",L11/H11*100)
L12: =K12-H12 | M12: =IF(H12=0,"",L12/H12*100)
L13: =K13-H13 | M13: =IF(H13=0,"",L13/H13*100)
L14: =K14-H14 | M14: =IF(H14=0,"",L14/H14*100)
L15: =K15-H15 | M15: =IF(H15=0,"",L15/H15*100)
L16: =K16-H16 | M16: =IF(H16=0,"",L16/H16*100)
L17: =K17-H17 | M17: =IF(H17=0,"",L17/H17*100)
L18: =K18-H18 | M18: =IF(H18=0,"",L18/H18*100)
... L25: =K25-H25 | M25: =IF(H25=0,"",L25/H25*100)
A26: 合计1 | B26: 合 计 | F26: =ROUND(SUM(F7:F25),2) | H26: =ROUND(SUM(H7:H25),2) | I26: =ROUND(SUM(I7:I25),2) | K26: =ROUND(SUM(K7:K25),2) | L26: =K26-H26 | M26: =IF(H26=0,"",L26/H26*100)
A27: 坏账准备 | B27: 减：存货跌价准备 | L27: =K27-H27 | M27: =IF(H27=0,"",L27/H27*100)
A28: 合计2 | B28: 合 计 | F28: =ROUND(F26-F27,2) | H28: =ROUND(H26-H27,2) | I28: =ROUND(I26-I27,2) | K28: =ROUND(K26-K27,2) | L28: =K28-H28 | M28: =IF(H28=0,"",L28/H28*100)

Sheet 3-9-5产成品（库存商品）
A1: 表头区域 | B1: 存货—产成品（库存商品、开发产品、农产品）评估明细表
A2: 表头区域 | B2: ='2-分类汇总'!B2
A3: 表头区域 | O3: 表3-9-5
A4: 表头区域 | B4: ='2-分类汇总'!B4 | O4: ='2-分类汇总'!H4
A5: 检索表头1 | B5: 序号 | C5: 名 称 | D5: 规格型号 | E5: 计量单位 | F5: 账面价值 | I5: 评估价值 | M5: 增值额 | N5: 增值率% | O5: 备注
A6: 检索表头2 | F6: 数量 | G6: 单价 | H6: 金额 | I6: 实际数量 | J6: 单价 | K6: 汇率 | L6: 金额
M7: =L7-H7 | N7: =IF(H7=0,"",M7/H7*100)
M8: =L8-H8 | N8: =IF(H8=0,"",M8/H8*100)
M9: =L9-H9 | N9: =IF(H9=0,"",M9/H9*100)
M10: =L10-H10 | N10: =IF(H10=0,"",M10/H10*100)
M11: =L11-H11 | N11: =IF(H11=0,"",M11/H11*100)
M12: =L12-H12 | N12: =IF(H12=0,"",M12/H12*100)
M13: =L13-H13 | N13: =IF(H13=0,"",M13/H13*100)
M14: =L14-H14 | N14: =IF(H14=0,"",M14/H14*100)
M15: =L15-H15 | N15: =IF(H15=0,"",M15/H15*100)
M16: =L16-H16 | N16: =IF(H16=0,"",M16/H16*100)
M17: =L17-H17 | N17: =IF(H17=0,"",M17/H17*100)
M18: =L18-H18 | N18: =IF(H18=0,"",M18/H18*100)
... M25: =L25-H25 | N25: =IF(H25=0,"",M25/H25*100)
A26: 合计1 | B26: 合 计 | F26: =ROUND(SUM(F7:F25),2) | H26: =ROUND(SUM(H7:H25),2) | I26: =ROUND(SUM(I7:I25),2) | L26: =ROUND(SUM(L7:L25),2) | M26: =L26-H26 | N26: =IF(H26=0,"",M26/H26*100)
A27: 坏账准备 | B27: 减：存货跌价准备 | M27: =L27-H27 | N27: =IF(H27=0,"",M27/H27*100)
A28: 合计2 | B28: 合 计 | F28: =ROUND(F26-F27,2) | H28: =ROUND(H26-H27,2) | I28: =ROUND(I26-I27,2) | L28: =ROUND(L26-L27,2) | M28: =L28-H28 | N28: =IF(H28=0,"",M28/H28*100)

Sheet 3-9-6在产品（自制半成品）
A1: 表头区域 | B1: 存货—在产品（自制半成品）评估明细表
A2: 表头区域 | B2: ='2-分类汇总'!B2
A3: 表头区域 | N3: 表3-9-6
A4: 表头区域 | B4: ='2-分类汇总'!B4 | N4: ='2-分类汇总'!H4
A5: 检索表头1 | B5: 序号 | C5: 名称 | D5: 规格型号 | E5: 计量 单位 | F5: 账面价值 | I5: 评估价值 | L5: 增值额 | M5: 增值率% | N5: 备注
A6: 检索表头2 | F6: 数量 | G6: 单价 | H6: 金额 | I6: 实际数量 | J6: 单价 | K6: 金额
L7: =K7-H7 | M7: =IF(H7=0,"",L7/H7*100)
L8: =K8-H8 | M8: =IF(H8=0,"",L8/H8*100)
L9: =K9-H9 | M9: =IF(H9=0,"",L9/H9*100)
L10: =K10-H10 | M10: =IF(H10=0,"",L10/H10*100)
L11: =K11-H11 | M11: =IF(H11=0,"",L11/H11*100)
L12: =K12-H12 | M12: =IF(H12=0,"",L12/H12*100)
L13: =K13-H13 | M13: =IF(H13=0,"",L13/H13*100)
L14: =K14-H14 | M14: =IF(H14=0,"",L14/H14*100)
L15: =K15-H15 | M15: =IF(H15=0,"",L15/H15*100)
L16: =K16-H16 | M16: =IF(H16=0,"",L16/H16*100)
L17: =K17-H17 | M17: =IF(H17=0,"",L17/H17*100)
L18: =K18-H18 | M18: =IF(H18=0,"",L18/H18*100)
... L25: =K25-H25 | M25: =IF(H25=0,"",L25/H25*100)
A26: 合计1 | B26: 合 计 | F26: =ROUND(SUM(F7:F25),2) | H26: =ROUND(SUM(H7:H25),2) | I26: =ROUND(SUM(I7:I25),2) | K26: =ROUND(SUM(K7:K25),2) | L26: =K26-H26 | M26: =IF(H26=0,"",L26/H26*100)
A27: 坏账准备 | B27: 减：存货跌价准备 | L27: =K27-H27 | M27: =IF(H27=0,"",L27/H27*100)
A28: 合计2 | B28: 合 计 | F28: =ROUND(F26-F27,2) | H28: =ROUND(H26-H27,2) | I28: =ROUND(I26-I27,2) | K28: =ROUND(K26-K27,2) | L28: =K28-H28 | M28: =IF(H28=0,"",L28/H28*100)

Sheet 3-9-7发出商品
A1: 表头区域 | B1: 存货—发出商品评估明细表
A2: 表头区域 | B2: ='2-分类汇总'!B2
A3: 表头区域 | M3: 表3-9-7
A4: 表头区域 | B4: ='2-分类汇总'!B4 | N4: ='2-分类汇总'!H4
A5: 检索表头1 | B5: 序号 | C5: 商品名称 | D5: 对方单位名称 | E5: 计量 单位 | F5: 账面价值 | I5: 评估价值 | L5: 增值额 | M5: 增值率% | N5: 备注
A6: 检索表头2 | F6: 数量 | G6: 单价 | H6: 金额 | I6: 实际数量 | J6: 单价 | K6: 金额
L7: =K7-H7 | M7: =IF(H7=0,"",L7/H7*100)
L8: =K8-H8 | M8: =IF(H8=0,"",L8/H8*100)
L9: =K9-H9 | M9: =IF(H9=0,"",L9/H9*100)
L10: =K10-H10 | M10: =IF(H10=0,"",L10/H10*100)
L11: =K11-H11 | M11: =IF(H11=0,"",L11/H11*100)
L12: =K12-H12 | M12: =IF(H12=0,"",L12/H12*100)
L13: =K13-H13 | M13: =IF(H13=0,"",L13/H13*100)
L14: =K14-H14 | M14: =IF(H14=0,"",L14/H14*100)
L15: =K15-H15 | M15: =IF(H15=0,"",L15/H15*100)
L16: =K16-H16 | M16: =IF(H16=0,"",L16/H16*100)
L17: =K17-H17 | M17: =IF(H17=0,"",L17/H17*100)
L18: =K18-H18 | M18: =IF(H18=0,"",L18/H18*100)
... L25: =K25-H25 | M25: =IF(H25=0,"",L25/H25*100)
A26: 合计1 | B26: 合 计 | F26: =ROUND(SUM(F7:F25),2) | H26: =ROUND(SUM(H7:H25),2) | I26: =ROUND(SUM(I7:I25),2) | K26: =ROUND(SUM(K7:K25),2) | L26: =K26-H26 | M26: =IF(H26=0,"",L26/H26*100)
A27: 坏账准备 | B27: 减：存货跌价准备 | L27: =K27-H27 | M27: =IF(H27=0,"",L27/H27*100)
A28: 合计2 | B28: 合 计 | F28: =ROUND(F26-F27,2) | H28: =ROUND(H26-H27,2) | I28: =ROUND(I26-I27,2) | K28: =ROUND(K26-K27,2) | L28: =K28-H28 | M28: =IF(H28=0,"",L28/H28*100)

Sheet 3-9-8在用周转材料
A1: 表头区域 | B1: 存货—在用周转材料评估明细表
A2: 表头区域 | B2: ='2-分类汇总'!B2
A3: 表头区域 | O3: 表3-9-8
A4: 表头区域 | B4: ='2-分类汇总'!B4 | O4: ='2-分类汇总'!H4
A5: 检索表头1 | B5: 序号 | C5: 名称 | D5: 规格型号 | E5: 启用日期 | F5: 原始入账价值 | G5: 账面价值（摊余价值） | I5: 实际数量 | J5: 评估价值 | M5: 增值额 | N5: 增值率% | O5: 备注
A6: 检索表头2 | G6: 数量 | H6: 金额 | J6: 评估原值 | K6: 成新率% | L6: 金额
M7: =L7-H7 | N7: =IF(H7=0,"",M7/H7*100)
M8: =L8-H8 | N8: =IF(H8=0,"",M8/H8*100)
M9: =L9-H9 | N9: =IF(H9=0,"",M9/H9*100)
M10: =L10-H10 | N10: =IF(H10=0,"",M10/H10*100)
M11: =L11-H11 | N11: =IF(H11=0,"",M11/H11*100)
M12: =L12-H12 | N12: =IF(H12=0,"",M12/H12*100)
M13: =L13-H13 | N13: =IF(H13=0,"",M13/H13*100)
M14: =L14-H14 | N14: =IF(H14=0,"",M14/H14*100)
M15: =L15-H15 | N15: =IF(H15=0,"",M15/H15*100)
M16: =L16-H16 | N16: =IF(H16=0,"",M16/H16*100)
M17: =L17-H17 | N17: =IF(H17=0,"",M17/H17*100)
M18: =L18-H18 | N18: =IF(H18=0,"",M18/H18*100)
... M25: =L25-H25 | N25: =IF(H25=0,"",M25/H25*100)
A26: 合计1 | B26: 合 计 | F26: =ROUND(SUM(F7:F25),2) | G26: =ROUND(SUM(G7:G25),2) | H26: =ROUND(SUM(H7:H25),2) | I26: =ROUND(SUM(I7:I25),2) | J26: =ROUND(SUM(J7:J25),2) | L26: =ROUND(SUM(L7:L25),2) | M26: =L26-H26 | N26: =IF(H26=0,"",M26/H26*100)
A27: 坏账准备 | B27: 减：存货跌价准备 | M27: =L27-H27 | N27: =IF(H27=0,"",M27/H27*100)
A28: 合计2 | B28: 合 计 | F28: =ROUND(F26-F27,2) | G28: =ROUND(G26-G27,2) | H28: =ROUND(H26-H27,2) | I28: =ROUND(I26-I27,2) | J28: =ROUND(J26-J27,2) | L28: =ROUND(L26-L27,2) | M28: =L28-H28 | N28: =IF(H28=0,"",M28/H28*100)

Sheet 3-9-9合同履约成本
A1: 表头区域 | B1: 存货—合同履约成本评估明细表
A2: 表头区域 | B2: ='2-分类汇总'!B2
A3: 表头区域 | I3: 表3-9-9
A4: 表头区域 | B4: ='2-分类汇总'!B4 | I4: ='2-分类汇总'!H4
A5: 检索表头1 | B5: 序号 | C5: 项目名称 | D5: 结算对象 | E5: 账面价值 | F5: 评估价值 | G5: 增值额 | H5: 增值率% | I5: 备注
A6: 检索表头2
G7: =F7-E7 | H7: =IF(E7=0,"",G7/E7*100)
G8: =F8-E8 | H8: =IF(E8=0,"",G8/E8*100)
G9: =F9-E9 | H9: =IF(E9=0,"",G9/E9*100)
G10: =F10-E10 | H10: =IF(E10=0,"",G10/E10*100)
G11: =F11-E11 | H11: =IF(E11=0,"",G11/E11*100)
G12: =F12-E12 | H12: =IF(E12=0,"",G12/E12*100)
G13: =F13-E13 | H13: =IF(E13=0,"",G13/E13*100)
G14: =F14-E14 | H14: =IF(E14=0,"",G14/E14*100)
G15: =F15-E15 | H15: =IF(E15=0,"",G15/E15*100)
G16: =F16-E16 | H16: =IF(E16=0,"",G16/E16*100)
G17: =F17-E17 | H17: =IF(E17=0,"",G17/E17*100)
G18: =F18-E18 | H18: =IF(E18=0,"",G18/E18*100)
... G25: =F25-E25 | H25: =IF(E25=0,"",G25/E25*100)
A26: 合计1 | B26: 合 计 | E26: =ROUND(SUM(E7:E25),2) | F26: =ROUND(SUM(F7:F25),2) | G26: =F26-E26 | H26: =IF(E26=0,"",G26/E26*100)
A27: 坏账准备 | B27: 减：减值准备 | G27: =F27-E27 | H27: =IF(E27=0,"",G27/E27*100)
A28: 合计2 | B28: 合 计 | E28: =ROUND(E26-E27,2) | F28: =ROUND(F26-F27,2) | G28: =F28-E28 | H28: =IF(E28=0,"",G28/E28*100)

Sheet 3-10合同资产
A1: 表头区域 | B1: 合同资产评估明细表
A2: 表头区域 | B2: ='2-分类汇总'!B2
A3: 表头区域 | J3: 表3-10
A4: 表头区域 | B4: ='2-分类汇总'!B4 | J4: ='2-分类汇总'!H4
A5: 检索表头 | B5: 序号 | C5: 项目及内容 | D5: 发生日期 | E5: 结算内容 | F5: 账面价值 | G5: 评估价值 | H5: 增值额 | I5: 增值率% | J5: 备注
H6: =G6-F6 | I6: =IF(F6=0,"",H6/F6*100)
H7: =G7-F7 | I7: =IF(F7=0,"",H7/F7*100)
H8: =G8-F8 | I8: =IF(F8=0,"",H8/F8*100)
H9: =G9-F9 | I9: =IF(F9=0,"",H9/F9*100)
H10: =G10-F10 | I10: =IF(F10=0,"",H10/F10*100)
H11: =G11-F11 | I11: =IF(F11=0,"",H11/F11*100)
H12: =G12-F12 | I12: =IF(F12=0,"",H12/F12*100)
H13: =G13-F13 | I13: =IF(F13=0,"",H13/F13*100)
H14: =G14-F14 | I14: =IF(F14=0,"",H14/F14*100)
H15: =G15-F15 | I15: =IF(F15=0,"",H15/F15*100)
H16: =G16-F16 | I16: =IF(F16=0,"",H16/F16*100)
H17: =G17-F17 | I17: =IF(F17=0,"",H17/F17*100)
... H25: =G25-F25 | I25: =IF(F25=0,"",H25/F25*100)
A26: 合计1 | B26: 合 计 | F26: =SUM(F6:F25) | G26: =SUM(G6:G25) | H26: =G26-F26 | I26: =IF(F26=0,"",H26/F26*100)
A27: 坏账准备 | B27: 减：合同资产减值准备 | H27: =G27-F27 | I27: =IF(F27=0,"",H27/F27*100)
A28: 预计风险 | B28: 减：合同资产减值损失 | H28: =G28-F28 | I28: =IF(F28=0,"",H28/F28*100)
A29: 合计2 | B29: 合 计 | F29: =F26-F27 | G29: =G26-G28 | H29: =G29-F29 | I29: =IF(F29=0,"",H29/F29*100)

Sheet 3-11持有待售资产
A1: 表头区域 | B1: 持有待售资产评估明细表
A2: 表头区域 | B2: ='2-分类汇总'!B2
A3: 表头区域 | M3: 表3-11
A4: 表头区域 | B4: ='2-分类汇总'!B4 | M4: ='2-分类汇总'!H4
A5: 检索表头 | B5: 序号 | C5: 资产名称 | D5: 规格型号 | E5: 生产厂家 | F5: 原始入账日期 | G5: 启用日期 | H5: 数量 | I5: 账面价值 | J5: 评估价值 | K5: 增值额 | L5: 增值率% | M5: 备注
K6: =J6-I6 | L6: =IF(I6=0,"",K6/I6*100)
K7: =J7-I7 | L7: =IF(I7=0,"",K7/I7*100)
K8: =J8-I8 | L8: =IF(I8=0,"",K8/I8*100)
K9: =J9-I9 | L9: =IF(I9=0,"",K9/I9*100)
K10: =J10-I10 | L10: =IF(I10=0,"",K10/I10*100)
K11: =J11-I11 | L11: =IF(I11=0,"",K11/I11*100)
K12: =J12-I12 | L12: =IF(I12=0,"",K12/I12*100)
K13: =J13-I13 | L13: =IF(I13=0,"",K13/I13*100)
K14: =J14-I14 | L14: =IF(I14=0,"",K14/I14*100)
K15: =J15-I15 | L15: =IF(I15=0,"",K15/I15*100)
K16: =J16-I16 | L16: =IF(I16=0,"",K16/I16*100)
K17: =J17-I17 | L17: =IF(I17=0,"",K17/I17*100)
... K29: =J29-I29 | L29: =IF(I29=0,"",K29/I29*100)
A30: 合计1 | B30: 合 计 | H30: =ROUND(SUM(H6:H29),2) | I30: =ROUND(SUM(I6:I29),2) | J30: =ROUND(SUM(J6:J29),2) | K30: =J30-I30 | L30: =IF(I30=0,"",K30/I30*100)
C32: 注：
C33: 只有待售资产的种类较多，本表涉及仅以待售资产为设备类资产为例。若待售资产为自用房产等，请相应修改参数。

Sheet 3-12一年到期非流动资产
A1: 表头区域 | B1: 一年内到期的非流动资产评估明细表
A2: 表头区域 | B2: ='2-分类汇总'!B2
A3: 表头区域 | J3: 表3-12
A4: 表头区域 | B4: ='2-分类汇总'!B4 | J4: ='2-分类汇总'!H4
A5: 检索表头 | B5: 序号 | C5: 项目及内容 | D5: 发生日期 | E5: 结算内容 | F5: 账面价值 | G5: 评估价值 | H5: 增值额 | I5: 增值率% | J5: 备注
H6: =G6-F6 | I6: =IF(F6=0,"",H6/F6*100)
H7: =G7-F7 | I7: =IF(F7=0,"",H7/F7*100)
H8: =G8-F8 | I8: =IF(F8=0,"",H8/F8*100)
H9: =G9-F9 | I9: =IF(F9=0,"",H9/F9*100)
H10: =G10-F10 | I10: =IF(F10=0,"",H10/F10*100)
H11: =G11-F11 | I11: =IF(F11=0,"",H11/F11*100)
H12: =G12-F12 | I12: =IF(F12=0,"",H12/F12*100)
H13: =G13-F13 | I13: =IF(F13=0,"",H13/F13*100)
H14: =G14-F14 | I14: =IF(F14=0,"",H14/F14*100)
H15: =G15-F15 | I15: =IF(F15=0,"",H15/F15*100)
H16: =G16-F16 | I16: =IF(F16=0,"",H16/F16*100)
H17: =G17-F17 | I17: =IF(F17=0,"",H17/F17*100)
... H27: =G27-F27 | I27: =IF(F27=0,"",H27/F27*100)
A28: 合计1 | B28: 合 计 | F28: =SUM(F6:F27) | G28: =SUM(G6:G27) | H28: =G28-F28 | I28: =IF(F28=0,"",H28/F28*100)

Sheet 3-13其他流动资产
A1: 表头区域 | B1: 其他流动资产评估明细表
A2: 表头区域 | B2: ='2-分类汇总'!B2
A3: 表头区域 | K3: 表3-13
A4: 表头区域 | B4: ='2-分类汇总'!B4 | K4: ='2-分类汇总'!H4
A5: 检索表头 | B5: 序号 | C5: 项目及内容 | D5: 发生日期 | E5: 结算内容 | F5: 成本 | G5: 账面价值 | H5: 评估价值 | I5: 增值额 | J5: 增值率% | K5: 备注
I6: =H6-G6 | J6: =IF(G6=0,"",I6/G6*100)
I7: =H7-G7 | J7: =IF(G7=0,"",I7/G7*100)
I8: =H8-G8 | J8: =IF(G8=0,"",I8/G8*100)
I9: =H9-G9 | J9: =IF(G9=0,"",I9/G9*100)
I10: =H10-G10 | J10: =IF(G10=0,"",I10/G10*100)
I11: =H11-G11 | J11: =IF(G11=0,"",I11/G11*100)
I12: =H12-G12 | J12: =IF(G12=0,"",I12/G12*100)
I13: =H13-G13 | J13: =IF(G13=0,"",I13/G13*100)
I14: =H14-G14 | J14: =IF(G14=0,"",I14/G14*100)
I15: =H15-G15 | J15: =IF(G15=0,"",I15/G15*100)
I16: =H16-G16 | J16: =IF(G16=0,"",I16/G16*100)
I17: =H17-G17 | J17: =IF(G17=0,"",I17/G17*100)
... I27: =H27-G27 | J27: =IF(G27=0,"",I27/G27*100)
A28: 合计1 | B28: 合 计 | F28: =ROUND(SUM(F6:F27),2) | G28: =ROUND(SUM(G6:G27),2) | H28: =ROUND(SUM(H6:H27),2) | I28: =H28-G28 | J28: =IF(G28=0,"",I28/G28*100)

Sheet 4-非流动资产汇总
B1: 非流动资产评估汇总表
B2: ='2-分类汇总'!B2
H3: 表4
B4: ='2-分类汇总'!B4 | H4: ='2-分类汇总'!H4
B5: 编号 | C5: 项目编号 | D5: 科目名称 | E5: 账面价值 | F5: 评估价值 | G5: 增值额 | H5: 增值率%
B6: 4-1 | C6: 债权投资 | D6: 债权投资 | E6: ='4-1债权投资'!I28 | F6: ='4-1债权投资'!J28 | G6: =F6-E6 | H6: =IF(E6=0,"",G6/E6*100)
B7: 4-2 | C7: 其他债权 | D7: 其他债权投资 | E7: ='4-2其他债权投资'!I28 | F7: ='4-2其他债权投资'!J28 | G7: =F7-E7 | H7: =IF(E7=0,"",G7/E7*100)
B8: 4-3 | C8: 长期应收 | D8: 长期应收款 | E8: ='4-3长期应收'!F28 | F8: ='4-3长期应收'!G28 | G8: =F8-E8 | H8: =IF(E8=0,"",G8/E8*100)
B9: 4-4 | C9: 长期股权 | D9: 长期股权投资 | E9: ='4-4股权投资'!H29 | F9: ='4-4股权投资'!I29 | G9: =F9-E9 | H9: =IF(E9=0,"",G9/E9*100)
B10: 4-5 | C10: 其他权投 | D10: 其他权益工具投资 | E10: ='4-5其他权益工具投资'!G29 | F10: ='4-5其他权益工具投资'!H29 | G10: =F10-E10 | H10: =IF(E10=0,"",G10/E10*100)
B11: 4-6 | C11: 其他非金 | D11: 其他非流动金融资产 | E11: ='4-6其他非流动金融资产汇总'!E24 | F11: ='4-6其他非流动金融资产汇总'!F24 | G11: =F11-E11 | H11: =IF(E11=0,"",G11/E11*100)
B12: 4-7 | C12: 投房汇总 | D12: 投资性房地产 | E12: ='4-7-1投资性房地产'!L29+'4-7-2投资性房地产'!L26+'4-7-3投资性地产'!N29+'4-7-4投资性地产'!N29 | F12: ='4-7-1投资性房地产'!O29+'4-7-2投资性房地产'!M26+'4-7-3投资性地产'!O29+'4-7-4投资性地产'!O29 | G12: =F12-E12 | H12: =IF(E12=0,"",G12/E12*100)
B13: 4-8 | C13: 固资汇总 | D13: 固定资产 | E13: ='4-8固定资产汇总'!F20 | F13: ='4-8固定资产汇总'!H20 | G13: =F13-E13 | H13: =IF(E13=0,"",G13/E13*100)
B14: 4-9 | C14: 在建汇总 | D14: 在建工程 | E14: ='4-9在建工程汇总'!E25 | F14: ='4-9在建工程汇总'!F25 | G14: =F14-E14 | H14: =IF(E14=0,"",G14/E14*100)
B15: 4-10 | C15: 生物资产 | D15: 生产性生物资产 | E15: ='4-10生产性生物资产'!I27 | F15: ='4-10生产性生物资产'!L27 | G15: =F15-E15 | H15: =IF(E15=0,"",G15/E15*100)
B16: 4-11 | C16: 油气资产 | D16: 油气资产 | E16: ='4-11油气资产'!J28 | F16: ='4-11油气资产'!M28 | G16: =F16-E16 | H16: =IF(E16=0,"",G16/E16*100)
B17: 4-12 | C17: 使用资产 | D17: 使用权资产 | E17: ='4-12使用权资产'!G30 | F17: ='4-12使用权资产'!H30 | G17: =F17-E17 | H17: =IF(E17=0,"",G17/E17*100)
B18: 4-13 | C18: 无形汇总 | D18: 无形资产 | E18: ='4-13无形资产汇总'!E24 | F18: ='4-13无形资产汇总'!F24 | G18: =F18-E18 | H18: =IF(E18=0,"",G18/E18*100)
B19: 4-14 | C19: 开发支出 | D19: 开发支出 | E19: ='4-14开发支出'!E27 | F19: ='4-14开发支出'!F27 | G19: =F19-E19 | H19: =IF(E19=0,"",G19/E19*100)
B20: 4-15 | C20: 商誉资产 | D20: 商誉 | E20: ='4-15商誉'!E26 | F20: ='4-15商誉'!F26 | G20: =F20-E20 | H20: =IF(E20=0,"",G20/E20*100)
B21: 4-16 | C21: 长期待摊 | D21: 长期待摊费用 | E21: ='4-16长期待摊费用'!G29 | F21: ='4-16长期待摊费用'!I29 | G21: =F21-E21 | H21: =IF(E21=0,"",G21/E21*100)
B22: 4-17 | C22: 递延资产 | D22: 递延所得税资产 | E22: ='4-17递延所得税资产'!E28 | F22: ='4-17递延所得税资产'!F28 | G22: =F22-E22 | H22: =IF(E22=0,"",G22/E22*100)
B23: 4-18 | C23: 其他非资 | D23: 其他非流动资产 | E23: ='4-18其他非流动资产'!E28 | F23: ='4-18其他非流动资产'!F28 | G23: =F23-E23 | H23: =IF(E23=0,"",G23/E23*100)
G24: =F24-E24 | H24: =IF(E24=0,"",G24/E24*100)
G25: =F25-E25 | H25: =IF(E25=0,"",G25/E25*100)
G26: =F26-E26 | H26: =IF(E26=0,"",G26/E26*100)
A27: 合计1 | C27: 非资汇总 | D27: 合 计 | E27: =SUM(E6:E26) | F27: =SUM(F6:F26) | G27: =F27-E27 | H27: =IF(E27=0,"",G27/E27*100)

Sheet 4-1债权投资
A1: 表头区域 | B1: 债权投资评估明细表
A2: 表头区域 | B2: ='2-分类汇总'!B2
A3: 表头区域 | M3: 表4-1
A4: 表头区域 | B4: ='2-分类汇总'!B4 | M4: ='2-分类汇总'!H4
A5: 检索表头 | B5: 序号 | C5: 被投资单位名称 | D5: 债券种类 | E5: 发行日期 | F5: 到期日 | G5: 利率% | H5: 成本（面值） | I5: 账面价值 | J5: 评估价值 | K5: 增值额 | L5: 增值率% | M5: 备注
K6: =J6-I6 | L6: =IF(I6=0,"",K6/I6*100)
K7: =J7-I7 | L7: =IF(I7=0,"",K7/I7*100)
K8: =J8-I8 | L8: =IF(I8=0,"",K8/I8*100)
K9: =J9-I9 | L9: =IF(I9=0,"",K9/I9*100)
K10: =J10-I10 | L10: =IF(I10=0,"",K10/I10*100)
K11: =J11-I11 | L11: =IF(I11=0,"",K11/I11*100)
K12: =J12-I12 | L12: =IF(I12=0,"",K12/I12*100)
K13: =J13-I13 | L13: =IF(I13=0,"",K13/I13*100)
K14: =J14-I14 | L14: =IF(I14=0,"",K14/I14*100)
K15: =J15-I15 | L15: =IF(I15=0,"",K15/I15*100)
K16: =J16-I16 | L16: =IF(I16=0,"",K16/I16*100)
K17: =J17-I17 | L17: =IF(I17=0,"",K17/I17*100)
... K25: =J25-I25 | L25: =IF(I25=0,"",K25/I25*100)
A26: 合计1 | B26: 合 计 | H26: =ROUND(SUM(H6:H25),2) | I26: =ROUND(SUM(I6:I25),2) | J26: =ROUND(SUM(J6:J25),2) | K26: =J26-I26 | L26: =IF(I26=0,"",K26/I26*100)
A27: 坏账准备 | B27: 减：减值准备 | K27: =J27-I27 | L27: =IF(I27=0,"",K27/I27*100)
A28: 合计2 | B28: 合 计 | H28: =H26-H27 | I28: =I26-I27 | J28: =J26-J27 | K28: =J28-I28 | L28: =IF(I28=0,"",K28/I28*100)

Sheet 4-2其他债权投资
A1: 表头区域 | B1: 其他债权投资评估明细表
A2: 表头区域 | B2: 评估基准日：2018年5月31日
A3: 表头区域 | M3: 表4-2
A4: 表头区域 | B4: 被评估单位：ABC公司 | M4: ='2-分类汇总'!H4
A5: 检索表头 | B5: 序号 | C5: 被投资单位名称 | D5: 债券种类 | E5: 发行日期 | F5: 到期日 | G5: 票面利率% | H5: 成本（面值） | I5: 账面价值 | J5: 评估价值 | K5: 增值额 | L5: 增值率% | M5: 备注
K6: =J6-I6 | L6: =IF(I6=0,"",K6/I6*100)
K7: =J7-I7 | L7: =IF(I7=0,"",K7/I7*100)
K8: =J8-I8 | L8: =IF(I8=0,"",K8/I8*100)
K9: =J9-I9 | L9: =IF(I9=0,"",K9/I9*100)
K10: =J10-I10 | L10: =IF(I10=0,"",K10/I10*100)
K11: =J11-I11 | L11: =IF(I11=0,"",K11/I11*100)
K12: =J12-I12 | L12: =IF(I12=0,"",K12/I12*100)
K13: =J13-I13 | L13: =IF(I13=0,"",K13/I13*100)
K14: =J14-I14 | L14: =IF(I14=0,"",K14/I14*100)
K15: =J15-I15 | L15: =IF(I15=0,"",K15/I15*100)
K16: =J16-I16 | L16: =IF(I16=0,"",K16/I16*100)
K17: =J17-I17 | L17: =IF(I17=0,"",K17/I17*100)
... K25: =J25-I25 | L25: =IF(I25=0,"",K25/I25*100)
A26: 合计1 | B26: 合 计 | H26: =ROUND(SUM(H6:H25),2) | I26: =ROUND(SUM(I6:I25),2) | J26: =ROUND(SUM(J6:J25),2) | K26: =J26-I26 | L26: =IF(I26=0,"",K26/I26*100)
A27: 坏账准备 | B27: 减：减值准备 | K27: =J27-I27 | L27: =IF(I27=0,"",K27/I27*100)
A28: 合计2 | B28: 合 计 | H28: =H26-H27 | I28: =I26-I27 | J28: =J26-J27 | K28: =J28-I28 | L28: =IF(I28=0,"",K28/I28*100)

Sheet 4-3长期应收
A1: 表头区域 | B1: 长期应收款评估明细表
A2: 表头区域 | B2: ='2-分类汇总'!B2
A3: 表头区域 | I3: 表4-3
A4: 表头区域 | B4: ='2-分类汇总'!B4 | J4: ='2-分类汇总'!H4
A5: 检索表头 | B5: 序号 | C5: 欠款单位名称（结算对象) | D5: 业务内容 | E5: 发生日期 | F5: 账面价值 | G5: 评估价值 | H5: 增值额 | I5: 增值率% | J5: 备注
H6: =G6-F6 | I6: =IF(F6=0,"",H6/F6*100)
H7: =G7-F7 | I7: =IF(F7=0,"",H7/F7*100)
H8: =G8-F8 | I8: =IF(F8=0,"",H8/F8*100)
H9: =G9-F9 | I9: =IF(F9=0,"",H9/F9*100)
H10: =G10-F10 | I10: =IF(F10=0,"",H10/F10*100)
H11: =G11-F11 | I11: =IF(F11=0,"",H11/F11*100)
H12: =G12-F12 | I12: =IF(F12=0,"",H12/F12*100)
H13: =G13-F13 | I13: =IF(F13=0,"",H13/F13*100)
H14: =G14-F14 | I14: =IF(F14=0,"",H14/F14*100)
H15: =G15-F15 | I15: =IF(F15=0,"",H15/F15*100)
H16: =G16-F16 | I16: =IF(F16=0,"",H16/F16*100)
H17: =G17-F17 | I17: =IF(F17=0,"",H17/F17*100)
... H25: =G25-F25 | I25: =IF(F25=0,"",H25/F25*100)
A26: 合计1 | B26: 合 计 | F26: =ROUND(SUM(F6:F25),2) | G26: =ROUND(SUM(G6:G25),2) | H26: =G26-F26 | I26: =IF(F26=0,"",H26/F26*100)
A27: 坏账准备 | B27: 减：长期应收款坏账准备 | H27: =G27-F27 | I27: =IF(F27=0,"",H27/F27*100)
A28: 合计2 | B28: 合 计 | F28: =F26-F27 | G28: =G26-G27 | H28: =G28-F28 | I28: =IF(F28=0,"",H28/F28*100)

Sheet 4-4股权投资
A1: 表头区域 | B1: 长期股权投资评估明细表
A2: 表头区域 | B2: ='2-分类汇总'!B2
A3: 表头区域 | K3: 表4-4
A4: 表头区域 | B4: ='2-分类汇总'!B4 | L4: ='2-分类汇总'!H4
A5: 检索表头 | B5: 序号 | C5: 被投资单位名称 | D5: 投资日期 | E5: 协议投资期限 | F5: 持股比例（%） | G5: 投资成本 | H5: 账面价值 | I5: 评估价值 | J5: 增值额 | K5: 增值率% | L5: 备注
J6: =I6-H6 | K6: =IF(H6=0,"",J6/H6*100)
J7: =I7-H7 | K7: =IF(H7=0,"",J7/H7*100)
J8: =I8-H8 | K8: =IF(H8=0,"",J8/H8*100)
J9: =I9-H9 | K9: =IF(H9=0,"",J9/H9*100)
J10: =I10-H10 | K10: =IF(H10=0,"",J10/H10*100)
J11: =I11-H11 | K11: =IF(H11=0,"",J11/H11*100)
J12: =I12-H12 | K12: =IF(H12=0,"",J12/H12*100)
J13: =I13-H13 | K13: =IF(H13=0,"",J13/H13*100)
J14: =I14-H14 | K14: =IF(H14=0,"",J14/H14*100)
J15: =I15-H15 | K15: =IF(H15=0,"",J15/H15*100)
J16: =I16-H16 | K16: =IF(H16=0,"",J16/H16*100)
J17: =I17-H17 | K17: =IF(H17=0,"",J17/H17*100)
... J26: =I26-H26 | K26: =IF(H26=0,"",J26/H26*100)
A27: 合计1 | B27: 合 计 | G27: =ROUND(SUM(G6:G26),2) | H27: =ROUND(SUM(H6:H26),2) | I27: =ROUND(SUM(I6:I26),2) | J27: =I27-H27 | K27: =IF(H27=0,"",J27/H27*100)
A28: 坏账准备 | B28: 减：长期股权投资减值准备 | J28: =I28-H28 | K28: =IF(H28=0,"",J28/H28*100)
A29: 合计2 | B29: 合 计 | G29: =G27-G28 | H29: =H27-H28 | I29: =I27-I28 | J29: =I29-H29 | K29: =IF(H29=0,"",J29/H29*100)

Sheet 4-5其他权益工具投资
A1: 表头区域 | B1: 其他权益工具投资评估明细表
A2: 表头区域 | B2: ='2-分类汇总'!B2
A3: 表头区域 | J3: 表4-5
A4: 表头区域 | B4: ='2-分类汇总'!B4 | K4: ='2-分类汇总'!H4
A5: 检索表头 | B5: 序号 | C5: 被投资单位名称 | D5: 投资日期 | E5: 投资数量 | F5: 投资成本 | G5: 账面价值 | H5: 评估价值 | I5: 增值额 | J5: 增值率% | K5: 备注
I6: =H6-G6 | J6: =IF(G6=0,"",I6/G6*100)
I7: =H7-G7 | J7: =IF(G7=0,"",I7/G7*100)
I8: =H8-G8 | J8: =IF(G8=0,"",I8/G8*100)
I9: =H9-G9 | J9: =IF(G9=0,"",I9/G9*100)
I10: =H10-G10 | J10: =IF(G10=0,"",I10/G10*100)
I11: =H11-G11 | J11: =IF(G11=0,"",I11/G11*100)
I12: =H12-G12 | J12: =IF(G12=0,"",I12/G12*100)
I13: =H13-G13 | J13: =IF(G13=0,"",I13/G13*100)
I14: =H14-G14 | J14: =IF(G14=0,"",I14/G14*100)
I15: =H15-G15 | J15: =IF(G15=0,"",I15/G15*100)
I16: =H16-G16 | J16: =IF(G16=0,"",I16/G16*100)
I17: =H17-G17 | J17: =IF(G17=0,"",I17/G17*100)
... I26: =H26-G26 | J26: =IF(G26=0,"",I26/G26*100)
A27: 合计1 | B27: 合 计 | F27: =ROUND(SUM(F6:F26),2) | G27: =ROUND(SUM(G6:G26),2) | H27: =ROUND(SUM(H6:H26),2) | I27: =H27-G27 | J27: =IF(G27=0,"",I27/G27*100)
A28: 坏账准备 | B28: 减：减值准备 | I28: =H28-G28 | J28: =IF(G28=0,"",I28/G28*100)
A29: 合计2 | B29: 合 计 | F29: =F27-F28 | G29: =G27-G28 | H29: =H27-H28 | I29: =H29-G29 | J29: =IF(G29=0,"",I29/G29*100)

Sheet 4-6其他非流动金融资产汇总
B1: 其他非流动金融资产评估汇总表
B2: ='2-分类汇总'!B2
H3: 表4-6
B4: ='2-分类汇总'!B4 | H4: ='2-分类汇总'!H4
B5: 编号 | C5: 项目编号 | D5: 科目名称 | E5: 账面价值 | F5: 评估价值 | G5: 增值额 | H5: 增值率%
B6: 4-6-1 | C6: 可售股票 | D6: 其他非流动金融资产-股票投资 | E6: ='4-6-1-股票'!H29 | F6: ='4-6-1-股票'!J29 | G6: =F6-E6 | H6: =IF(E6=0,"",G6/E6*100)
B7: 4-6-2 | C7: 可售债券 | D7: 其他非流动金融资产-债券投资 | E7: ='4-6-2-债券'!I29 | F7: ='4-6-2-债券'!J29 | G7: =F7-E7 | H7: =IF(E7=0,"",G7/E7*100)
B8: 4-6-3 | C8: 可售其他 | D8: 其他非流动金融资产-基金投资 | E8: ='4-6-3-基金'!H31 | F8: ='4-6-3-基金'!J31 | G8: =F8-E8 | H8: =IF(E8=0,"",G8/E8*100)
A24: 合计1 | C24: 可售汇总 | D24: 合 计 | E24: =SUM(E6:E23) | F24: =SUM(F6:F23) | G24: =F24-E24 | H24: =IF(E24=0,"",G24/E24*100)

Sheet 4-6-1-股票
A1: 表头区域 | B1: 其他非流动金融资产金融资产—股票投资评估明细表
A2: 表头区域 | B2: ='2-分类汇总'!B2
A3: 表头区域 | L3: 表4-6-1
A4: 表头区域 | B4: ='2-分类汇总'!B4 | M4: ='2-分类汇总'!H4
A5: 检索表头 | B5: 序号 | C5: 被投资单位名称 | D5: 股票名称 | E5: 投资日期 | F5: 持股数量 | G5: 成 本 | H5: 账面价值 | I5: 基准日收盘价元/股 | J5: 评估价值 | K5: 增值额 | L5: 增值率% | M5: 备注
K6: =J6-H6 | L6: =IF(H6=0,"",K6/H6*100)
K7: =J7-H7 | L7: =IF(H7=0,"",K7/H7*100)
K8: =J8-H8 | L8: =IF(H8=0,"",K8/H8*100)
K9: =J9-H9 | L9: =IF(H9=0,"",K9/H9*100)
K10: =J10-H10 | L10: =IF(H10=0,"",K10/H10*100)
K11: =J11-H11 | L11: =IF(H11=0,"",K11/H11*100)
K12: =J12-H12 | L12: =IF(H12=0,"",K12/H12*100)
K13: =J13-H13 | L13: =IF(H13=0,"",K13/H13*100)
K14: =J14-H14 | L14: =IF(H14=0,"",K14/H14*100)
K15: =J15-H15 | L15: =IF(H15=0,"",K15/H15*100)
K16: =J16-H16 | L16: =IF(H16=0,"",K16/H16*100)
K17: =J17-H17 | L17: =IF(H17=0,"",K17/H17*100)
... K28: =J28-H28 | L28: =IF(H28=0,"",K28/H28*100)
A29: 合计1 | B29: 合 计 | G29: =ROUND(SUM(G6:G28),2) | H29: =ROUND(SUM(H6:H28),2) | J29: =ROUND(SUM(J6:J28),2) | K29: =J29-H29 | L29: =IF(H29=0,"",K29/H29*100)

Sheet 4-6-2-债券
A1: 表头区域 | B1: 其他非流动金融资产—债券投资评估明细表
A2: 表头区域 | B2: ='2-分类汇总'!B2
A3: 表头区域 | L3: 表4-6-2
A4: 表头区域 | B4: ='2-分类汇总'!B4 | M4: ='2-分类汇总'!H4
A5: 检索表头 | B5: 序号 | C5: 被投资单位名称 | D5: 债券名称 | E5: 发行日期 | F5: 投资日期 | G5: 票面利率% | H5: 成本 | I5: 账面价值 | J5: 评估价值 | K5: 增值额 | L5: 增值率% | M5: 备注
K6: =J6-I6 | L6: =IF(I6=0,"",K6/I6*100)
K7: =J7-I7 | L7: =IF(I7=0,"",K7/I7*100)
K8: =J8-I8 | L8: =IF(I8=0,"",K8/I8*100)
K9: =J9-I9 | L9: =IF(I9=0,"",K9/I9*100)
K10: =J10-I10 | L10: =IF(I10=0,"",K10/I10*100)
K11: =J11-I11 | L11: =IF(I11=0,"",K11/I11*100)
K12: =J12-I12 | L12: =IF(I12=0,"",K12/I12*100)
K13: =J13-I13 | L13: =IF(I13=0,"",K13/I13*100)
K14: =J14-I14 | L14: =IF(I14=0,"",K14/I14*100)
K15: =J15-I15 | L15: =IF(I15=0,"",K15/I15*100)
K16: =J16-I16 | L16: =IF(I16=0,"",K16/I16*100)
K17: =J17-I17 | L17: =IF(I17=0,"",K17/I17*100)
... K28: =J28-I28 | L28: =IF(I28=0,"",K28/I28*100)
A29: 合计1 | B29: 合 计 | H29: =ROUND(SUM(H6:H28),2) | I29: =ROUND(SUM(I6:I28),2) | J29: =ROUND(SUM(J6:J28),2) | K29: =J29-I29 | L29: =IF(I29=0,"",K29/I29*100)

Sheet 4-6-3-基金
A1: 表头区域 | B1: 其他非流动金融资产—基金投资评估明细表
A2: 表头区域 | B2: ='2-分类汇总'!B2
A3: 表头区域 | L3: 表4-6-3
A4: 表头区域 | B4: ='2-分类汇总'!B4 | M4: ='2-分类汇总'!H4
A5: 检索表头 | B5: 序号 | C5: 基金发行单位 | D5: 基金名称 | E5: 基金类型 | F5: 投资日期 | G5: 成本 | H5: 账面价值 | I5: 基准日净值/份 | J5: 评估价值 | K5: 增值额 | L5: 增值率% | M5: 备注
K6: =J6-H6 | L6: =IF(H6=0,"",K6/H6*100)
K7: =J7-H7 | L7: =IF(H7=0,"",K7/H7*100)
K8: =J8-H8 | L8: =IF(H8=0,"",K8/H8*100)
K9: =J9-H9 | L9: =IF(H9=0,"",K9/H9*100)
K10: =J10-H10 | L10: =IF(H10=0,"",K10/H10*100)
K11: =J11-H11 | L11: =IF(H11=0,"",K11/H11*100)
K12: =J12-H12 | L12: =IF(H12=0,"",K12/H12*100)
K13: =J13-H13 | L13: =IF(H13=0,"",K13/H13*100)
K14: =J14-H14 | L14: =IF(H14=0,"",K14/H14*100)
K15: =J15-H15 | L15: =IF(H15=0,"",K15/H15*100)
K16: =J16-H16 | L16: =IF(H16=0,"",K16/H16*100)
K17: =J17-H17 | L17: =IF(H17=0,"",K17/H17*100)
... K30: =J30-H30 | L30: =IF(H30=0,"",K30/H30*100)
A31: 合计1 | B31: 合 计 | G31: =ROUND(SUM(G6:G30),2) | H31: =ROUND(SUM(H6:H30),2) | J31: =ROUND(SUM(J6:J30),2) | K31: =J31-H31 | L31: =IF(H31=0,"",K31/H31*100)

Sheet 4-7投资性房地产汇总
B1: 投资性房地产评估汇总表
B2: ='2-分类汇总'!B2
H3: 表4-7
B4: ='2-分类汇总'!B4 | H4: ='2-分类汇总'!H4
B5: 编号 | C5: 项目编号 | D5: 科目名称 | E5: 账面价值 | F5: 评估价值 | G5: 增值额 | H5: 增值率%
B6: 4-7-1 | C6: 投房房成 | D6: 投资性房地产——房屋(成本) | E6: ='4-7-1投资性房地产'!L29 | F6: ='4-7-1投资性房地产'!O29 | G6: =F6-E6 | H6: =IF(E6=0,"",ROUND(G6/E6*100,2))
B7: 4-7-2 | C7: 投房房公 | D7: 投资性房地产——房屋(公允) | E7: ='4-7-2投资性房地产'!L26 | F7: ='4-7-2投资性房地产'!M26 | G7: =F7-E7 | H7: =IF(E7=0,"",ROUND(G7/E7*100,2))
B8: 4-7-3 | C8: 投房土成 | D8: 投资性房地产——土地使用权(成本) | E8: ='4-7-3投资性地产'!N29 | F8: ='4-7-3投资性地产'!O29 | G8: =F8-E8 | H8: =IF(E8=0,"",ROUND(G8/E8*100,2))
B9: 4-7-4 | C9: 投房土公 | D9: 投资性房地产——土地使用权(公允) | E9: ='4-7-4投资性地产'!N29 | F9: ='4-7-4投资性地产'!O29 | G9: =F9-E9 | H9: =IF(E9=0,"",ROUND(G9/E9*100,2))
H18: =IF(E18=0,"",ROUND(G18/E18*100,2))
C19: 投房汇总
C20: 投房准备
A21: 合计1 | C21: 投房净额 | D21: 投资性房地产合计 | E21: =SUM(E6:E20) | F21: =SUM(F6:F20) | G21: =F21-E21 | H21: =IF(E21=0,"",ROUND(G21/E21*100,2))

Sheet 4-7-1投资性房地产
A1: 表头区域 | B1: 投资性房地产——房屋评估明细表
A2: 表头区域 | B2: （采用成本模式计量）
A3: 表头区域 | B3: ='2-分类汇总'!B2
A4: 表头区域 | P4: 表4-7
A5: 表头区域 | B5: ='2-分类汇总'!B4 | R5: ='2-分类汇总'!H4
A6: 检索表头1 | B6: 序号 | C6: 权证编号 | D6: 房屋名称 | E6: 来源 | F6: 结构 | G6: 建成 年月 | H6: 计量单位 | I6: 建筑面积 | J6: 成本单价(元/m2) | K6: 账面价值 | M6: 评估价值 | P6: 增值额 | Q6: 增值率% | R6: 备注
A7: 检索表头2 | K7: 原值 | L7: 净值 | M7: 原值 | N7: 成新率% | O7: 净值
O8: =ROUND(M8*N8/100,-2) | P8: =O8-L8 | Q8: =IF(L8=0,"",P8/L8*100)
O9: =ROUND(M9*N9/100,-2) | P9: =O9-L9 | Q9: =IF(L9=0,"",P9/L9*100)
O10: =ROUND(M10*N10/100,-2) | P10: =O10-L10 | Q10: =IF(L10=0,"",P10/L10*100)
O11: =ROUND(M11*N11/100,-2) | P11: =O11-L11 | Q11: =IF(L11=0,"",P11/L11*100)
O12: =ROUND(M12*N12/100,-2) | P12: =O12-L12 | Q12: =IF(L12=0,"",P12/L12*100)
O13: =ROUND(M13*N13/100,-2) | P13: =O13-L13 | Q13: =IF(L13=0,"",P13/L13*100)
O14: =ROUND(M14*N14/100,-2) | P14: =O14-L14 | Q14: =IF(L14=0,"",P14/L14*100)
O15: =ROUND(M15*N15/100,-2) | P15: =O15-L15 | Q15: =IF(L15=0,"",P15/L15*100)
O16: =ROUND(M16*N16/100,-2) | P16: =O16-L16 | Q16: =IF(L16=0,"",P16/L16*100)
O17: =ROUND(M17*N17/100,-2) | P17: =O17-L17 | Q17: =IF(L17=0,"",P17/L17*100)
O18: =ROUND(M18*N18/100,-2) | P18: =O18-L18 | Q18: =IF(L18=0,"",P18/L18*100)
O19: =ROUND(M19*N19/100,-2) | P19: =O19-L19 | Q19: =IF(L19=0,"",P19/L19*100)
... O26: =ROUND(M26*N26/100,-2) | P26: =O26-L26 | Q26: =IF(L26=0,"",P26/L26*100)
A27: 合计1 | B27: 合 计 | I27: =ROUND(SUM(I8:I26),2) | K27: =ROUND(SUM(K8:K26),2) | L27: =ROUND(SUM(L8:L26),2) | M27: =ROUND(SUM(M8:M26),2) | O27: =ROUND(SUM(O8:O26),2) | P27: =O27-L27 | Q27: =IF(L27=0,"",P27/L27*100)
A28: 坏账准备 | B28: 减：投资性房地产减值准备 | P28: =O28-L28 | Q28: =IF(L28=0,"",P28/L28*100)
A29: 合计2 | B29: 合 计 | I29: =I27-I28 | K29: =K27-K28 | L29: =L27-L28 | M29: =M27-M28 | O29: =O27-O28 | P29: =O29-L29 | Q29: =IF(L29=0,"",P29/L29*100)

Sheet 4-7-2投资性房地产
A1: 表头区域 | B1: 投资性房地产——房屋评估明细表
A2: 表头区域 | B2: （采用公允价值模式计量）
A3: 表头区域 | B3: ='2-分类汇总'!B2
A4: 表头区域 | P4: 表4-7
A5: 表头区域 | B5: ='2-分类汇总'!B4 | P5: ='2-分类汇总'!H4
A6: 检索表头1 | B6: 序号 | C6: 权证编号 | D6: 房屋名称 | E6: 来源 | F6: 结构 | G6: 建成 年月 | H6: 计量单位 | I6: 建筑 面积 | J6: 成本单价(元/m2) | K6: 原始入帐价值 （转入日公允价值） | L6: 账面价值 | M6: 评估价值 | N6: 增值额 | O6: 增值率% | P6: 备注
A7: 检索表头2
N8: =M8-L8 | O8: =IF(L8=0,"",N8/L8*100)
N9: =M9-L9 | O9: =IF(L9=0,"",N9/L9*100)
N10: =M10-L10 | O10: =IF(L10=0,"",N10/L10*100)
N11: =M11-L11 | O11: =IF(L11=0,"",N11/L11*100)
N12: =M12-L12 | O12: =IF(L12=0,"",N12/L12*100)
N13: =M13-L13 | O13: =IF(L13=0,"",N13/L13*100)
N14: =M14-L14 | O14: =IF(L14=0,"",N14/L14*100)
N15: =M15-L15 | O15: =IF(L15=0,"",N15/L15*100)
N16: =M16-L16 | O16: =IF(L16=0,"",N16/L16*100)
N17: =M17-L17 | O17: =IF(L17=0,"",N17/L17*100)
N18: =M18-L18 | O18: =IF(L18=0,"",N18/L18*100)
N19: =M19-L19 | O19: =IF(L19=0,"",N19/L19*100)
... N23: =M23-L23 | O23: =IF(L23=0,"",N23/L23*100)
A24: 合计1 | B24: 合 计 | I24: =SUM(I6:I23) | K24: =SUM(K6:K23) | L24: =SUM(L6:L23) | M24: =SUM(M6:M23) | N24: =M24-L24 | O24: =IF(L24=0,"",N24/L24*100)
A25: 坏账准备 | B25: 减：投资性房地产减值准备 | N25: =M25-L25 | O25: =IF(L25=0,"",N25/L25*100)
A26: 合计2 | B26: 合 计 | I26: =I24-I25 | K26: =K24-K25 | L26: =L24-L25 | M26: =M24-M25 | N26: =M26-L26 | O26: =IF(L26=0,"",N26/L26*100)

Sheet 4-7-3投资性地产
A1: 表头区域 | B1: 投资性房地产——土地使用权评估明细表
A2: 表头区域 | B2: （采用成本模式计量）
A3: 表头区域 | B3: ='2-分类汇总'!B2
A4: 表头区域 | Q4: 表4-7
A5: 表头区域 | B5: ='2-分类汇总'!B4 | R5: ='2-分类汇总'!H4
A6: 检索表头 | B6: 序号 | C6: 土地权证编号 | D6: 宗地名称 | E6: 来源 | F6: 土地位置 | G6: 取得日期 | H6: 用地性质 | I6: 土地用途 | J6: 准用年限 | K6: 开发程度 | L6: 面积(m2) | M6: 原始入账价值 | N6: 账面价值 | O6: 评估价值 | P6: 增值额 | Q6: 增值率% | R6: 备注
P7: =O7-N7 | Q7: =IF(N7=0,"",P7/N7*100)
P8: =O8-N8 | Q8: =IF(N8=0,"",P8/N8*100)
P9: =O9-N9 | Q9: =IF(N9=0,"",P9/N9*100)
P10: =O10-N10 | Q10: =IF(N10=0,"",P10/N10*100)
P11: =O11-N11 | Q11: =IF(N11=0,"",P11/N11*100)
P12: =O12-N12 | Q12: =IF(N12=0,"",P12/N12*100)
P13: =O13-N13 | Q13: =IF(N13=0,"",P13/N13*100)
P14: =O14-N14 | Q14: =IF(N14=0,"",P14/N14*100)
P15: =O15-N15 | Q15: =IF(N15=0,"",P15/N15*100)
P16: =O16-N16 | Q16: =IF(N16=0,"",P16/N16*100)
P17: =O17-N17 | Q17: =IF(N17=0,"",P17/N17*100)
P18: =O18-N18 | Q18: =IF(N18=0,"",P18/N18*100)
... P26: =O26-N26 | Q26: =IF(N26=0,"",P26/N26*100)
A27: 合计1 | B27: 合 计 | L27: =SUM(L7:L26) | M27: =SUM(M7:M26) | N27: =SUM(N7:N26) | O27: =SUM(O7:O26) | P27: =O27-N27 | Q27: =IF(N27=0,"",P27/N27*100)
A28: 坏账准备 | B28: 减：投资性房地产减值准备 | P28: =O28-N28 | Q28: =IF(N28=0,"",P28/N28*100)
A29: 合计2 | B29: 合 计 | L29: =L27-L28 | M29: =M27-M28 | N29: =N27-N28 | O29: =O27-O28 | P29: =O29-N29 | Q29: =IF(N29=0,"",P29/N29*100)

Sheet 4-7-4投资性地产
B1: 投资性房地产——土地使用权评估明细表
A2: 表头区域 | B2: （采用公允价值模式计量）
A3: 表头区域 | B3: ='2-分类汇总'!B2
A4: 表头区域 | R4: 表4-7
A5: 表头区域 | B5: ='2-分类汇总'!B4 | R5: ='2-分类汇总'!H4
A6: 检索表头 | B6: 序号 | C6: 土地权证编号 | D6: 宗地名称 | E6: 来源 | F6: 土地位置 | G6: 取得日期 | H6: 用地性质 | I6: 土地用途 | J6: 准用年限 | K6: 开发程度 | L6: 面积(m2) | M6: 原始入账价值（转入日公允价值） | N6: 账面价值 | O6: 评估价值 | P6: 增值额 | Q6: 增值率% | R6: 备注
P7: =O7-N7 | Q7: =IF(N7=0,"",P7/N7*100)
P8: =O8-N8 | Q8: =IF(N8=0,"",P8/N8*100)
P9: =O9-N9 | Q9: =IF(N9=0,"",P9/N9*100)
P10: =O10-N10 | Q10: =IF(N10=0,"",P10/N10*100)
P11: =O11-N11 | Q11: =IF(N11=0,"",P11/N11*100)
P12: =O12-N12 | Q12: =IF(N12=0,"",P12/N12*100)
P13: =O13-N13 | Q13: =IF(N13=0,"",P13/N13*100)
P14: =O14-N14 | Q14: =IF(N14=0,"",P14/N14*100)
P15: =O15-N15 | Q15: =IF(N15=0,"",P15/N15*100)
P16: =O16-N16 | Q16: =IF(N16=0,"",P16/N16*100)
P17: =O17-N17 | Q17: =IF(N17=0,"",P17/N17*100)
P18: =O18-N18 | Q18: =IF(N18=0,"",P18/N18*100)
... P26: =O26-N26 | Q26: =IF(N26=0,"",P26/N26*100)
A27: 合计1 | B27: 合 计 | L27: =SUM(L7:L26) | M27: =SUM(M7:M26) | N27: =SUM(N7:N26) | O27: =SUM(O7:O26) | P27: =O27-N27 | Q27: =IF(N27=0,"",P27/N27*100)
A28: 坏账准备 | B28: 减：投资性房地产减值准备 | P28: =O28-N28 | Q28: =IF(N28=0,"",P28/N28*100)
A29: 合计2 | B29: 合 计 | L29: =L27-L28 | M29: =M27-M28 | N29: =N27-N28 | O29: =O27-O28 | P29: =O29-N29 | Q29: =IF(N29=0,"",P29/N29*100)

Sheet 4-8固定资产汇总
B1: 固定资产评估汇总表
B2: ='2-分类汇总'!B2
J3: 表4-8
B4: ='2-分类汇总'!B4 | L4: ='2-分类汇总'!H4
B5: 编号 | C5: 项目编号 | D5: 科目名称 | E5: 账面价值 | G5: 评估价值 | I5: 增值额 | K5: 增值率%
E6: 原值 | F6: 净值 | G6: 原值 | H6: 净值 | I6: 原值 | J6: 净值 | K6: 原值 | L6: 净值
B7: 4-8-1 | C7: 固资房屋 | D7: 固定资产-房屋建筑物 | E7: ='4-8-1房屋建筑物'!J34 | F7: ='4-8-1房屋建筑物'!K34 | G7: ='4-8-1房屋建筑物'!L34 | H7: ='4-8-1房屋建筑物'!N34 | I7: =G7-E7 | J7: =H7-F7 | K7: =IF(E7=0,"",ROUND(I7/E7*100,2)) | L7: =IF(F7=0,"",ROUND(J7/F7*100,2))
B8: 4-8-2 | C8: 固资构筑 | D8: 固定资产-构筑物及其他辅助设施 | E8: ='4-8-2构筑物'!J34 | F8: ='4-8-2构筑物'!K34 | G8: ='4-8-2构筑物'!L34 | H8: ='4-8-2构筑物'!N34 | I8: =G8-E8 | J8: =H8-F8 | K8: =IF(E8=0,"",ROUND(I8/E8*100,2)) | L8: =IF(F8=0,"",ROUND(J8/F8*100,2))
B9: 4-8-3 | C9: 固资管道 | D9: 固定资产-管道及沟槽 | E9: ='4-8-3管道沟槽'!J34 | F9: ='4-8-3管道沟槽'!K34 | G9: ='4-8-3管道沟槽'!L34 | H9: ='4-8-3管道沟槽'!N34 | I9: =G9-E9 | J9: =H9-F9 | K9: =IF(E9=0,"",ROUND(I9/E9*100,2)) | L9: =IF(F9=0,"",ROUND(J9/F9*100,2))
C10: 固房汇总 | D10: 房屋建筑物类合计 | E10: =SUBTOTAL(9,E7:E9) | F10: =SUBTOTAL(9,F7:F9) | G10: =SUBTOTAL(9,G7:G9) | H10: =SUBTOTAL(9,H7:H9) | I10: =G10-E10 | J10: =H10-F10 | K10: =IF(E10=0,"",ROUND(I10/E10*100,2)) | L10: =IF(F10=0,"",ROUND(J10/F10*100,2))
B13: 4-8-4 | C13: 固资机器 | D13: 固定资产-机器设备 | E13: ='4-8-4机器设备'!K34 | F13: ='4-8-4机器设备'!L34 | G13: ='4-8-4机器设备'!M34 | H13: ='4-8-4机器设备'!O34 | I13: =G13-E13 | J13: =H13-F13 | K13: =IF(E13=0,"",ROUND(I13/E13*100,2)) | L13: =IF(F13=0,"",ROUND(J13/F13*100,2))
B14: 4-8-5 | C14: 固资运输 | D14: 固定资产-车辆 | E14: ='4-8-5车辆'!K34 | F14: ='4-8-5车辆'!L34 | G14: ='4-8-5车辆'!M34 | H14: ='4-8-5车辆'!O34 | I14: =G14-E14 | J14: =H14-F14 | K14: =IF(E14=0,"",ROUND(I14/E14*100,2)) | L14: =IF(F14=0,"",ROUND(J14/F14*100,2))
B15: 4-8-6 | C15: 固资电子 | D15: 固定资产-电子设备 | E15: ='4-8-6电子设备'!K34 | F15: ='4-8-6电子设备'!L34 | G15: ='4-8-6电子设备'!M34 | H15: ='4-8-6电子设备'!O34 | I15: =G15-E15 | J15: =H15-F15 | K15: =IF(E15=0,"",ROUND(I15/E15*100,2)) | L15: =IF(F15=0,"",ROUND(J15/F15*100,2))
C16: 固设汇总 | D16: 设备类合计 | E16: =SUBTOTAL(9,E13:E15) | F16: =SUBTOTAL(9,F13:F15) | G16: =SUBTOTAL(9,G13:G15) | H16: =SUBTOTAL(9,H13:H15) | I16: =G16-E16 | J16: =H16-F16 | K16: =IF(E16=0,"",ROUND(I16/E16*100,2)) | L16: =IF(F16=0,"",ROUND(J16/F16*100,2))
B18: 4-8-7 | C18: 固资清理 | D18: 固定资产清理 | E18: ='4-8-7固定资产清理'!E29 | F18: ='4-8-7固定资产清理'!F29 | G18: ='4-8-7固定资产清理'!G29 | H18: ='4-8-7固定资产清理'!I29 | I18: =G18-E18 | J18: =H18-F18 | K18: =IF(E18=0,"",ROUND(I18/E18*100,2)) | L18: =IF(F18=0,"",ROUND(J18/F18*100,2))
A20: 合计1 | C20: 固资汇总 | D20: 固定资产合计 | E20: =SUBTOTAL(9,E7:E19) | F20: =SUBTOTAL(9,F7:F19) | G20: =SUBTOTAL(9,G7:G19) | H20: =SUBTOTAL(9,H7:H19) | I20: =G20-E20 | J20: =H20-F20 | K20: =IF(E20=0,"",ROUND(I20/E20*100,2)) | L20: =IF(F20=0,"",ROUND(J20/F20*100,2))

Sheet 4-8-1房屋建筑物
A1: 表头区域 | B1: 固定资产—房屋建筑物评估明细表
A2: 表头区域 | B2: ='2-分类汇总'!B2
A3: 表头区域 | R3: 表4-8-1
A4: 表头区域 | B4: ='2-分类汇总'!B4 | S4: ='2-分类汇总'!H4 | T4: 辅助栏
A5: 检索表头1 | B5: 序号 | C5: 权证编号 | D5: 建筑物名称 | E5: 结构 | F5: 建成 年月 | G5: 计量单位 | H5: 建筑面积 (m2) | I5: 成本单价 (元/m2) | J5: 账面价值 | L5: 评估价值 | O5: 增值额 | Q5: 增值率% | R5: 评估原值单价 (元/m2) | S5: 备注 | T5: 计提减值准备
A6: 检索表头2 | J6: 原值 | K6: 净值 | L6: 原值 | M6: 成新率% | N6: 净值 | O6: 原值 | P6: 净值
N7: =ROUND(L7*M7/100,-2) | O7: =L7-J7 | P7: =N7-K7 | Q7: =IF(K7=0,"",ROUND(P7/K7*100,2)) | R7: =IF(H7=0,"",ROUND(L7/H7,0))
N8: =ROUND(L8*M8/100,-2) | O8: =L8-J8 | P8: =N8-K8 | Q8: =IF(K8=0,"",ROUND(P8/K8*100,2)) | R8: =IF(H8=0,"",ROUND(L8/H8,0))
N9: =ROUND(L9*M9/100,-2) | O9: =L9-J9 | P9: =N9-K9 | Q9: =IF(K9=0,"",ROUND(P9/K9*100,2)) | R9: =IF(H9=0,"",ROUND(L9/H9,0))
N10: =ROUND(L10*M10/100,-2) | O10: =L10-J10 | P10: =N10-K10 | Q10: =IF(K10=0,"",ROUND(P10/K10*100,2)) | R10: =IF(H10=0,"",ROUND(L10/H10,0))
N11: =ROUND(L11*M11/100,-2) | O11: =L11-J11 | P11: =N11-K11 | Q11: =IF(K11=0,"",ROUND(P11/K11*100,2)) | R11: =IF(H11=0,"",ROUND(L11/H11,0))
N12: =ROUND(L12*M12/100,-2) | O12: =L12-J12 | P12: =N12-K12 | Q12: =IF(K12=0,"",ROUND(P12/K12*100,2)) | R12: =IF(H12=0,"",ROUND(L12/H12,0))
N13: =ROUND(L13*M13/100,-2) | O13: =L13-J13 | P13: =N13-K13 | Q13: =IF(K13=0,"",ROUND(P13/K13*100,2)) | R13: =IF(H13=0,"",ROUND(L13/H13,0))
N14: =ROUND(L14*M14/100,-2) | O14: =L14-J14 | P14: =N14-K14 | Q14: =IF(K14=0,"",ROUND(P14/K14*100,2)) | R14: =IF(H14=0,"",ROUND(L14/H14,0))
N15: =ROUND(L15*M15/100,-2) | O15: =L15-J15 | P15: =N15-K15 | Q15: =IF(K15=0,"",ROUND(P15/K15*100,2)) | R15: =IF(H15=0,"",ROUND(L15/H15,0))
N16: =ROUND(L16*M16/100,-2) | O16: =L16-J16 | P16: =N16-K16 | Q16: =IF(K16=0,"",ROUND(P16/K16*100,2)) | R16: =IF(H16=0,"",ROUND(L16/H16,0))
N17: =ROUND(L17*M17/100,-2) | O17: =L17-J17 | P17: =N17-K17 | Q17: =IF(K17=0,"",ROUND(P17/K17*100,2)) | R17: =IF(H17=0,"",ROUND(L17/H17,0))
N18: =ROUND(L18*M18/100,-2) | O18: =L18-J18 | P18: =N18-K18 | Q18: =IF(K18=0,"",ROUND(P18/K18*100,2)) | R18: =IF(H18=0,"",ROUND(L18/H18,0))
... N31: =ROUND(L31*M31/100,-2) | O31: =L31-J31 | P31: =N31-K31 | Q31: =IF(K31=0,"",ROUND(P31/K31*100,2)) | R31: =IF(H31=0,"",ROUND(L31/H31,0))
A32: 合计1 | B32: 合 计 | H32: =SUM(H7:H31) | J32: =SUM(J7:J31) | K32: =SUM(K7:K31) | L32: =SUM(L7:L31) | N32: =SUM(N7:N31) | O32: =L32-J32 | P32: =N32-K32 | Q32: =IF(K32=0,"",ROUND(P32/K32*100,2)) | R32: =IF(H32=0,"",ROUND(L32/H32,0)) | T32: =SUM(T7:T31)
A33: 坏账准备 | B33: 减：房屋建筑物减值准备 | O33: =L33-J33 | P33: =N33-K33 | Q33: =IF(K33=0,"",ROUND(P33/K33*100,2)) | R33: =IF(H33=0,"",ROUND(L33/H33,0)) | T33: 校验
A34: 合计2 | B34: 合 计 | H34: =H32-H33 | J34: =J32-J33 | K34: =K32-K33 | L34: =L32-L33 | N34: =N32-N33 | O34: =L34-J34 | P34: =N34-K34 | Q34: =IF(K34=0,"",ROUND(P34/K34*100,2)) | R34: =IF(H34=0,"",ROUND(L34/H34,0)) | T34: =T32-K33

Sheet 4-8-2构筑物
A1: 表头区域 | B1: 固定资产—构筑物及其他辅助设施评估明细表
A2: 表头区域 | B2: ='2-分类汇总'!B2
A3: 表头区域 | Q3: 表4-8-2
A4: 表头区域 | B4: ='2-分类汇总'!B4 | S4: ='2-分类汇总'!H4
A5: 检索表头1 | B5: 序号 | C5: 名称 | D5: 结构 | E5: 建成 年月 | F5: 长度 (m) | G5: 宽度 (m) | H5: 计量单位 | I5: 面积/体积 | J5: 账面价值 | L5: 评估价值 | O5: 增值额 | Q5: 增值率% | R5: 评估原值单价(元/m2) | S5: 备注
A6: 检索表头2 | J6: 原值 | K6: 净值 | L6: 原值 | M6: 成新率% | N6: 净值 | O6: 原值 | P6: 净值
N7: =ROUND(L7*M7/100,-2) | O7: =L7-J7 | P7: =N7-K7 | Q7: =IF(K7=0,"",ROUND(P7/K7*100,2)) | R7: =IF(I7=0,"",ROUND(L7/I7,0))
N8: =ROUND(L8*M8/100,-2) | O8: =L8-J8 | P8: =N8-K8 | Q8: =IF(K8=0,"",ROUND(P8/K8*100,2)) | R8: =IF(I8=0,"",ROUND(L8/I8,0))
N9: =ROUND(L9*M9/100,-2) | O9: =L9-J9 | P9: =N9-K9 | Q9: =IF(K9=0,"",ROUND(P9/K9*100,2)) | R9: =IF(I9=0,"",ROUND(L9/I9,0))
N10: =ROUND(L10*M10/100,-2) | O10: =L10-J10 | P10: =N10-K10 | Q10: =IF(K10=0,"",ROUND(P10/K10*100,2)) | R10: =IF(I10=0,"",ROUND(L10/I10,0))
N11: =ROUND(L11*M11/100,-2) | O11: =L11-J11 | P11: =N11-K11 | Q11: =IF(K11=0,"",ROUND(P11/K11*100,2)) | R11: =IF(I11=0,"",ROUND(L11/I11,0))
N12: =ROUND(L12*M12/100,-2) | O12: =L12-J12 | P12: =N12-K12 | Q12: =IF(K12=0,"",ROUND(P12/K12*100,2)) | R12: =IF(I12=0,"",ROUND(L12/I12,0))
N13: =ROUND(L13*M13/100,-2) | O13: =L13-J13 | P13: =N13-K13 | Q13: =IF(K13=0,"",ROUND(P13/K13*100,2)) | R13: =IF(I13=0,"",ROUND(L13/I13,0))
N14: =ROUND(L14*M14/100,-2) | O14: =L14-J14 | P14: =N14-K14 | Q14: =IF(K14=0,"",ROUND(P14/K14*100,2)) | R14: =IF(I14=0,"",ROUND(L14/I14,0))
N15: =ROUND(L15*M15/100,-2) | O15: =L15-J15 | P15: =N15-K15 | Q15: =IF(K15=0,"",ROUND(P15/K15*100,2)) | R15: =IF(I15=0,"",ROUND(L15/I15,0))
N16: =ROUND(L16*M16/100,-2) | O16: =L16-J16 | P16: =N16-K16 | Q16: =IF(K16=0,"",ROUND(P16/K16*100,2)) | R16: =IF(I16=0,"",ROUND(L16/I16,0))
N17: =ROUND(L17*M17/100,-2) | O17: =L17-J17 | P17: =N17-K17 | Q17: =IF(K17=0,"",ROUND(P17/K17*100,2)) | R17: =IF(I17=0,"",ROUND(L17/I17,0))
N18: =ROUND(L18*M18/100,-2) | O18: =L18-J18 | P18: =N18-K18 | Q18: =IF(K18=0,"",ROUND(P18/K18*100,2)) | R18: =IF(I18=0,"",ROUND(L18/I18,0))
... N31: =ROUND(L31*M31/100,-2) | O31: =L31-J31 | P31: =N31-K31 | Q31: =IF(K31=0,"",ROUND(P31/K31*100,2)) | R31: =IF(I31=0,"",ROUND(L31/I31,0))
A32: 合计1 | B32: 合 计 | I32: =SUM(I7:I31) | J32: =SUM(J7:J31) | K32: =SUM(K7:K31) | L32: =SUM(L7:L31) | N32: =SUM(N7:N31) | O32: =L32-J32 | P32: =N32-K32 | Q32: =IF(K32=0,"",ROUND(P32/K32*100,2)) | R32: =IF(H32=0,"",ROUND(L32/H32,0))
A33: 坏账准备 | B33: 减：构筑物及其他辅助设施减值准备 | O33: =L33-J33 | P33: =N33-K33 | Q33: =IF(K33=0,"",ROUND(P33/K33*100,2)) | R33: =IF(H33=0,"",ROUND(L33/H33,0))
A34: 合计2 | B34: 合 计 | I34: =I32-I33 | J34: =J32-J33 | K34: =K32-K33 | L34: =L32-L33 | N34: =N32-N33 | O34: =L34-J34 | P34: =N34-K34 | Q34: =IF(K34=0,"",ROUND(P34/K34*100,2)) | R34: =IF(H34=0,"",ROUND(L34/H34,0))

Sheet 4-8-3管道沟槽
A1: 表头区域 | B1: 固定资产—管道和沟槽评估明细表
A2: 表头区域 | B2: ='2-分类汇总'!B2
A3: 表头区域 | R3: 表4-8-3
A4: 表头区域 | B4: ='2-分类汇总'!B4 | R4: ='2-分类汇总'!H4
A5: 检索表头1 | B5: 序号 | C5: 名称 | D5: 长度 (m) | E5: 漕深 (m) | F5: 沟宽*沟厚(mm*mm) 管径*壁厚(mm*mm) | G5: 材质 | H5: 绝缘方式 | I5: 建成年月 | J5: 账面价值 | L5: 评估价值 | O5: 增值额 | Q5: 增值率% | R5: 备注
A6: 检索表头2 | J6: 原值 | K6: 净值 | L6: 原值 | M6: 成新率% | N6: 净值 | O6: 原值 | P6: 净值
N7: =ROUND(L7*M7/100,-2) | O7: =L7-J7 | P7: =N7-K7 | Q7: =IF(K7=0,"",ROUND(P7/K7*100,2))
N8: =ROUND(L8*M8/100,-2) | O8: =L8-J8 | P8: =N8-K8 | Q8: =IF(K8=0,"",ROUND(P8/K8*100,2))
N9: =ROUND(L9*M9/100,-2) | O9: =L9-J9 | P9: =N9-K9 | Q9: =IF(K9=0,"",ROUND(P9/K9*100,2))
N10: =ROUND(L10*M10/100,-2) | O10: =L10-J10 | P10: =N10-K10 | Q10: =IF(K10=0,"",ROUND(P10/K10*100,2))
N11: =ROUND(L11*M11/100,-2) | O11: =L11-J11 | P11: =N11-K11 | Q11: =IF(K11=0,"",ROUND(P11/K11*100,2))
N12: =ROUND(L12*M12/100,-2) | O12: =L12-J12 | P12: =N12-K12 | Q12: =IF(K12=0,"",ROUND(P12/K12*100,2))
N13: =ROUND(L13*M13/100,-2) | O13: =L13-J13 | P13: =N13-K13 | Q13: =IF(K13=0,"",ROUND(P13/K13*100,2))
N14: =ROUND(L14*M14/100,-2) | O14: =L14-J14 | P14: =N14-K14 | Q14: =IF(K14=0,"",ROUND(P14/K14*100,2))
N15: =ROUND(L15*M15/100,-2) | O15: =L15-J15 | P15: =N15-K15 | Q15: =IF(K15=0,"",ROUND(P15/K15*100,2))
N16: =ROUND(L16*M16/100,-2) | O16: =L16-J16 | P16: =N16-K16 | Q16: =IF(K16=0,"",ROUND(P16/K16*100,2))
N17: =ROUND(L17*M17/100,-2) | O17: =L17-J17 | P17: =N17-K17 | Q17: =IF(K17=0,"",ROUND(P17/K17*100,2))
N18: =ROUND(L18*M18/100,-2) | O18: =L18-J18 | P18: =N18-K18 | Q18: =IF(K18=0,"",ROUND(P18/K18*100,2))
... N31: =ROUND(L31*M31/100,-2) | O31: =L31-J31 | P31: =N31-K31 | Q31: =IF(K31=0,"",ROUND(P31/K31*100,2))
A32: 合计1 | B32: 合 计 | J32: =SUM(J7:J31) | K32: =SUM(K7:K31) | L32: =SUM(L7:L31) | N32: =SUM(N7:N31) | O32: =L32-J32 | P32: =N32-K32 | Q32: =IF(K32=0,"",ROUND(P32/K32*100,2))
A33: 坏账准备 | B33: 减：管道和沟槽减值准备 | O33: =L33-J33 | P33: =N33-K33 | Q33: =IF(K33=0,"",ROUND(P33/K33*100,2))
A34: 合计2 | B34: 合 计 | J34: =J32-J33 | K34: =K32-K33 | L34: =L32-L33 | N34: =N32-N33 | O34: =L34-J34 | P34: =N34-K34 | Q34: =IF(K34=0,"",ROUND(P34/K34*100,2))

Sheet 4-8-4机器设备
A1: 表头区域 | B1: 固定资产—机器设备评估明细表
A2: 表头区域 | B2: ='2-分类汇总'!B2
A3: 表头区域 | O3: 表4-8-4
A4: 表头区域 | B4: ='2-分类汇总'!B4 | S4: ='2-分类汇总'!H4
A5: 检索表头1 | B5: 序号 | C5: 设备编号 | D5: 设备名称 | E5: 规格型号 | F5: 生产厂家 | G5: 计量单位 | H5: 数量 | I5: 购置日期 | J5: 启用日期 | K5: 账面价值 | M5: 评估价值 | P5: 增值额 | R5: 增值率% | S5: 备注
A6: 检索表头2 | K6: 原值 | L6: 净值 | M6: 原值 | N6: 成新率% | O6: 净值 | P6: 原值 | Q6: 净值
O7: =ROUND(M7*N7/100,-1) | P7: =M7-K7 | Q7: =O7-L7 | R7: =IF(L7=0,"",ROUND(Q7/L7*100,2))
O8: =ROUND(M8*N8/100,-1) | P8: =M8-K8 | Q8: =O8-L8 | R8: =IF(L8=0,"",ROUND(Q8/L8*100,2))
O9: =ROUND(M9*N9/100,-1) | P9: =M9-K9 | Q9: =O9-L9 | R9: =IF(L9=0,"",ROUND(Q9/L9*100,2))
O10: =ROUND(M10*N10/100,-1) | P10: =M10-K10 | Q10: =O10-L10 | R10: =IF(L10=0,"",ROUND(Q10/L10*100,2))
O11: =ROUND(M11*N11/100,-1) | P11: =M11-K11 | Q11: =O11-L11 | R11: =IF(L11=0,"",ROUND(Q11/L11*100,2))
O12: =ROUND(M12*N12/100,-1) | P12: =M12-K12 | Q12: =O12-L12 | R12: =IF(L12=0,"",ROUND(Q12/L12*100,2))
O13: =ROUND(M13*N13/100,-1) | P13: =M13-K13 | Q13: =O13-L13 | R13: =IF(L13=0,"",ROUND(Q13/L13*100,2))
O14: =ROUND(M14*N14/100,-1) | P14: =M14-K14 | Q14: =O14-L14 | R14: =IF(L14=0,"",ROUND(Q14/L14*100,2))
O15: =ROUND(M15*N15/100,-1) | P15: =M15-K15 | Q15: =O15-L15 | R15: =IF(L15=0,"",ROUND(Q15/L15*100,2))
O16: =ROUND(M16*N16/100,-1) | P16: =M16-K16 | Q16: =O16-L16 | R16: =IF(L16=0,"",ROUND(Q16/L16*100,2))
O17: =ROUND(M17*N17/100,-1) | P17: =M17-K17 | Q17: =O17-L17 | R17: =IF(L17=0,"",ROUND(Q17/L17*100,2))
O18: =ROUND(M18*N18/100,-1) | P18: =M18-K18 | Q18: =O18-L18 | R18: =IF(L18=0,"",ROUND(Q18/L18*100,2))
... O31: =ROUND(M31*N31/100,-1) | P31: =M31-K31 | Q31: =O31-L31 | R31: =IF(L31=0,"",ROUND(Q31/L31*100,2))
A32: 合计1 | B32: 合 计 | H32: =SUM(H7:H31) | K32: =SUM(K7:K31) | L32: =SUM(L7:L31) | M32: =SUM(M7:M31) | O32: =SUM(O7:O31) | P32: =M32-K32 | Q32: =O32-L32 | R32: =IF(L32=0,"",ROUND(Q32/L32*100,2))
A33: 坏账准备 | B33: 减：机器设备减值准备 | P33: =M33-K33 | Q33: =O33-L33 | R33: =IF(L33=0,"",ROUND(Q33/L33*100,2))
A34: 合计2 | B34: 合 计 | H34: =H32-H33 | K34: =K32-K33 | L34: =L32-L33 | M34: =M32-M33 | O34: =O32-O33 | P34: =M34-K34 | Q34: =O34-L34 | R34: =IF(L34=0,"",ROUND(Q34/L34*100,2))

Sheet 4-8-5车辆
A1: 表头区域 | B1: 固定资产—车辆评估明细表
A2: 表头区域 | B2: ='2-分类汇总'!B2
A3: 表头区域 | S3: 表4-8-5
A4: 表头区域 | B4: ='2-分类汇总'!B4 | S4: ='2-分类汇总'!H4
A5: 检索表头1 | B5: 序号 | C5: 车辆牌号 | D5: 车辆名称 及规格型号 | E5: 生产厂家 | F5: 计量单位 | G5: 数量 | H5: 购置日期 | I5: 启用日期 | J5: 已行驶里程(公里) | K5: 账面价值 | M5: 评估价值 | P5: 增值额 | R5: 增值率% | S5: 备注
A6: 检索表头2 | K6: 原值 | L6: 净值 | M6: 原值 | N6: 成新率% | O6: 净值 | P6: 原值 | Q6: 净值
O7: =ROUND(M7*N7/100,-2) | P7: =M7-K7 | Q7: =O7-L7 | R7: =IF(L7=0,"",ROUND(Q7/L7*100,2))
O8: =ROUND(M8*N8/100,-2) | P8: =M8-K8 | Q8: =O8-L8 | R8: =IF(L8=0,"",ROUND(Q8/L8*100,2))
O9: =ROUND(M9*N9/100,-2) | P9: =M9-K9 | Q9: =O9-L9 | R9: =IF(L9=0,"",ROUND(Q9/L9*100,2))
O10: =ROUND(M10*N10/100,-2) | P10: =M10-K10 | Q10: =O10-L10 | R10: =IF(L10=0,"",ROUND(Q10/L10*100,2))
O11: =ROUND(M11*N11/100,-2) | P11: =M11-K11 | Q11: =O11-L11 | R11: =IF(L11=0,"",ROUND(Q11/L11*100,2))
O12: =ROUND(M12*N12/100,-2) | P12: =M12-K12 | Q12: =O12-L12 | R12: =IF(L12=0,"",ROUND(Q12/L12*100,2))
O13: =ROUND(M13*N13/100,-2) | P13: =M13-K13 | Q13: =O13-L13 | R13: =IF(L13=0,"",ROUND(Q13/L13*100,2))
O14: =ROUND(M14*N14/100,-2) | P14: =M14-K14 | Q14: =O14-L14 | R14: =IF(L14=0,"",ROUND(Q14/L14*100,2))
O15: =ROUND(M15*N15/100,-2) | P15: =M15-K15 | Q15: =O15-L15 | R15: =IF(L15=0,"",ROUND(Q15/L15*100,2))
O16: =ROUND(M16*N16/100,-2) | P16: =M16-K16 | Q16: =O16-L16 | R16: =IF(L16=0,"",ROUND(Q16/L16*100,2))
O17: =ROUND(M17*N17/100,-2) | P17: =M17-K17 | Q17: =O17-L17 | R17: =IF(L17=0,"",ROUND(Q17/L17*100,2))
O18: =ROUND(M18*N18/100,-2) | P18: =M18-K18 | Q18: =O18-L18 | R18: =IF(L18=0,"",ROUND(Q18/L18*100,2))
... O31: =ROUND(M31*N31/100,-2) | P31: =M31-K31 | Q31: =O31-L31 | R31: =IF(L31=0,"",ROUND(Q31/L31*100,2))
A32: 合计1 | B32: 合 计 | G32: =SUM(G7:G31) | K32: =SUM(K7:K31) | L32: =SUM(L7:L31) | M32: =SUM(M7:M31) | O32: =SUM(O7:O31) | P32: =M32-K32 | Q32: =O32-L32 | R32: =IF(L32=0,"",ROUND(Q32/L32*100,2))
A33: 坏账准备 | B33: 减：车辆减值准备 | P33: =M33-K33 | Q33: =O33-L33 | R33: =IF(L33=0,"",ROUND(Q33/L33*100,2))
A34: 合计2 | B34: 合 计 | G34: =G32-G33 | K34: =K32-K33 | L34: =L32-L33 | M34: =M32-M33 | O34: =O32-O33 | P34: =M34-K34 | Q34: =O34-L34 | R34: =IF(L34=0,"",ROUND(Q34/L34*100,2))

Sheet 4-8-6电子设备
A1: 表头区域 | B1: 固定资产—电子设备评估明细表
A2: 表头区域 | B2: ='2-分类汇总'!B2
A3: 表头区域 | S3: 表4-8-6
A4: 表头区域 | B4: ='2-分类汇总'!B4 | S4: ='2-分类汇总'!H4
A5: 检索表头1 | B5: 序号 | C5: 设备 编号 | D5: 设备名称 | E5: 规格型号 | F5: 生产厂家 | G5: 计量单位 | H5: 数量 | I5: 购置日期 | J5: 启用日期 | K5: 账面价值 | M5: 评估价值 | P5: 增值额 | R5: 增值率% | S5: 备注
A6: 检索表头2 | K6: 原值 | L6: 净值 | M6: 原值 | N6: 成新率% | O6: 净值 | P6: 原值 | Q6: 净值
O7: =ROUND(M7*N7/100,-2) | P7: =M7-K7 | Q7: =O7-L7 | R7: =IF(L7=0,"",ROUND(Q7/L7*100,2))
O8: =ROUND(M8*N8/100,-2) | P8: =M8-K8 | Q8: =O8-L8 | R8: =IF(L8=0,"",ROUND(Q8/L8*100,2))
O9: =ROUND(M9*N9/100,-2) | P9: =M9-K9 | Q9: =O9-L9 | R9: =IF(L9=0,"",ROUND(Q9/L9*100,2))
O10: =ROUND(M10*N10/100,-2) | P10: =M10-K10 | Q10: =O10-L10 | R10: =IF(L10=0,"",ROUND(Q10/L10*100,2))
O11: =ROUND(M11*N11/100,-2) | P11: =M11-K11 | Q11: =O11-L11 | R11: =IF(L11=0,"",ROUND(Q11/L11*100,2))
O12: =ROUND(M12*N12/100,-2) | P12: =M12-K12 | Q12: =O12-L12 | R12: =IF(L12=0,"",ROUND(Q12/L12*100,2))
O13: =ROUND(M13*N13/100,-2) | P13: =M13-K13 | Q13: =O13-L13 | R13: =IF(L13=0,"",ROUND(Q13/L13*100,2))
O14: =ROUND(M14*N14/100,-2) | P14: =M14-K14 | Q14: =O14-L14 | R14: =IF(L14=0,"",ROUND(Q14/L14*100,2))
O15: =ROUND(M15*N15/100,-2) | P15: =M15-K15 | Q15: =O15-L15 | R15: =IF(L15=0,"",ROUND(Q15/L15*100,2))
O16: =ROUND(M16*N16/100,-2) | P16: =M16-K16 | Q16: =O16-L16 | R16: =IF(L16=0,"",ROUND(Q16/L16*100,2))
O17: =ROUND(M17*N17/100,-2) | P17: =M17-K17 | Q17: =O17-L17 | R17: =IF(L17=0,"",ROUND(Q17/L17*100,2))
O18: =ROUND(M18*N18/100,-2) | P18: =M18-K18 | Q18: =O18-L18 | R18: =IF(L18=0,"",ROUND(Q18/L18*100,2))
... O31: =ROUND(M31*N31/100,-2) | P31: =M31-K31 | Q31: =O31-L31 | R31: =IF(L31=0,"",ROUND(Q31/L31*100,2))
A32: 合计1 | B32: 合 计 | H32: =SUM(H7:H31) | K32: =SUM(K7:K31) | L32: =SUM(L7:L31) | M32: =SUM(M7:M31) | O32: =SUM(O7:O31) | P32: =M32-K32 | Q32: =O32-L32 | R32: =IF(L32=0,"",ROUND(Q32/L32*100,2))
A33: 坏账准备 | B33: 减：电子设备减值准备 | P33: =M33-K33 | Q33: =O33-L33 | R33: =IF(L33=0,"",ROUND(Q33/L33*100,2))
A34: 合计2 | B34: 合 计 | H34: =H32-H33 | K34: =K32-K33 | L34: =L32-L33 | M34: =M32-M33 | O34: =O32-O33 | P34: =M34-K34 | Q34: =O34-L34 | R34: =IF(L34=0,"",ROUND(Q34/L34*100,2))

Sheet 4-8-7固定资产清理
A1: 表头区域 | B1: 固定资产清理评估明细表
A2: 表头区域 | B2: ='2-分类汇总'!B2
A3: 表头区域 | L3: 表4-8-7
A4: 表头区域 | B4: ='2-分类汇总'!B4 | L4: ='2-分类汇总'!H4
A5: 检索表头1 | B5: 序号 | C5: 待处理资产名称 | D5: 发生日期 | E5: 账面价值 | G5: 评估价值 | J5: 增值额 | K5: 增值率% | L5: 备注
A6: 检索表头2 | E6: 原值 | F6: 净值 | G6: 原值 | H6: 成新率% | I6: 净值
J7: =I7-F7 | K7: =IF(F7=0,"",J7/F7*100)
J8: =G8-E8 | K8: =IF(E8=0,"",J8/E8*100)
J9: =G9-E9 | K9: =IF(E9=0,"",J9/E9*100)
J10: =G10-E10 | K10: =IF(E10=0,"",J10/E10*100)
J11: =G11-E11 | K11: =IF(E11=0,"",J11/E11*100)
J12: =G12-E12 | K12: =IF(E12=0,"",J12/E12*100)
J13: =G13-E13 | K13: =IF(E13=0,"",J13/E13*100)
J14: =G14-E14 | K14: =IF(E14=0,"",J14/E14*100)
J15: =G15-E15 | K15: =IF(E15=0,"",J15/E15*100)
J16: =G16-E16 | K16: =IF(E16=0,"",J16/E16*100)
J17: =G17-E17 | K17: =IF(E17=0,"",J17/E17*100)
J18: =G18-E18 | K18: =IF(E18=0,"",J18/E18*100)
J19: =G19-E19 | K19: =IF(E19=0,"",J19/E19*100)
... J28: =G28-E28 | K28: =IF(E28=0,"",J28/E28*100)
A29: 合计1 | B29: 合 计 | E29: =SUM(E7:E28) | F29: =SUM(F7:F28) | G29: =SUM(G7:G28) | I29: =SUM(I7:I28) | J29: =I29-F29 | K29: =IF(F29=0,"",J29/F29*100)

Sheet 4-9在建工程汇总
B1: 在建工程评估汇总表
B2: ='2-分类汇总'!B2
H3: 表4-9
B4: ='2-分类汇总'!B4 | H4: ='2-分类汇总'!H4
B5: 编号 | C5: 项目编号 | D5: 科目名称 | E5: 账面价值 | F5: 评估价值 | G5: 增值额 | H5: 增值率%
B6: 4-9-1 | C6: 在建土建 | D6: 在建工程—土建工程 | E6: ='4-9-1在建（土建）'!J29 | F6: ='4-9-1在建（土建）'!K29 | G6: =F6-E6 | H6: =IF(E6=0,"",G6/E6*100)
B7: 4-9-2 | C7: 在建设备 | D7: 在建工程—设备安装工程 | E7: ='4-9-2在建（设备）'!L29 | F7: ='4-9-2在建（设备）'!P29 | G7: =F7-E7 | H7: =IF(E7=0,"",G7/E7*100)
B8: 4-9-3 | C8: 在建物资 | D8: 在建工程—工程物资 | E8: ='4-9-3在建工程（工程物资）'!H29 | F8: ='4-9-3在建工程（工程物资）'!K29 | G8: =F8-E8 | H8: =IF(E8=0,"",G8/E8*100)
G9: =F9-E9 | H9: =IF(E9=0,"",G9/E9*100)
A25: 合计1 | C25: 在建汇总 | D25: 合 计 | E25: =SUM(E6:E24) | F25: =SUM(F6:F24) | G25: =F25-E25 | H25: =IF(E25=0,"",G25/E25*100)

Sheet 4-9-1在建（土建）
A1: 表头区域 | B1: 在建工程—土建工程评估明细表
A2: 表头区域 | B2: ='2-分类汇总'!B2
A3: 表头区域 | N3: 表4-9-1
A4: 表头区域 | B4: ='2-分类汇总'!B4 | N4: ='2-分类汇总'!H4
A5: 检索表头 | B5: 序号 | C5: 项目名称 | D5: 结构 | E5: 建筑面积/容积 | F5: 开工日期 | G5: 预计完工日期 | H5: 形象进度 | I5: 付款比例 | J5: 账面价值 | K5: 评估价值 | L5: 增值额 | M5: 增值率% | N5: 备注
L6: =K6-J6 | M6: =IF(J6=0,"",L6/J6*100)
L7: =K7-J7 | M7: =IF(J7=0,"",L7/J7*100)
L8: =K8-J8 | M8: =IF(J8=0,"",L8/J8*100)
L9: =K9-J9 | M9: =IF(J9=0,"",L9/J9*100)
L10: =K10-J10 | M10: =IF(J10=0,"",L10/J10*100)
L11: =K11-J11 | M11: =IF(J11=0,"",L11/J11*100)
L12: =K12-J12 | M12: =IF(J12=0,"",L12/J12*100)
L13: =K13-J13 | M13: =IF(J13=0,"",L13/J13*100)
L14: =K14-J14 | M14: =IF(J14=0,"",L14/J14*100)
L15: =K15-J15 | M15: =IF(J15=0,"",L15/J15*100)
L16: =K16-J16 | M16: =IF(J16=0,"",L16/J16*100)
L17: =K17-J17 | M17: =IF(J17=0,"",L17/J17*100)
... L26: =K26-J26 | M26: =IF(J26=0,"",L26/J26*100)
A27: 合计1 | B27: 合 计 | E27: =SUM(E6:E26) | J27: =SUM(J6:J26) | K27: =SUM(K6:K26) | L27: =K27-J27 | M27: =IF(J27=0,"",L27/J27*100)
A28: 坏账准备 | B28: 减：在建土建工程减值准备 | L28: =K28-J28 | M28: =IF(J28=0,"",L28/J28*100)
A29: 合计2 | B29: 合 计 | E29: =E27-E28 | J29: =J27-J28 | K29: =K27-K28 | L29: =K29-J29 | M29: =IF(J29=0,"",L29/J29*100)

Sheet 4-9-2在建（设备）
A1: 表头区域 | B1: 在建工程—设备安装工程评估明细表
A2: 表头区域 | B2: ='2-分类汇总'!B2
A3: 表头区域 | S3: 表4-9-2
A4: 表头区域 | B4: ='2-分类汇总'!B4 | S4: ='2-分类汇总'!H4
A5: 检索表头1 | B5: 序号 | C5: 项目名称 | D5: 规格型号 | E5: 数量 | F5: 计量 单位 | G5: 开工 日期 | H5: 预计完 工日期 | I5: 账面价值 | M5: 评估价值 | Q5: 增值额 | R5: 增值率% | S5: 备注
A6: 检索表头2 | I6: 设备费 | J6: 资金成本 | K6: 安装费及其他 | L6: 合计 | M6: 设备费 | N6: 资金成本 | O6: 安装费及其他 | P6: 合计
L7: =SUM(I7:K7) | O7: =K7*2 | P7: =SUM(M7:O7) | Q7: =P7-L7 | R7: =IF(L7=0,"",Q7/L7*100)
L8: =SUM(I8:K8) | P8: =SUM(M8:O8) | Q8: =P8-L8 | R8: =IF(L8=0,"",Q8/L8*100)
L9: =SUM(I9:K9) | P9: =SUM(M9:O9) | Q9: =P9-L9 | R9: =IF(L9=0,"",Q9/L9*100)
L10: =SUM(I10:K10) | P10: =SUM(M10:O10) | Q10: =P10-L10 | R10: =IF(L10=0,"",Q10/L10*100)
L11: =SUM(I11:K11) | P11: =SUM(M11:O11) | Q11: =P11-L11 | R11: =IF(L11=0,"",Q11/L11*100)
L12: =SUM(I12:K12) | P12: =SUM(M12:O12) | Q12: =P12-L12 | R12: =IF(L12=0,"",Q12/L12*100)
L13: =SUM(I13:K13) | P13: =SUM(M13:O13) | Q13: =P13-L13 | R13: =IF(L13=0,"",Q13/L13*100)
P14: =SUM(M14:O14) | Q14: =P14-L14 | R14: =IF(L14=0,"",Q14/L14*100)
L15: =SUM(I15:K15) | P15: =SUM(M15:O15) | Q15: =P15-L15 | R15: =IF(L15=0,"",Q15/L15*100)
L16: =SUM(I16:K16) | P16: =SUM(M16:O16) | Q16: =P16-L16 | R16: =IF(L16=0,"",Q16/L16*100)
L17: =SUM(I17:K17) | P17: =SUM(M17:O17) | Q17: =P17-L17 | R17: =IF(L17=0,"",Q17/L17*100)
L18: =SUM(I18:K18) | P18: =SUM(M18:O18) | Q18: =P18-L18 | R18: =IF(L18=0,"",Q18/L18*100)
L19: =SUM(I19:K19) | P19: =SUM(M19:O19) | Q19: =P19-L19 | R19: =IF(L19=0,"",Q19/L19*100)
L20: =SUM(I20:K20) | P20: =SUM(M20:O20) | Q20: =P20-L20 | R20: =IF(L20=0,"",Q20/L20*100)
L21: =SUM(I21:K21) | P21: =SUM(M21:O21) | Q21: =P21-L21 | R21: =IF(L21=0,"",Q21/L21*100)
L22: =SUM(I22:K22) | P22: =SUM(M22:O22) | Q22: =P22-L22 | R22: =IF(L22=0,"",Q22/L22*100)
L23: =SUM(I23:K23) | P23: =SUM(M23:O23) | Q23: =P23-L23 | R23: =IF(L23=0,"",Q23/L23*100)
L24: =SUM(I24:K24) | P24: =SUM(M24:O24) | Q24: =P24-L24 | R24: =IF(L24=0,"",Q24/L24*100)
L25: =SUM(I25:K25) | P25: =SUM(M25:O25) | Q25: =P25-L25 | R25: =IF(L25=0,"",Q25/L25*100)
L26: =SUM(I26:K26) | P26: =SUM(M26:O26) | Q26: =P26-L26 | R26: =IF(L26=0,"",Q26/L26*100)
A27: 合计1 | B27: 合 计 | I27: =SUM(I7:I26) | J27: =SUM(J7:J26) | K27: =SUM(K7:K26) | L27: =SUM(L7:L26) | M27: =SUM(M7:M26) | N27: =SUM(N7:N26) | O27: =SUM(O7:O26) | P27: =SUM(P7:P26) | Q27: =P27-L27 | R27: =IF(L27=0,"",Q27/L27*100)
A28: 坏账准备 | B28: 减：在建设备安装工程减值准备 | Q28: =P28-L28 | R28: =IF(L28=0,"",Q28/L28*100)
A29: 合计2 | B29: 合 计 | I29: =I27-I28 | J29: =J27-J28 | K29: =K27-K28 | L29: =L27-L28 | M29: =M27-M28 | N29: =N27-N28 | O29: =O27-O28 | P29: =P27-P28 | Q29: =P29-L29 | R29: =IF(L29=0,"",Q29/L29*100)

Sheet 4-9-3在建工程（工程物资）
A1: 表头区域 | B1: 在建工程—工程物资评估明细表
A2: 表头区域 | B2: ='2-分类汇总'!B2
A3: 表头区域 | M3: 表4-9-3
A4: 表头区域 | B4: ='2-分类汇总'!B4 | N4: ='2-分类汇总'!H4
A5: 检索表头1 | B5: 序号 | C5: 名称 | D5: 工程项目 | E5: 计量 单位 | F5: 账面价值 | I5: 评估价值 | L5: 增值额 | M5: 增值率 % | N5: 备注
A6: 检索表头2 | F6: 数量 | G6: 单价 | H6: 金额 | I6: 实际数量 | J6: 单价 | K6: 金额
L7: =K7-H7 | M7: =IF(H7=0,"",L7/H7*100)
L8: =K8-H8 | M8: =IF(H8=0,"",L8/H8*100)
L9: =K9-H9 | M9: =IF(H9=0,"",L9/H9*100)
L10: =K10-H10 | M10: =IF(H10=0,"",L10/H10*100)
L11: =K11-H11 | M11: =IF(H11=0,"",L11/H11*100)
L12: =K12-H12 | M12: =IF(H12=0,"",L12/H12*100)
L13: =K13-H13 | M13: =IF(H13=0,"",L13/H13*100)
L14: =K14-H14 | M14: =IF(H14=0,"",L14/H14*100)
L15: =K15-H15 | M15: =IF(H15=0,"",L15/H15*100)
L16: =K16-H16 | M16: =IF(H16=0,"",L16/H16*100)
L17: =K17-H17 | M17: =IF(H17=0,"",L17/H17*100)
L18: =K18-H18 | M18: =IF(H18=0,"",L18/H18*100)
... L26: =K26-H26 | M26: =IF(H26=0,"",L26/H26*100)
A27: 合计1 | B27: 合 计 | F27: =SUM(F7:F26) | H27: =SUM(H7:H26) | I27: =SUM(I7:I26) | K27: =SUM(K7:K26) | L27: =K27-H27 | M27: =IF(H27=0,"",L27/H27*100)
A28: 坏账准备 | B28: 减：工程物资减值准备 | L28: =K28-H28 | M28: =IF(H28=0,"",L28/H28*100)
A29: 合计2 | B29: 合 计 | F29: =F27-F28 | H29: =H27-H28 | I29: =I27-I28 | K29: =K27-K28 | L29: =K29-H29 | M29: =IF(H29=0,"",L29/H29*100)

Sheet 4-10生产性生物资产
A1: 表头区域 | B1: 生产性生物资产评估明细表
A2: 表头区域 | B2: ='2-分类汇总'!B2
A3: 表头区域 | L3: 表4-10
A4: 表头区域 | B4: ='2-分类汇总'!B4 | N4: ='2-分类汇总'!H4
A5: 检索表头1 | B5: 序号 | C5: 种类 | D5: 群别 | E5: 计量 单位 | F5: 数量 | G5: 购置日期 | H5: 账面价值 | J5: 评估价值 | M5: 增值率% | N5: 备注
A6: 检索表头2 | H6: 原值 | I6: 净值 | J6: 原值 | K6: 成新率% | L6: 净值
L7: =ROUND(J7*K7/100,-1) | M7: =IF(I7=0,"",(L7-I7)/I7*100)
L8: =ROUND(J8*K8/100,-1) | M8: =IF(I8=0,"",(L8-I8)/I8*100)
L9: =ROUND(J9*K9/100,-1) | M9: =IF(I9=0,"",(L9-I9)/I9*100)
L10: =ROUND(J10*K10/100,-1) | M10: =IF(I10=0,"",(L10-I10)/I10*100)
L11: =ROUND(J11*K11/100,-1) | M11: =IF(I11=0,"",(L11-I11)/I11*100)
L12: =ROUND(J12*K12/100,-1) | M12: =IF(I12=0,"",(L12-I12)/I12*100)
L13: =ROUND(J13*K13/100,-1) | M13: =IF(I13=0,"",(L13-I13)/I13*100)
L14: =ROUND(J14*K14/100,-1) | M14: =IF(I14=0,"",(L14-I14)/I14*100)
L15: =ROUND(J15*K15/100,-1) | M15: =IF(I15=0,"",(L15-I15)/I15*100)
L16: =ROUND(J16*K16/100,-1) | M16: =IF(I16=0,"",(L16-I16)/I16*100)
L17: =ROUND(J17*K17/100,-1) | M17: =IF(I17=0,"",(L17-I17)/I17*100)
L18: =ROUND(J18*K18/100,-1) | M18: =IF(I18=0,"",(L18-I18)/I18*100)
... L24: =ROUND(J24*K24/100,-1) | M24: =IF(I24=0,"",(L24-I24)/I24*100)
A25: 合计1 | B25: 合 计 | F25: =ROUND(SUM(F7:F24),2) | H25: =ROUND(SUM(H7:H24),2) | I25: =ROUND(SUM(I7:I24),2) | J25: =ROUND(SUM(J7:J24),2) | L25: =ROUND(SUM(L7:L24),2) | M25: =IF(I25=0,"",(L25-I25)/I25*100)
A26: 坏账准备 | B26: 减：生产性生物资产减值准备 | M26: =IF(I26=0,"",(L26-I26)/I26*100)
A27: 合计2 | B27: 合 计 | F27: =F25-F26 | H27: =H25-H26 | I27: =I25-I26 | J27: =J25-J26 | K27: =K25-K26 | L27: =L25-L26 | M27: =IF(I27=0,"",(L27-I27)/I27*100)

Sheet 4-11油气资产
A1: 表头区域 | B1: 油气资产评估明细表
A2: 表头区域 | B2: ='2-分类汇总'!B2
A3: 表头区域 | O3: 表4-11
A4: 表头区域 | B4: ='2-分类汇总'!B4 | O4: ='2-分类汇总'!H4
A5: 检索表头1 | B5: 序号 | C5: 类别 | D5: 矿区（或油田） | E5: 计量 单位 | F5: 数量 | G5: 形成日期 | H5: 来源 | I5: 账面价值 | K5: 评估价值 | N5: 增值率% | O5: 备注
A6: 检索表头2 | I6: 原值 | J6: 净值 | K6: 原值 | L6: 成新率% | M6: 净值
M7: =ROUND(K7*L7/100,-1) | N7: =IF(J7=0,"",(M7-J7)/J7*100)
M8: =ROUND(K8*L8/100,-1) | N8: =IF(J8=0,"",(M8-J8)/J8*100)
M9: =ROUND(K9*L9/100,-1) | N9: =IF(J9=0,"",(M9-J9)/J9*100)
M10: =ROUND(K10*L10/100,-1) | N10: =IF(J10=0,"",(M10-J10)/J10*100)
M11: =ROUND(K11*L11/100,-1) | N11: =IF(J11=0,"",(M11-J11)/J11*100)
M12: =ROUND(K12*L12/100,-1) | N12: =IF(J12=0,"",(M12-J12)/J12*100)
M13: =ROUND(K13*L13/100,-1) | N13: =IF(J13=0,"",(M13-J13)/J13*100)
M14: =ROUND(K14*L14/100,-1) | N14: =IF(J14=0,"",(M14-J14)/J14*100)
M15: =ROUND(K15*L15/100,-1) | N15: =IF(J15=0,"",(M15-J15)/J15*100)
M16: =ROUND(K16*L16/100,-1) | N16: =IF(J16=0,"",(M16-J16)/J16*100)
M17: =ROUND(K17*L17/100,-1) | N17: =IF(J17=0,"",(M17-J17)/J17*100)
M18: =ROUND(K18*L18/100,-1) | N18: =IF(J18=0,"",(M18-J18)/J18*100)
... M25: =ROUND(K25*L25/100,-1) | N25: =IF(J25=0,"",(M25-J25)/J25*100)
A26: 合计1 | B26: 合 计 | F26: =ROUND(SUM(F6:F25),2) | I26: =ROUND(SUM(I6:I25),2) | J26: =ROUND(SUM(J6:J25),2) | K26: =ROUND(SUM(K6:K25),2) | M26: =ROUND(SUM(M6:M25),2) | N26: =IF(J26=0,"",(M26-J26)/J26*100)
A27: 坏账准备 | B27: 减：油气资产减值准备 | N27: =IF(J27=0,"",(M27-J27)/J27*100)
A28: 合计2 | B28: 合 计 | F28: =F26-F27 | I28: =I26-I27 | J28: =J26-J27 | K28: =K26-K27 | M28: =M26-M27 | N28: =IF(J28=0,"",(M28-J28)/J28*100)

Sheet 4-12使用权资产
A1: 表头区域 | B1: 使用权资产评估明细表
A2: 表头区域 | B2: ='2-分类汇总'!B2
A3: 表头区域 | K3: 表4-12
A4: 表头区域 | B4: ='2-分类汇总'!B4 | K4: ='2-分类汇总'!H4
A5: 检索表头 | B5: 序号 | C5: 资产名称或内容 | D5: 规格型号及其他 | E5: 形成日期 | F5: 原始发生额 | G5: 账面价值 | H5: 评估价值 | I5: 增值额 | J5: 增值率% | K5: 备注
I6: =H6-G6 | J6: =IF(G6=0,"",I6/G6*100)
I7: =H7-G7 | J7: =IF(G7=0,"",I7/G7*100)
I8: =H8-G8 | J8: =IF(G8=0,"",I8/G8*100)
I9: =H9-G9 | J9: =IF(G9=0,"",I9/G9*100)
I10: =H10-G10 | J10: =IF(G10=0,"",I10/G10*100)
I11: =H11-G11 | J11: =IF(G11=0,"",I11/G11*100)
I12: =H12-G12 | J12: =IF(G12=0,"",I12/G12*100)
I13: =H13-G13 | J13: =IF(G13=0,"",I13/G13*100)
I14: =H14-G14 | J14: =IF(G14=0,"",I14/G14*100)
I15: =H15-G15 | J15: =IF(G15=0,"",I15/G15*100)
I16: =H16-G16 | J16: =IF(G16=0,"",I16/G16*100)
I17: =H17-G17 | J17: =IF(G17=0,"",I17/G17*100)
... I29: =H29-G29 | J29: =IF(G29=0,"",I29/G29*100)
A30: 合计1 | B30: 合 计 | F30: =ROUND(SUM(F6:F29),2) | G30: =ROUND(SUM(G6:G29),2) | H30: =ROUND(SUM(H6:H29),2) | I30: =H30-G30 | J30: =IF(G30=0,"",I30/G30*100)

Sheet 4-13无形资产汇总
B1: 无形资产评估汇总表
B2: ='2-分类汇总'!B2
H3: 表4-13
B4: ='2-分类汇总'!B4 | H4: ='2-分类汇总'!H4
B5: 编号 | D5: 科目名称 | E5: 账面价值 | F5: 评估价值 | G5: 增值额 | H5: 增值率%
B6: 4-13-1 | C6: 无形土地 | D6: 无形资产-土地使用权 | E6: ='4-13-1无形-土地'!M30 | F6: ='4-13-1无形-土地'!N30 | G6: =F6-E6 | H6: =IF(E6=0,"",G6/E6*100)
B7: 4-13-2 | C7: 无形矿权 | D7: 无形资产-矿业权 | E7: ='4-13-2无形-矿业权'!K30 | F7: ='4-13-2无形-矿业权'!L30 | G7: =F7-E7 | H7: =IF(E7=0,"",G7/E7*100)
B8: 4-13-3 | C8: 无形其他 | D8: 无形资产-其他无形资产 | E8: ='4-13-3无形-其他'!G27 | F8: ='4-13-3无形-其他'!I27 | G8: =F8-E8 | H8: =IF(E8=0,"",G8/E8*100)
H9: =IF(E9=0,"",G9/E9)
H10: =IF(E10=0,"",G10/E10)
H11: =IF(E11=0,"",G11/E11)
H12: =IF(E12=0,"",G12/E12)
H13: =IF(E13=0,"",G13/E13)
H14: =IF(E14=0,"",G14/E14)
H15: =IF(E15=0,"",G15/E15)
H16: =IF(E16=0,"",G16/E16)
H17: =IF(E17=0,"",G17/E17)
H18: =IF(E18=0,"",G18/E18)
H19: =IF(E19=0,"",G19/E19)
H20: =IF(E20=0,"",G20/E20)
H21: =IF(E21=0,"",G21/E21)
A24: 合计1 | C24: 无形净额 | D24: 合 计 | E24: =SUM(E6:E23) | F24: =SUM(F6:F23) | G24: =F24-E24 | H24: =IF(E24=0,"",G24/E24*100)

Sheet 4-13-1无形-土地
A1: 表头区域 | B1: 无形资产—土地使用权评估明细表
A2: 表头区域 | B2: ='2-分类汇总'!B2
A3: 表头区域 | P3: 表4-13-1
A4: 表头区域 | B4: ='2-分类汇总'!B4 | Q4: ='2-分类汇总'!H4
A5: 检索表头 | B5: 序号 | C5: 土地权证编号 | D5: 宗地名称 | E5: 土地位置 | F5: 取得日期 | G5: 用地性质 | H5: 土地用途 | I5: 准用年限 | J5: 开发程度 | K5: 面积(m2) | L5: 原始入账价值 | M5: 账面价值 | N5: 评估价值 | O5: 增值额 | P5: 增值率% | Q5: 备注
O6: =N6-M6 | P6: =IF(M6=0,"",O6/M6*100)
O7: =N7-M7 | P7: =IF(M7=0,"",O7/M7*100)
O8: =N8-M8 | P8: =IF(M8=0,"",O8/M8*100)
O9: =N9-M9 | P9: =IF(M9=0,"",O9/M9*100)
O10: =N10-M10 | P10: =IF(M10=0,"",O10/M10*100)
O11: =N11-M11 | P11: =IF(M11=0,"",O11/M11*100)
O12: =N12-M12 | P12: =IF(M12=0,"",O12/M12*100)
O13: =N13-M13 | P13: =IF(M13=0,"",O13/M13*100)
O14: =N14-M14 | P14: =IF(M14=0,"",O14/M14*100)
O15: =N15-M15 | P15: =IF(M15=0,"",O15/M15*100)
O16: =N16-M16 | P16: =IF(M16=0,"",O16/M16*100)
O17: =N17-M17 | P17: =IF(M17=0,"",O17/M17*100)
... O27: =N27-M27 | P27: =IF(M27=0,"",O27/M27*100)
A28: 合计1 | B28: 合 计 | K28: =SUM(K6:K27) | L28: =SUM(L6:L27) | M28: =SUM(M6:M27) | N28: =SUM(N6:N27) | O28: =N28-M28 | P28: =IF(M28=0,"",O28/M28*100)
A29: 坏账准备 | B29: 减：土地使用权减值准备 | O29: =N29-M29 | P29: =IF(M29=0,"",O29/M29*100)
A30: 合计2 | B30: 合 计 | K30: =K28-K29 | L30: =L28-L29 | M30: =M28-M29 | N30: =N28-N29 | O30: =N30-M30 | P30: =IF(M30=0,"",O30/M30*100)

Sheet 4-13-2无形-矿业权
A1: 表头区域 | B1: 无形资产—矿业权评估明细表
A2: 表头区域 | B2: ='2-分类汇总'!B2
A3: 表头区域 | N3: 表4-13-2
A4: 表头区域 | B4: ='2-分类汇总'!B4 | O4: ='2-分类汇总'!H4
A5: 检索表头 | B5: 序号 | C5: 名称、种类（探矿权/采矿权） | D5: 勘查（采矿）许可证编号 | E5: 取得方式 | F5: 取得日期 | G5: 剩余有效年限 | H5: 勘查开发阶段 | I5: 核定（批准）生产规模 | J5: 原始入账价值 | K5: 账面价值 | L5: 评估价值 | M5: 增值额 | N5: 增值率% | O5: 备注
M6: =L6-K6 | N6: =IF(K6=0,"",M6/K6*100)
M7: =L7-K7 | N7: =IF(K7=0,"",M7/K7*100)
M8: =L8-K8 | N8: =IF(K8=0,"",M8/K8*100)
M9: =L9-K9 | N9: =IF(K9=0,"",M9/K9*100)
M10: =L10-K10 | N10: =IF(K10=0,"",M10/K10*100)
M11: =L11-K11 | N11: =IF(K11=0,"",M11/K11*100)
M12: =L12-K12 | N12: =IF(K12=0,"",M12/K12*100)
M13: =L13-K13 | N13: =IF(K13=0,"",M13/K13*100)
M14: =L14-K14 | N14: =IF(K14=0,"",M14/K14*100)
M15: =L15-K15 | N15: =IF(K15=0,"",M15/K15*100)
M16: =L16-K16 | N16: =IF(K16=0,"",M16/K16*100)
M17: =L17-K17 | N17: =IF(K17=0,"",M17/K17*100)
... M27: =L27-K27 | N27: =IF(K27=0,"",M27/K27*100)
A28: 合计1 | B28: 合 计 | J28: =SUM(J6:J27) | K28: =SUM(K6:K27) | L28: =SUM(L6:L27) | M28: =L28-K28 | N28: =IF(K28=0,"",M28/K28*100)
A29: 坏账准备 | B29: 减：矿业权减值准备 | M29: =L29-K29 | N29: =IF(K29=0,"",M29/K29*100)
A30: 合计2 | B30: 合 计 | J30: =J28-J29 | K30: =K28-K29 | L30: =L28-L29 | M30: =L30-K30 | N30: =IF(K30=0,"",M30/K30*100)

Sheet 4-13-3无形-其他
A1: 表头区域 | B1: 无形资产—其他无形资产评估明细表
A2: 表头区域 | B2: ='2-分类汇总'!B2
A3: 表头区域 | L3: 表4-13-3
A4: 表头区域 | B4: ='2-分类汇总'!B4 | L4: ='2-分类汇总'!H4
A5: 检索表头 | B5: 序号 | C5: 无形资产名称和内容 | D5: 取得日期 | E5: 法定/预计使用年限 | F5: 原始入账价值 | G5: 账面价值 | H5: 尚可使用年限 | I5: 评估价值 | J5: 增值额 | K5: 增值率% | L5: 备注
J6: =I6-G6 | K6: =IF(G6=0,"",J6/G6*100)
J7: =I7-G7 | K7: =IF(G7=0,"",J7/G7*100)
J8: =I8-G8 | K8: =IF(G8=0,"",J8/G8*100)
J9: =I9-G9 | K9: =IF(G9=0,"",J9/G9*100)
J10: =I10-G10 | K10: =IF(G10=0,"",J10/G10*100)
J11: =I11-G11 | K11: =IF(G11=0,"",J11/G11*100)
J12: =I12-G12 | K12: =IF(G12=0,"",J12/G12*100)
J13: =I13-G13 | K13: =IF(G13=0,"",J13/G13*100)
J14: =I14-G14 | K14: =IF(G14=0,"",J14/G14*100)
J15: =I15-G15 | K15: =IF(G15=0,"",J15/G15*100)
J16: =I16-G16 | K16: =IF(G16=0,"",J16/G16*100)
J17: =I17-G17 | K17: =IF(G17=0,"",J17/G17*100)
... J24: =I24-G24 | K24: =IF(G24=0,"",J24/G24*100)
A25: 合计1 | B25: 合 计 | F25: =SUM(F6:F24) | G25: =SUM(G6:G24) | I25: =SUM(I6:I24) | J25: =I25-G25 | K25: =IF(G25=0,"",J25/G25*100)
A26: 坏账准备 | B26: 减：其他无形资产减值准备 | J26: =I26-G26 | K26: =IF(G26=0,"",J26/G26*100)
A27: 合计2 | B27: 合 计 | F27: =F25-F26 | G27: =G25-G26 | I27: =I25-I26 | J27: =I27-G27 | K27: =IF(G27=0,"",J27/G27*100)

Sheet 4-14开发支出
A1: 表头区域 | B1: 开发支出评估明细表
A2: 表头区域 | B2: ='2-分类汇总'!B2
A3: 表头区域 | I3: 表4-14
A4: 表头区域 | B4: ='2-分类汇总'!B4 | I4: ='2-分类汇总'!H4
A5: 检索表头 | B5: 序号 | C5: 内容或名称 | D5: 发生日期 | E5: 账面价值 | F5: 评估价值 | G5: 增值额 | H5: 增值率% | I5: 备注
G6: =F6-E6 | H6: =IF(E6=0,"",G6/E6*100)
G7: =F7-E7 | H7: =IF(E7=0,"",G7/E7*100)
G8: =F8-E8 | H8: =IF(E8=0,"",G8/E8*100)
G9: =F9-E9 | H9: =IF(E9=0,"",G9/E9*100)
G10: =F10-E10 | H10: =IF(E10=0,"",G10/E10*100)
G11: =F11-E11 | H11: =IF(E11=0,"",G11/E11*100)
G12: =F12-E12 | H12: =IF(E12=0,"",G12/E12*100)
G13: =F13-E13 | H13: =IF(E13=0,"",G13/E13*100)
G14: =F14-E14 | H14: =IF(E14=0,"",G14/E14*100)
G15: =F15-E15 | H15: =IF(E15=0,"",G15/E15*100)
G16: =F16-E16 | H16: =IF(E16=0,"",G16/E16*100)
G17: =F17-E17 | H17: =IF(E17=0,"",G17/E17*100)
... G26: =F26-E26 | H26: =IF(E26=0,"",G26/E26*100)
A27: 合计1 | B27: 合 计 | E27: =ROUND(SUM(E6:E26),2) | F27: =ROUND(SUM(F6:F26),2) | G27: =F27-E27 | H27: =IF(E27=0,"",G27/E27*100)

Sheet 4-15商誉
A1: 表头区域 | B1: 商誉评估明细表
A2: 表头区域 | B2: ='2-分类汇总'!B2
A3: 表头区域 | I3: 表4-15
A4: 表头区域 | B4: ='2-分类汇总'!B4 | I4: ='2-分类汇总'!H4
A5: 检索表头 | B5: 序号 | C5: 内容或名称 | D5: 取得日期 | E5: 账面价值 | F5: 评估价值 | G5: 增值额 | H5: 增值率% | I5: 备注
G6: =F6-E6 | H6: =IF(E6=0,"",G6/E6*100)
G7: =F7-E7 | H7: =IF(E7=0,"",G7/E7*100)
G8: =F8-E8 | H8: =IF(E8=0,"",G8/E8*100)
G9: =F9-E9 | H9: =IF(E9=0,"",G9/E9*100)
G10: =F10-E10 | H10: =IF(E10=0,"",G10/E10*100)
G11: =F11-E11 | H11: =IF(E11=0,"",G11/E11*100)
G12: =F12-E12 | H12: =IF(E12=0,"",G12/E12*100)
G13: =F13-E13 | H13: =IF(E13=0,"",G13/E13*100)
G14: =F14-E14 | H14: =IF(E14=0,"",G14/E14*100)
G15: =F15-E15 | H15: =IF(E15=0,"",G15/E15*100)
G16: =F16-E16 | H16: =IF(E16=0,"",G16/E16*100)
G17: =F17-E17 | H17: =IF(E17=0,"",G17/E17*100)
... G23: =F23-E23 | H23: =IF(E23=0,"",G23/E23*100)
A24: 合计1 | B24: 合 计 | E24: =ROUND(SUM(E6:E23),2) | F24: =ROUND(SUM(F6:F23),2) | G24: =F24-E24 | H24: =IF(E24=0,"",G24/E24*100)
A25: 坏账准备 | B25: 减：商誉减值准备 | G25: =F25-E25 | H25: =IF(E25=0,"",G25/E25*100)
A26: 合计2 | B26: 合 计 | E26: =E24-E25 | F26: =F24-F25 | G26: =F26-E26 | H26: =IF(E26=0,"",G26/E26*100)

Sheet 4-16长期待摊费用
A1: 表头区域 | B1: 长期待摊费用评估明细表
A2: 表头区域 | B2: ='2-分类汇总'!B2
A3: 表头区域 | L3: 表4-16
A4: 表头区域 | B4: ='2-分类汇总'!B4 | L4: ='2-分类汇总'!H4
A5: 检索表头 | B5: 序号 | C5: 费用名称或内容 | D5: 形成日期 | E5: 原始发生额 | F5: 预计摊 销月数 | G5: 账面价值 | H5: 尚存受 益月数 | I5: 评估价值 | J5: 增值额 | K5: 增值率% | L5: 备注
J6: =I6-G6 | K6: =IF(G6=0,"",J6/G6*100)
J7: =I7-G7 | K7: =IF(G7=0,"",J7/G7*100)
J8: =I8-G8 | K8: =IF(G8=0,"",J8/G8*100)
J9: =I9-G9 | K9: =IF(G9=0,"",J9/G9*100)
J10: =I10-G10 | K10: =IF(G10=0,"",J10/G10*100)
J11: =I11-G11 | K11: =IF(G11=0,"",J11/G11*100)
J12: =I12-G12 | K12: =IF(G12=0,"",J12/G12*100)
J13: =I13-G13 | K13: =IF(G13=0,"",J13/G13*100)
J14: =I14-G14 | K14: =IF(G14=0,"",J14/G14*100)
J15: =I15-G15 | K15: =IF(G15=0,"",J15/G15*100)
J16: =I16-G16 | K16: =IF(G16=0,"",J16/G16*100)
J17: =I17-G17 | K17: =IF(G17=0,"",J17/G17*100)
... J28: =I28-G28 | K28: =IF(G28=0,"",J28/G28*100)
A29: 合计1 | B29: 合 计 | E29: =ROUND(SUM(E6:E28),2) | G29: =ROUND(SUM(G6:G28),2) | I29: =ROUND(SUM(I6:I28),2) | J29: =I29-G29 | K29: =IF(G29=0,"",J29/G29*100)

Sheet 4-17递延所得税资产
A1: 表头区域 | B1: 递延所得税资产评估明细表
A2: 表头区域 | B2: ='2-分类汇总'!B2
A3: 表头区域 | I3: 表4-17
A4: 表头区域 | B4: ='2-分类汇总'!B4 | I4: ='2-分类汇总'!H4
A5: 检索表头 | B5: 序号 | C5: 内容或名称 | D5: 发生日期 | E5: 账面价值 | F5: 评估价值 | G5: 增值额 | H5: 增值率% | I5: 备注
G6: =F6-E6 | H6: =IF(E6=0,"",G6/E6*100)
G7: =F7-E7 | H7: =IF(E7=0,"",G7/E7*100)
G8: =F8-E8 | H8: =IF(E8=0,"",G8/E8*100)
G9: =F9-E9 | H9: =IF(E9=0,"",G9/E9*100)
G10: =F10-E10 | H10: =IF(E10=0,"",G10/E10*100)
G11: =F11-E11 | H11: =IF(E11=0,"",G11/E11*100)
G12: =F12-E12 | H12: =IF(E12=0,"",G12/E12*100)
G13: =F13-E13 | H13: =IF(E13=0,"",G13/E13*100)
G14: =F14-E14 | H14: =IF(E14=0,"",G14/E14*100)
G15: =F15-E15 | H15: =IF(E15=0,"",G15/E15*100)
G16: =F16-E16 | H16: =IF(E16=0,"",G16/E16*100)
G17: =F17-E17 | H17: =IF(E17=0,"",G17/E17*100)
... G27: =F27-E27 | H27: =IF(E27=0,"",G27/E27*100)
A28: 合计1 | B28: 合 计 | E28: =ROUND(SUM(E6:E27),2) | F28: =ROUND(SUM(F6:F27),2) | G28: =F28-E28 | H28: =IF(E28=0,"",G28/E28*100)

Sheet 4-18其他非流动资产
A1: 表头区域 | B1: 其他非流动资产评估明细表
A2: 表头区域 | B2: ='2-分类汇总'!B2
A3: 表头区域 | I3: 表4-18
A4: 表头区域 | B4: ='2-分类汇总'!B4 | I4: ='2-分类汇总'!H4
A5: 检索表头 | B5: 序号 | C5: 内容或名称 | D5: 取得日期 | E5: 账面价值 | F5: 评估价值 | G5: 增值额 | H5: 增值率% | I5: 备注
G6: =F6-E6 | H6: =IF(E6=0,"",G6/E6*100)
G7: =F7-E7 | H7: =IF(E7=0,"",G7/E7*100)
G8: =F8-E8 | H8: =IF(E8=0,"",G8/E8*100)
G9: =F9-E9 | H9: =IF(E9=0,"",G9/E9*100)
G10: =F10-E10 | H10: =IF(E10=0,"",G10/E10*100)
G11: =F11-E11 | H11: =IF(E11=0,"",G11/E11*100)
G12: =F12-E12 | H12: =IF(E12=0,"",G12/E12*100)
G13: =F13-E13 | H13: =IF(E13=0,"",G13/E13*100)
G14: =F14-E14 | H14: =IF(E14=0,"",G14/E14*100)
G15: =F15-E15 | H15: =IF(E15=0,"",G15/E15*100)
G16: =F16-E16 | H16: =IF(E16=0,"",G16/E16*100)
G17: =F17-E17 | H17: =IF(E17=0,"",G17/E17*100)
... G27: =F27-E27 | H27: =IF(E27=0,"",G27/E27*100)
A28: 合计1 | B28: 合 计 | E28: =SUM(E6:E27) | F28: =SUM(F6:F27) | G28: =F28-E28 | H28: =IF(E28=0,"",G28/E28*100)

Sheet 5-流动负债汇总
B1: 流动负债评估汇总表
B2: ='2-分类汇总'!B2
H3: 表5
B4: ='2-分类汇总'!B4 | H4: ='2-分类汇总'!H4
B5: 编号 | C5: 项目编号 | D5: 科目名称 | E5: 账面价值 | F5: 评估价值 | G5: 增值额 | H5: 增值率%
B6: 5-1 | C6: 短期借款 | D6: 短期借款 | E6: ='5-1短期借款'!J28 | F6: ='5-1短期借款'!K28 | G6: =F6-E6 | H6: =IF(E6=0,"",G6/E6*100)
B7: 5-2 | C7: 交融负债 | D7: 交易性金融负债 | E7: ='5-2交易性金融负债'!F29 | F7: ='5-2交易性金融负债'!G29 | G7: =F7-E7 | H7: =IF(E7=0,"",G7/E7*100)
B8: 5-3 | C8: 衍金负债 | D8: 衍生金融负债 | E8: ='5-3衍生金融负债'!G31 | F8: ='5-3衍生金融负债'!H31 | G8: =F8-E8 | H8: =IF(E8=0,"",G8/E8*100)
B9: 5-4 | C9: 应付票据 | D9: 应付票据 | E9: ='5-4应付票据'!G30 | F9: ='5-4应付票据'!H30 | G9: =F9-E9 | H9: =IF(E9=0,"",G9/E9*100)
B10: 5-5 | C10: 应付账款 | D10: 应付账款 | E10: ='5-5应付账款'!I28 | F10: ='5-5应付账款'!J28 | G10: =F10-E10 | H10: =IF(E10=0,"",G10/E10*100)
B11: 5-6 | C11: 预收账款 | D11: 预收款项 | E11: ='5-6预收款项'!I28 | F11: ='5-6预收款项'!J28 | G11: =F11-E11 | H11: =IF(E11=0,"",G11/E11*100)
B12: 5-7 | C12: 合同负债 | D12: 合同负债 | E12: ='5-7合同负债'!F28 | F12: ='5-7合同负债'!G28 | G12: =F12-E12 | H12: =IF(E12=0,"",G12/E12*100)
B13: 5-8 | C13: 应付薪酬 | D13: 应付职工薪酬 | E13: ='5-8应付职工薪酬'!E26 | F13: ='5-8应付职工薪酬'!F26 | G13: =F13-E13 | H13: =IF(E13=0,"",G13/E13*100)
B14: 5-9 | C14: 应交税费 | D14: 应交税费 | E14: ='5-9应交税费'!F27 | F14: ='5-9应交税费'!G27 | G14: =F14-E14 | H14: =IF(E14=0,"",G14/E14*100)
B15: 5-10 | C15: 其付汇总 | D15: 其他应付款 | E15: ='5-10其他应付款汇总表'!E26 | F15: ='5-10其他应付款汇总表'!F26 | G15: =F15-E15 | H15: =IF(E15=0,"",G15/E15*100)
B16: 5-11 | C16: 持有待债 | D16: 持有待售负债 | E16: ='5-11持有待售负债'!F27 | F16: ='5-11持有待售负债'!G27 | G16: =F16-E16 | H16: =IF(E16=0,"",G16/E16*100)
B17: 5-12 | C17: 到期非债 | D17: 一年内到期的非流动负债 | E17: ='5-12一年到期非流动负债'!J28 | F17: ='5-12一年到期非流动负债'!K28 | G17: =F17-E17 | H17: =IF(E17=0,"",G17/E17*100)
B18: 5-13 | C18: 其他流债 | D18: 其他流动负债 | E18: ='5-13其他流动负债'!F26 | F18: ='5-13其他流动负债'!G26 | G18: =F18-E18 | H18: =IF(E18=0,"",G18/E18*100)
H19: =IF(E19=0,"",G19/E19*100)
H20: =IF(E20=0,"",G20/E20*100)
H21: =IF(E21=0,"",G21/E21*100)
H22: =IF(E22=0,"",G22/E22*100)
H23: =IF(E23=0,"",G23/E23*100)
H24: =IF(E24=0,"",G24/E24*100)
H25: =IF(E25=0,"",G25/E25*100)
H26: =IF(E26=0,"",G26/E26*100)
A27: 合计1 | C27: 流债汇总 | D27: 流动负债合计 | E27: =SUM(E6:E26) | F27: =SUM(F6:F26) | G27: =F27-E27 | H27: =IF(E27=0,"",G27/E27*100)

Sheet 5-1短期借款
A1: 表头区域 | B1: 短期借款评估明细表
A2: 表头区域 | B2: ='2-分类汇总'!B2
A3: 表头区域 | N3: 表5-1
A4: 表头区域 | B4: ='2-分类汇总'!B4 | N4: ='2-分类汇总'!H4
A5: 检索表头 | B5: 序号 | C5: 放款银行（或机构）名称 | D5: 发生日期 | E5: 到期日 | F5: 年利率% | G5: 币种 | H5: 外币账面金额 | I5: 评估基准日汇率 | J5: 账面价值 | K5: 评估价值 | L5: 增值额 | M5: 增值率% | N5: 备注
L6: =K6-J6 | M6: =IF(J6=0,"",L6/J6*100)
L7: =K7-J7 | M7: =IF(J7=0,"",L7/J7*100)
L8: =K8-J8 | M8: =IF(J8=0,"",L8/J8*100)
L9: =K9-J9 | M9: =IF(J9=0,"",L9/J9*100)
L10: =K10-J10 | M10: =IF(J10=0,"",L10/J10*100)
L11: =K11-J11 | M11: =IF(J11=0,"",L11/J11*100)
L12: =K12-J12 | M12: =IF(J12=0,"",L12/J12*100)
L13: =K13-J13 | M13: =IF(J13=0,"",L13/J13*100)
L14: =K14-J14 | M14: =IF(J14=0,"",L14/J14*100)
L15: =K15-J15 | M15: =IF(J15=0,"",L15/J15*100)
L16: =K16-J16 | M16: =IF(J16=0,"",L16/J16*100)
L17: =K17-J17 | M17: =IF(J17=0,"",L17/J17*100)
... L27: =K27-J27 | M27: =IF(J27=0,"",L27/J27*100)
A28: 合计1 | B28: 合 计 | H28: =ROUND(SUM(H6:H27),2) | J28: =ROUND(SUM(J6:J27),2) | K28: =ROUND(SUM(K6:K27),2) | L28: =K28-J28 | M28: =IF(J28=0,"",L28/J28*100)

Sheet 5-2交易性金融负债
A1: 表头区域 | B1: 交易性金融负债评估明细表
A2: 表头区域 | B2: ='2-分类汇总'!B2
A3: 表头区域 | J3: 表5-2
A4: 表头区域 | B4: ='2-分类汇总'!B4 | J4: ='2-分类汇总'!H4
A5: 检索表头 | B5: 序号 | C5: 户名（结算对象) | D5: 发生日期 | E5: 业务内容 | F5: 账面价值 | G5: 评估价值 | H5: 增值额 | I5: 增值率% | J5: 备注
H6: =G6-F6 | I6: =IF(F6=0,"",H6/F6*100)
H7: =G7-F7 | I7: =IF(F7=0,"",H7/F7*100)
H8: =G8-F8 | I8: =IF(F8=0,"",H8/F8*100)
H9: =G9-F9 | I9: =IF(F9=0,"",H9/F9*100)
H10: =G10-F10 | I10: =IF(F10=0,"",H10/F10*100)
H11: =G11-F11 | I11: =IF(F11=0,"",H11/F11*100)
H12: =G12-F12 | I12: =IF(F12=0,"",H12/F12*100)
H13: =G13-F13 | I13: =IF(F13=0,"",H13/F13*100)
H14: =G14-F14 | I14: =IF(F14=0,"",H14/F14*100)
H15: =G15-F15 | I15: =IF(F15=0,"",H15/F15*100)
H16: =G16-F16 | I16: =IF(F16=0,"",H16/F16*100)
H17: =G17-F17 | I17: =IF(F17=0,"",H17/F17*100)
... H28: =G28-F28 | I28: =IF(F28=0,"",H28/F28*100)
A29: 合计1 | B29: 合 计 | F29: =ROUND(SUM(F6:F28),2) | G29: =ROUND(SUM(G6:G28),2) | H29: =G29-F29 | I29: =IF(F29=0,"",H29/F29*100)

Sheet 5-3衍生金融负债
A1: 表头区域 | B1: 衍生金融负债评估明细表
A2: 表头区域 | B2: ='2-分类汇总'!B2
A3: 表头区域 | K3: 表5-3
A4: 表头区域 | B4: ='2-分类汇总'!B4 | K4: ='2-分类汇总'!H4
A5: 检索表头 | B5: 序号 | C5: 户名（结算对象) | D5: 发生日期 | E5: 到期日 | F5: 票面利率% | G5: 账面价值 | H5: 评估价值 | I5: 增值额 | J5: 增值率% | K5: 备注
I6: =H6-G6 | J6: =IF(G6=0,"",I6/G6*100)
I7: =H7-G7 | J7: =IF(G7=0,"",I7/G7*100)
I8: =H8-G8 | J8: =IF(G8=0,"",I8/G8*100)
I9: =H9-G9 | J9: =IF(G9=0,"",I9/G9*100)
I10: =H10-G10 | J10: =IF(G10=0,"",I10/G10*100)
I11: =H11-G11 | J11: =IF(G11=0,"",I11/G11*100)
I12: =H12-G12 | J12: =IF(G12=0,"",I12/G12*100)
I13: =H13-G13 | J13: =IF(G13=0,"",I13/G13*100)
I14: =H14-G14 | J14: =IF(G14=0,"",I14/G14*100)
I15: =H15-G15 | J15: =IF(G15=0,"",I15/G15*100)
I16: =H16-G16 | J16: =IF(G16=0,"",I16/G16*100)
I17: =H17-G17 | J17: =IF(G17=0,"",I17/G17*100)
... I30: =H30-G30 | J30: =IF(G30=0,"",I30/G30*100)
A31: 合计1 | B31: 合 计 | G31: =ROUND(SUM(G6:G30),2) | H31: =ROUND(SUM(H6:H30),2) | I31: =H31-G31 | J31: =IF(G31=0,"",I31/G31*100)

Sheet 5-4应付票据
A1: 表头区域 | B1: 应付票据评估明细表
A2: 表头区域 | B2: ='2-分类汇总'!B2
A3: 表头区域 | K3: 表5-4
A4: 表头区域 | B4: ='2-分类汇总'!B4 | K4: ='2-分类汇总'!H4
A5: 检索表头 | B5: 序号 | C5: 户名（结算对象) | D5: 发生日期 | E5: 到期日 | F5: 票面利率% | G5: 账面价值 | H5: 评估价值 | I5: 增值额 | J5: 增值率% | K5: 备注
I6: =H6-G6 | J6: =IF(G6=0,"",I6/G6*100)
I7: =H7-G7 | J7: =IF(G7=0,"",I7/G7*100)
I8: =H8-G8 | J8: =IF(G8=0,"",I8/G8*100)
I9: =H9-G9 | J9: =IF(G9=0,"",I9/G9*100)
I10: =H10-G10 | J10: =IF(G10=0,"",I10/G10*100)
I11: =H11-G11 | J11: =IF(G11=0,"",I11/G11*100)
I12: =H12-G12 | J12: =IF(G12=0,"",I12/G12*100)
I13: =H13-G13 | J13: =IF(G13=0,"",I13/G13*100)
I14: =H14-G14 | J14: =IF(G14=0,"",I14/G14*100)
I15: =H15-G15 | J15: =IF(G15=0,"",I15/G15*100)
I16: =H16-G16 | J16: =IF(G16=0,"",I16/G16*100)
I17: =H17-G17 | J17: =IF(G17=0,"",I17/G17*100)
... I29: =H29-G29 | J29: =IF(G29=0,"",I29/G29*100)
A30: 合计1 | B30: 合 计 | G30: =ROUND(SUM(G6:G29),2) | H30: =ROUND(SUM(H6:H29),2) | I30: =H30-G30 | J30: =IF(G30=0,"",I30/G30*100)

Sheet 5-5应付账款
A1: 表头区域 | B1: 应付账款评估明细表
A2: 表头区域 | B2: ='2-分类汇总'!B2
A3: 表头区域 | M3: 表5-5
A4: 表头区域 | B4: ='2-分类汇总'!B4 | M4: ='2-分类汇总'!H4
A5: 检索表头 | B5: 序号 | C5: 户名（结算对象) | D5: 发生日期 | E5: 业务内容 | F5: 币种 | G5: 外币账面金额 | H5: 评估基准日汇率 | I5: 账面价值 | J5: 评估价值 | K5: 增值额 | L5: 增值率% | M5: 备注
K6: =J6-I6 | L6: =IF(I6=0,"",K6/I6*100)
K7: =J7-I7 | L7: =IF(I7=0,"",K7/I7*100)
K8: =J8-I8 | L8: =IF(I8=0,"",K8/I8*100)
K9: =J9-I9 | L9: =IF(I9=0,"",K9/I9*100)
K10: =J10-I10 | L10: =IF(I10=0,"",K10/I10*100)
K11: =J11-I11 | L11: =IF(I11=0,"",K11/I11*100)
K12: =J12-I12 | L12: =IF(I12=0,"",K12/I12*100)
K13: =J13-I13 | L13: =IF(I13=0,"",K13/I13*100)
K14: =J14-I14 | L14: =IF(I14=0,"",K14/I14*100)
K15: =J15-I15 | L15: =IF(I15=0,"",K15/I15*100)
K16: =J16-I16 | L16: =IF(I16=0,"",K16/I16*100)
K17: =J17-I17 | L17: =IF(I17=0,"",K17/I17*100)
... K27: =J27-I27 | L27: =IF(I27=0,"",K27/I27*100)
A28: 合计1 | B28: 合 计 | G28: =ROUND(SUM(G6:G27),2) | I28: =ROUND(SUM(I6:I27),2) | J28: =ROUND(SUM(J6:J27),2) | K28: =J28-I28 | L28: =IF(I28=0,"",K28/I28*100)

Sheet 5-6预收款项
A1: 表头区域 | B1: 预收款项评估明细表
A2: 表头区域 | B2: ='2-分类汇总'!B2
A3: 表头区域 | M3: 表5-6
A4: 表头区域 | B4: ='2-分类汇总'!B4 | M4: ='2-分类汇总'!H4
A5: 检索表头 | B5: 序号 | C5: 户名（结算对象) | D5: 发生日期 | E5: 业务内容 | F5: 币种 | G5: 外币账面金额 | H5: 评估基准日汇率 | I5: 账面价值 | J5: 评估价值 | K5: 增值额 | L5: 增值率% | M5: 备注
K6: =J6-I6 | L6: =IF(I6=0,"",K6/I6*100)
K7: =J7-I7 | L7: =IF(I7=0,"",K7/I7*100)
K8: =J8-I8 | L8: =IF(I8=0,"",K8/I8*100)
K9: =J9-I9 | L9: =IF(I9=0,"",K9/I9*100)
K10: =J10-I10 | L10: =IF(I10=0,"",K10/I10*100)
K11: =J11-I11 | L11: =IF(I11=0,"",K11/I11*100)
K12: =J12-I12 | L12: =IF(I12=0,"",K12/I12*100)
K13: =J13-I13 | L13: =IF(I13=0,"",K13/I13*100)
K14: =J14-I14 | L14: =IF(I14=0,"",K14/I14*100)
K15: =J15-I15 | L15: =IF(I15=0,"",K15/I15*100)
K16: =J16-I16 | L16: =IF(I16=0,"",K16/I16*100)
K17: =J17-I17 | L17: =IF(I17=0,"",K17/I17*100)
... K27: =J27-I27 | L27: =IF(I27=0,"",K27/I27*100)
A28: 合计1 | B28: 合 计 | G28: =ROUND(SUM(G6:G27),2) | I28: =ROUND(SUM(I6:I27),2) | J28: =ROUND(SUM(J6:J27),2) | K28: =J28-I28 | L28: =IF(I28=0,"",K28/I28*100)

Sheet 5-7合同负债
A1: 表头区域 | B1: 合同负债评估明细表
A2: 表头区域 | B2: ='2-分类汇总'!B2
A3: 表头区域 | J3: 表5-7
A4: 表头区域 | B4: ='2-分类汇总'!B4 | J4: ='2-分类汇总'!H4
A5: 检索表头 | B5: 序号 | C5: 项目及内容 | D5: 发生日期 | E5: 结算内容 | F5: 账面价值 | G5: 评估价值 | H5: 增值额 | I5: 增值率% | J5: 备注
H6: =G6-F6 | I6: =IF(F6=0,"",H6/F6*100)
H7: =G7-F7 | I7: =IF(F7=0,"",H7/F7*100)
H8: =G8-F8 | I8: =IF(F8=0,"",H8/F8*100)
H9: =G9-F9 | I9: =IF(F9=0,"",H9/F9*100)
H10: =G10-F10 | I10: =IF(F10=0,"",H10/F10*100)
H11: =G11-F11 | I11: =IF(F11=0,"",H11/F11*100)
H12: =G12-F12 | I12: =IF(F12=0,"",H12/F12*100)
H13: =G13-F13 | I13: =IF(F13=0,"",H13/F13*100)
H14: =G14-F14 | I14: =IF(F14=0,"",H14/F14*100)
H15: =G15-F15 | I15: =IF(F15=0,"",H15/F15*100)
H16: =G16-F16 | I16: =IF(F16=0,"",H16/F16*100)
H17: =G17-F17 | I17: =IF(F17=0,"",H17/F17*100)
... H27: =G27-F27 | I27: =IF(F27=0,"",H27/F27*100)
A28: 合计1 | B28: 合 计 | F28: =SUM(F6:F27) | G28: =SUM(G6:G27) | H28: =G28-F28 | I28: =IF(F28=0,"",H28/F28*100)

Sheet 5-8应付职工薪酬
A1: 表头区域 | B1: 应付职工薪酬评估明细表
A2: 表头区域 | B2: ='2-分类汇总'!B2
A3: 表头区域 | I3: 表5-8
A4: 表头区域 | B4: ='2-分类汇总'!B4 | I4: ='2-分类汇总'!H4
A5: 检索表头 | B5: 序号 | C5: 结算内容 | D5: 发生日期 | E5: 账面价值 | F5: 评估价值 | G5: 增值额 | H5: 增值率% | I5: 备注
G6: =F6-E6 | H6: =IF(E6=0,"",G6/E6*100)
G7: =F7-E7 | H7: =IF(E7=0,"",G7/E7*100)
G8: =F8-E8 | H8: =IF(E8=0,"",G8/E8*100)
G9: =F9-E9 | H9: =IF(E9=0,"",G9/E9*100)
G10: =F10-E10 | H10: =IF(E10=0,"",G10/E10*100)
G11: =F11-E11 | H11: =IF(E11=0,"",G11/E11*100)
G12: =F12-E12 | H12: =IF(E12=0,"",G12/E12*100)
G13: =F13-E13 | H13: =IF(E13=0,"",G13/E13*100)
G14: =F14-E14 | H14: =IF(E14=0,"",G14/E14*100)
G15: =F15-E15 | H15: =IF(E15=0,"",G15/E15*100)
G16: =F16-E16 | H16: =IF(E16=0,"",G16/E16*100)
G17: =F17-E17 | H17: =IF(E17=0,"",G17/E17*100)
... G25: =F25-E25 | H25: =IF(E25=0,"",G25/E25*100)
A26: 合计1 | B26: 合 计 | E26: =ROUND(SUM(E6:E25),2) | F26: =ROUND(SUM(F6:F25),2) | G26: =F26-E26 | H26: =IF(E26=0,"",G26/E26*100)

Sheet 5-9应交税费
A1: 表头区域 | B1: 应交税费评估明细表
A2: 表头区域 | B2: ='2-分类汇总'!B2
A3: 表头区域 | J3: 表5-9
A4: 表头区域 | B4: ='2-分类汇总'!B4 | J4: ='2-分类汇总'!H4
A5: 检索表头 | B5: 序号 | C5: 征税机关 | D5: 发生日期 | E5: 税费种类 | F5: 账面价值 | G5: 评估价值 | H5: 增值额 | I5: 增值率% | J5: 备注
C6: 根据被评估单位所在地确认国家税务总局的全称填列于此 | H6: =G6-F6 | I6: =IF(F6=0,"",H6/F6*100)
H7: =G7-F7 | I7: =IF(F7=0,"",H7/F7*100)
H8: =G8-F8 | I8: =IF(F8=0,"",H8/F8*100)
H9: =G9-F9 | I9: =IF(F9=0,"",H9/F9*100)
H10: =G10-F10 | I10: =IF(F10=0,"",H10/F10*100)
H11: =G11-F11 | I11: =IF(F11=0,"",H11/F11*100)
H12: =G12-F12 | I12: =IF(F12=0,"",H12/F12*100)
H13: =G13-F13 | I13: =IF(F13=0,"",H13/F13*100)
H14: =G14-F14 | I14: =IF(F14=0,"",H14/F14*100)
H15: =G15-F15 | I15: =IF(F15=0,"",H15/F15*100)
H16: =G16-F16 | I16: =IF(F16=0,"",H16/F16*100)
H17: =G17-F17 | I17: =IF(F17=0,"",H17/F17*100)
H18: =G18-F18 | I18: =IF(F18=0,"",H18/F18*100)
... H26: =G26-F26 | I26: =IF(F26=0,"",H26/F26*100)
A27: 合计1 | B27: 合 计 | F27: =ROUND(SUM(F6:F26),2) | G27: =ROUND(SUM(G6:G26),2) | H27: =G27-F27 | I27: =IF(F27=0,"",H27/F27*100)

Sheet 5-10其他应付款汇总表
B1: 其他应付款评估汇总表
B2: ='2-分类汇总'!B2
H3: 表5-10
B4: ='2-分类汇总'!B4 | H4: ='2-分类汇总'!H4
B5: 编号 | D5: 户名（结算对象) | E5: 账面价值 | F5: 评估价值 | G5: 增值额 | H5: 增值率%
B6: 5-10-1 | C6: 应付利息 | D6: 其他应付款—应付利息 | E6: ='5-10-1应付利息'!H27 | F6: ='5-10-1应付利息'!I27 | G6: =F6-E6 | H6: =IF(E6=0,"",G6/E6*100)
B7: 5-10-2 | C7: 应付股利 | D7: 其他应付款—应付股利（应付利润） | E7: ='5-10-2应付股利（利润）'!F27 | F7: ='5-10-2应付股利（利润）'!G27 | G7: =F7-E7 | H7: =IF(E7=0,"",G7/E7*100)
B8: 5-10-3 | C8: 其他应付 | D8: 其他应付款—其他应付款 | E8: ='5-10-3其他应付款'!I29 | F8: ='5-10-3其他应付款'!J29 | G8: =F8-E8 | H8: =IF(E8=0,"",G8/E8*100)
A26: 合计1 | C26: 其付汇总 | D26: 合 计 | E26: =ROUND(SUM(E6:E25),2) | F26: =ROUND(SUM(F6:F25),2) | G26: =F26-E26 | H26: =IF(E26=0,"",G26/E26*100)

Sheet 5-10-1应付利息
A1: 表头区域 | B1: 其他应付款—应付利息评估明细表
A2: 表头区域 | B2: ='5-10其他应付款汇总表'!B2
A3: 表头区域 | L3: 表5-10-1
A4: 表头区域 | B4: ='5-10其他应付款汇总表'!B4 | L4: ='2-分类汇总'!H4
A5: 检索表头 | B5: 序号 | C5: 户名（结算对象) | D5: 发生日期 | E5: 本金 | F5: 利息所属期间 | G5: 年利息率% | H5: 账面价值 | I5: 评估价值 | J5: 增值额 | K5: 增值率% | L5: 备注
J6: =I6-H6 | K6: =IF(H6=0,"",J6/H6*100)
J7: =I7-H7 | K7: =IF(H7=0,"",J7/H7*100)
J8: =I8-H8 | K8: =IF(H8=0,"",J8/H8*100)
J9: =I9-H9 | K9: =IF(H9=0,"",J9/H9*100)
J10: =I10-H10 | K10: =IF(H10=0,"",J10/H10*100)
J11: =I11-H11 | K11: =IF(H11=0,"",J11/H11*100)
J12: =I12-H12 | K12: =IF(H12=0,"",J12/H12*100)
J13: =I13-H13 | K13: =IF(H13=0,"",J13/H13*100)
J14: =I14-H14 | K14: =IF(H14=0,"",J14/H14*100)
J15: =I15-H15 | K15: =IF(H15=0,"",J15/H15*100)
J16: =I16-H16 | K16: =IF(H16=0,"",J16/H16*100)
J17: =I17-H17 | K17: =IF(H17=0,"",J17/H17*100)
... J26: =I26-H26 | K26: =IF(H26=0,"",J26/H26*100)
A27: 合计1 | B27: 合 计 | E27: =ROUND(SUM(E6:E26),2) | H27: =ROUND(SUM(H6:H26),2) | I27: =ROUND(SUM(I6:I26),2) | J27: =I27-H27 | K27: =IF(H27=0,"",J27/H27*100)

Sheet 5-10-2应付股利（利润）
A1: 表头区域 | B1: 其他应付款—应付股利（应付利润）评估明细表
A2: 表头区域 | B2: ='5-10其他应付款汇总表'!B2
A3: 表头区域 | J3: 表5-10-2
A4: 表头区域 | B4: ='5-10其他应付款汇总表'!B4 | J4: ='2-分类汇总'!H4
A5: 检索表头 | B5: 序号 | C5: 投资单位名称（股东） | D5: 发生日期 | E5: 利润所属期间 | F5: 账面价值 | G5: 评估价值 | H5: 增值额 | I5: 增值率% | J5: 备注
H6: =G6-F6 | I6: =IF(F6=0,"",H6/F6*100)
H7: =G7-F7 | I7: =IF(F7=0,"",H7/F7*100)
H8: =G8-F8 | I8: =IF(F8=0,"",H8/F8*100)
H9: =G9-F9 | I9: =IF(F9=0,"",H9/F9*100)
H10: =G10-F10 | I10: =IF(F10=0,"",H10/F10*100)
H11: =G11-F11 | I11: =IF(F11=0,"",H11/F11*100)
H12: =G12-F12 | I12: =IF(F12=0,"",H12/F12*100)
H13: =G13-F13 | I13: =IF(F13=0,"",H13/F13*100)
H14: =G14-F14 | I14: =IF(F14=0,"",H14/F14*100)
H15: =G15-F15 | I15: =IF(F15=0,"",H15/F15*100)
H16: =G16-F16 | I16: =IF(F16=0,"",H16/F16*100)
H17: =G17-F17 | I17: =IF(F17=0,"",H17/F17*100)
... H26: =G26-F26 | I26: =IF(F26=0,"",H26/F26*100)
A27: 合计1 | B27: 合 计 | F27: =ROUND(SUM(F6:F26),2) | G27: =ROUND(SUM(G6:G26),2) | H27: =G27-F27 | I27: =IF(F27=0,"",H27/F27*100)

Sheet 5-10-3其他应付款
A1: 表头区域 | B1: 其他应付款—其他应付款评估明细表
A2: 表头区域 | B2: ='2-分类汇总'!B2
A3: 表头区域 | M3: 表5-10-3
A4: 表头区域 | B4: ='2-分类汇总'!B4 | M4: ='2-分类汇总'!H4
A5: 检索表头 | B5: 序号 | C5: 户名（结算对象) | D5: 发生日期 | E5: 业务内容 | F5: 币种 | G5: 外币账面金额 | H5: 评估基准日汇率 | I5: 账面价值 | J5: 评估价值 | K5: 增值额 | L5: 增值率% | M5: 备注
K6: =J6-I6 | L6: =IF(I6=0,"",K6/I6*100)
K7: =J7-I7 | L7: =IF(I7=0,"",K7/I7*100)
K8: =J8-I8 | L8: =IF(I8=0,"",K8/I8*100)
K9: =J9-I9 | L9: =IF(I9=0,"",K9/I9*100)
K10: =J10-I10 | L10: =IF(I10=0,"",K10/I10*100)
K11: =J11-I11 | L11: =IF(I11=0,"",K11/I11*100)
K12: =J12-I12 | L12: =IF(I12=0,"",K12/I12*100)
K13: =J13-I13 | L13: =IF(I13=0,"",K13/I13*100)
K14: =J14-I14 | L14: =IF(I14=0,"",K14/I14*100)
K15: =J15-I15 | L15: =IF(I15=0,"",K15/I15*100)
K16: =J16-I16 | L16: =IF(I16=0,"",K16/I16*100)
K17: =J17-I17 | L17: =IF(I17=0,"",K17/I17*100)
... K28: =J28-I28 | L28: =IF(I28=0,"",K28/I28*100)
A29: 合计1 | B29: 合 计 | G29: =ROUND(SUM(G6:G28),2) | I29: =ROUND(SUM(I6:I28),2) | J29: =ROUND(SUM(J6:J28),2) | K29: =J29-I29 | L29: =IF(I29=0,"",K29/I29*100)

Sheet 5-11持有待售负债
A1: 表头区域 | B1: 持有待售负债评估明细表
A2: 表头区域 | B2: ='2-分类汇总'!B2
A3: 表头区域 | J3: 表5-11
A4: 表头区域 | B4: ='2-分类汇总'!B4 | J4: ='2-分类汇总'!H4
A5: 检索表头 | B5: 序号 | C5: 户名（结算对象) | D5: 发生日期 | E5: 结算内容 | F5: 账面价值 | G5: 评估价值 | H5: 增值额 | I5: 增值率% | J5: 备注
H6: =G6-F6 | I6: =IF(F6=0,"",H6/F6*100)
H7: =G7-F7 | I7: =IF(F7=0,"",H7/F7*100)
H8: =G8-F8 | I8: =IF(F8=0,"",H8/F8*100)
H9: =G9-F9 | I9: =IF(F9=0,"",H9/F9*100)
H10: =G10-F10 | I10: =IF(F10=0,"",H10/F10*100)
H11: =G11-F11 | I11: =IF(F11=0,"",H11/F11*100)
H12: =G12-F12 | I12: =IF(F12=0,"",H12/F12*100)
H13: =G13-F13 | I13: =IF(F13=0,"",H13/F13*100)
H14: =G14-F14 | I14: =IF(F14=0,"",H14/F14*100)
H15: =G15-F15 | I15: =IF(F15=0,"",H15/F15*100)
H16: =G16-F16 | I16: =IF(F16=0,"",H16/F16*100)
H17: =G17-F17 | I17: =IF(F17=0,"",H17/F17*100)
... H26: =G26-F26 | I26: =IF(F26=0,"",H26/F26*100)
A27: 合计1 | B27: 合 计 | F27: =ROUND(SUM(F6:F26),2) | G27: =ROUND(SUM(G6:G26),2) | H27: =G27-F27 | I27: =IF(F27=0,"",H27/F27*100)

Sheet 5-12一年到期非流动负债
A1: 表头区域 | B1: 一年内到期的非流动负债评估明细表
A2: 表头区域 | B2: ='2-分类汇总'!B2
A3: 表头区域 | N3: 表5-12
A4: 表头区域 | B4: ='2-分类汇总'!B4 | N4: ='2-分类汇总'!H4
A5: 检索表头 | B5: 序号 | C5: 结算项目 | D5: 发生日期 | E5: 到期日 | F5: 年利率% | G5: 币种 | H5: 外币账面金额 | I5: 评估基准日汇率 | J5: 账面价值 | K5: 评估价值 | L5: 增值额 | M5: 增值率% | N5: 备注
L6: =K6-J6 | M6: =IF(J6=0,"",L6/J6*100)
L7: =K7-J7 | M7: =IF(J7=0,"",L7/J7*100)
L8: =K8-J8 | M8: =IF(J8=0,"",L8/J8*100)
L9: =K9-J9 | M9: =IF(J9=0,"",L9/J9*100)
L10: =K10-J10 | M10: =IF(J10=0,"",L10/J10*100)
L11: =K11-J11 | M11: =IF(J11=0,"",L11/J11*100)
L12: =K12-J12 | M12: =IF(J12=0,"",L12/J12*100)
L13: =K13-J13 | M13: =IF(J13=0,"",L13/J13*100)
L14: =K14-J14 | M14: =IF(J14=0,"",L14/J14*100)
L15: =K15-J15 | M15: =IF(J15=0,"",L15/J15*100)
L16: =K16-J16 | M16: =IF(J16=0,"",L16/J16*100)
L17: =K17-J17 | M17: =IF(J17=0,"",L17/J17*100)
... L27: =K27-J27 | M27: =IF(J27=0,"",L27/J27*100)
A28: 合计1 | B28: 合 计 | H28: =ROUND(SUM(H6:H27),2) | J28: =SUM(J6:J27) | K28: =SUM(K6:K27) | L28: =K28-J28 | M28: =IF(J28=0,"",L28/J28*100)

Sheet 5-13其他流动负债
A1: 表头区域 | B1: 其他流动负债评估明细表
A2: 表头区域 | B2: ='2-分类汇总'!B2
A3: 表头区域 | J3: 表5-13
A4: 表头区域 | B4: ='2-分类汇总'!B4 | J4: ='2-分类汇总'!H4
A5: 检索表头 | B5: 序号 | C5: 户名（结算对象) | D5: 发生日期 | E5: 结算内容 | F5: 账面价值 | G5: 评估价值 | H5: 增值额 | I5: 增值率% | J5: 备注
H6: =G6-F6 | I6: =IF(F6=0,"",H6/F6*100)
H7: =G7-F7 | I7: =IF(F7=0,"",H7/F7*100)
H8: =G8-F8 | I8: =IF(F8=0,"",H8/F8*100)
H9: =G9-F9 | I9: =IF(F9=0,"",H9/F9*100)
H10: =G10-F10 | I10: =IF(F10=0,"",H10/F10*100)
H11: =G11-F11 | I11: =IF(F11=0,"",H11/F11*100)
H12: =G12-F12 | I12: =IF(F12=0,"",H12/F12*100)
H13: =G13-F13 | I13: =IF(F13=0,"",H13/F13*100)
H14: =G14-F14 | I14: =IF(F14=0,"",H14/F14*100)
H15: =G15-F15 | I15: =IF(F15=0,"",H15/F15*100)
H16: =G16-F16 | I16: =IF(F16=0,"",H16/F16*100)
H17: =G17-F17 | I17: =IF(F17=0,"",H17/F17*100)
... H25: =G25-F25 | I25: =IF(F25=0,"",H25/F25*100)
A26: 合计1 | B26: 合 计 | F26: =SUM(F6:F25) | G26: =SUM(G6:G25) | H26: =G26-F26 | I26: =IF(F26=0,"",H26/F26*100)

Sheet 6-非流动负债汇总
B1: 非流动负债评估汇总表
B2: ='2-分类汇总'!B2
H3: 表6
B4: ='2-分类汇总'!B4 | H4: ='2-分类汇总'!H4
B5: 编号 | C5: 项目编号 | D5: 科目名称 | E5: 账面价值 | F5: 评估价值 | G5: 增值额 | H5: 增值率%
B6: 6-1 | C6: 长期借款 | D6: 长期借款 | E6: ='6-1长期借款'!J29 | F6: ='6-1长期借款'!L29 | G6: =F6-E6 | H6: =IF(E6=0,"",G6/E6*100)
B7: 6-2 | C7: 应付债券 | D7: 应付债券 | E7: ='6-2应付债券'!H28 | F7: ='6-2应付债券'!I28 | G7: =F7-E7 | H7: =IF(E7=0,"",G7/E7*100)
B8: 6-3 | C8: 租赁负债 | D8: 租赁负债 | E8: ='6-3租赁负债'!G28 | F8: ='6-3租赁负债'!H28 | G8: =F8-E8 | H8: =IF(E8=0,"",G8/E8*100)
B9: 6-4 | C9: 长期应付 | D9: 长期应付款 | E9: ='6-4长期应付款'!K30 | F9: ='6-4长期应付款'!L30 | G9: =F9-E9 | H9: =IF(E9=0,"",G9/E9*100)
B10: 6-5 | C10: 长期薪酬 | D10: 长期应付职工薪酬 | E10: ='6-5长期应付职工薪酬'!E26 | F10: ='6-5长期应付职工薪酬'!F26 | G10: =F10-E10 | H10: =IF(E10=0,"",G10/E10*100)
B11: 6-6 | C11: 预计负债 | D11: 预计负债 | E11: ='6-6预计负债'!F28 | F11: ='6-6预计负债'!G28 | G11: =F11-E11 | H11: =IF(E11=0,"",G11/E11*100)
B12: 6-7 | C12: 递延收益 | D12: 递延收益 | E12: ='6-7递延收益'!G28 | F12: ='6-7递延收益'!H28 | G12: =F12-E12 | H12: =IF(E12=0,"",G12/E12*100)
B13: 6-8 | C13: 递延负债 | D13: 递延所得税负债 | E13: ='6-8递延所得税负债'!E28 | F13: ='6-8递延所得税负债'!F28 | G13: =F13-E13 | H13: =IF(E13=0,"",G13/E13*100)
B14: 6-9 | C14: 其他非债 | D14: 其他非流动负债 | E14: ='6-9其他非流动负债'!F28 | F14: ='6-9其他非流动负债'!G28 | G14: =F14-E14 | H14: =IF(E14=0,"",G14/E14*100)
H15: =IF(E15=0,"",G15/E15*100)
H16: =IF(E16=0,"",G16/E16*100)
H17: =IF(E17=0,"",G17/E17*100)
H18: =IF(E18=0,"",G18/E18*100)
H19: =IF(E19=0,"",G19/E19*100)
H20: =IF(E20=0,"",G20/E20*100)
H21: =IF(E21=0,"",G21/E21*100)
H22: =IF(E22=0,"",G22/E22*100)
H23: =IF(E23=0,"",G23/E23*100)
H24: =IF(E24=0,"",G24/E24*100)
H25: =IF(E25=0,"",G25/E25*100)
H26: =IF(E26=0,"",G26/E26*100)
A27: 合计1 | C27: 非债汇总 | D27: 非流动负债合计 | E27: =ROUND(SUM(E6:E26),2) | F27: =ROUND(SUM(F6:F26),2) | G27: =F27-E27 | H27: =IF(E27=0,"",G27/E27*100)

Sheet 6-1长期借款
A1: 表头区域 | B1: 长期借款评估明细表
A2: 表头区域 | B2: ='2-分类汇总'!B2
A3: 表头区域 | O3: 表6-1
A4: 表头区域 | B4: ='2-分类汇总'!B4 | O4: ='2-分类汇总'!H4
A5: 检索表头 | B5: 序号 | C5: 放款银行（或机构）名称 | D5: 发生日期 | E5: 到期日 | F5: 年利率% | G5: 币种 | H5: 外币账面金额 | I5: 评估基准日汇率 | J5: 账面价值 | K5: 外币基准日汇率 | L5: 评估价值 | M5: 增值额 | N5: 增值率% | O5: 备注
M6: =L6-J6 | N6: =IF(J6=0,"",M6/J6*100)
M7: =L7-J7 | N7: =IF(J7=0,"",M7/J7*100)
M8: =L8-J8 | N8: =IF(J8=0,"",M8/J8*100)
M9: =L9-J9 | N9: =IF(J9=0,"",M9/J9*100)
M10: =L10-J10 | N10: =IF(J10=0,"",M10/J10*100)
M11: =L11-J11 | N11: =IF(J11=0,"",M11/J11*100)
M12: =L12-J12 | N12: =IF(J12=0,"",M12/J12*100)
M13: =L13-J13 | N13: =IF(J13=0,"",M13/J13*100)
M14: =L14-J14 | N14: =IF(J14=0,"",M14/J14*100)
M15: =L15-J15 | N15: =IF(J15=0,"",M15/J15*100)
M16: =L16-J16 | N16: =IF(J16=0,"",M16/J16*100)
M17: =L17-J17 | N17: =IF(J17=0,"",M17/J17*100)
... M28: =L28-J28 | N28: =IF(J28=0,"",M28/J28*100)
A29: 合计1 | B29: 合 计 | H29: =ROUND(SUM(H6:H28),2) | J29: =ROUND(SUM(J6:J28),2) | L29: =ROUND(SUM(L6:L28),2) | M29: =L29-J29 | N29: =IF(J29=0,"",M29/J29*100)

Sheet 6-2应付债券
A1: 表头区域 | B1: 应付债券评估明细表
A2: 表头区域 | B2: ='2-分类汇总'!B2
A3: 表头区域 | L3: 表6-2
A4: 表头区域 | B4: ='2-分类汇总'!B4 | L4: ='2-分类汇总'!H4
A5: 检索表头 | B5: 序号 | C5: 债券发行单位 | D5: 债券种类 | E5: 发生日期 | F5: 到期日 | G5: 票面利率% | H5: 账面价值 | I5: 评估价值 | J5: 增值额 | K5: 增值率% | L5: 备 注
J6: =I6-H6 | K6: =IF(H6=0,"",J6/H6*100)
J7: =I7-H7 | K7: =IF(H7=0,"",J7/H7*100)
J8: =I8-H8 | K8: =IF(H8=0,"",J8/H8*100)
J9: =I9-H9 | K9: =IF(H9=0,"",J9/H9*100)
J10: =I10-H10 | K10: =IF(H10=0,"",J10/H10*100)
J11: =I11-H11 | K11: =IF(H11=0,"",J11/H11*100)
J12: =I12-H12 | K12: =IF(H12=0,"",J12/H12*100)
J13: =I13-H13 | K13: =IF(H13=0,"",J13/H13*100)
J14: =I14-H14 | K14: =IF(H14=0,"",J14/H14*100)
J15: =I15-H15 | K15: =IF(H15=0,"",J15/H15*100)
J16: =I16-H16 | K16: =IF(H16=0,"",J16/H16*100)
J17: =I17-H17 | K17: =IF(H17=0,"",J17/H17*100)
... J27: =I27-H27 | K27: =IF(H27=0,"",J27/H27*100)
A28: 合计1 | B28: 合 计 | H28: =ROUND(SUM(H6:H27),2) | I28: =ROUND(SUM(I6:I27),2) | J28: =I28-H28 | K28: =IF(H28=0,"",J28/H28*100)

Sheet 6-3租赁负债
A1: 表头区域 | B1: 租赁负债评估明细表
A2: 表头区域 | B2: ='2-分类汇总'!B2
A3: 表头区域 | K3: 表6-3
A4: 表头区域 | B4: ='2-分类汇总'!B4 | K4: ='2-分类汇总'!H4
A5: 检索表头1 | B5: 序号 | C5: 户名（结算对象) | D5: 发生日期 | E5: 到期日 | F5: 利率（%） | G5: 账面价值 | H5: 评估价值 | I5: 增值额 | J5: 增值率% | K5: 备注
A6: 检索表头2
I7: =H7-G7 | J7: =IF(G7=0,"",I7/G7*100)
I8: =H8-G8 | J8: =IF(G8=0,"",I8/G8*100)
I9: =H9-G9 | J9: =IF(G9=0,"",I9/G9*100)
I10: =H10-G10 | J10: =IF(G10=0,"",I10/G10*100)
I11: =H11-G11 | J11: =IF(G11=0,"",I11/G11*100)
I12: =H12-G12 | J12: =IF(G12=0,"",I12/G12*100)
I13: =H13-G13 | J13: =IF(G13=0,"",I13/G13*100)
I14: =H14-G14 | J14: =IF(G14=0,"",I14/G14*100)
I15: =H15-G15 | J15: =IF(G15=0,"",I15/G15*100)
I16: =H16-G16 | J16: =IF(G16=0,"",I16/G16*100)
I17: =H17-G17 | J17: =IF(G17=0,"",I17/G17*100)
I18: =H18-G18 | J18: =IF(G18=0,"",I18/G18*100)
... I27: =H27-G27 | J27: =IF(G27=0,"",I27/G27*100)
A28: 合计1 | B28: 合 计 | G28: =ROUND(SUM(G7:G27),2) | H28: =ROUND(SUM(H7:H27),2) | I28: =H28-G28 | J28: =IF(G28=0,"",I28/G28*100)

Sheet 6-4长期应付款
A1: 表头区域 | B1: 长期应付款评估明细表
A2: 表头区域 | B2: ='2-分类汇总'!B2
A3: 表头区域 | O3: 表6-4
A4: 表头区域 | B4: ='2-分类汇总'!B4 | O4: ='2-分类汇总'!H4
A5: 检索表头1 | B5: 序号 | C5: 户名（结算对象) | D5: 发生日期 | E5: 业务内容 | F5: 币种 | G5: 外币账面金额 | H5: 评估基准日汇率 | I5: 账面价值 | L5: 评估价值 | M5: 增值额 | N5: 增值率% | O5: 备注
A6: 检索表头2 | I6: 初始额 | J6: 利息及汇率净损失 | K6: 合计
K7: =SUM(I7:J7) | M7: =L7-K7 | N7: =IF(K7=0,"",M7/K7*100)
K8: =SUM(I8:J8) | M8: =L8-K8 | N8: =IF(K8=0,"",M8/K8*100)
K9: =SUM(I9:J9) | M9: =L9-K9 | N9: =IF(K9=0,"",M9/K9*100)
K10: =SUM(I10:J10) | M10: =L10-K10 | N10: =IF(K10=0,"",M10/K10*100)
K11: =SUM(I11:J11) | M11: =L11-K11 | N11: =IF(K11=0,"",M11/K11*100)
K12: =SUM(I12:J12) | M12: =L12-K12 | N12: =IF(K12=0,"",M12/K12*100)
K13: =SUM(I13:J13) | M13: =L13-K13 | N13: =IF(K13=0,"",M13/K13*100)
K14: =SUM(I14:J14) | M14: =L14-K14 | N14: =IF(K14=0,"",M14/K14*100)
K15: =SUM(I15:J15) | M15: =L15-K15 | N15: =IF(K15=0,"",M15/K15*100)
K16: =SUM(I16:J16) | M16: =L16-K16 | N16: =IF(K16=0,"",M16/K16*100)
K17: =SUM(I17:J17) | M17: =L17-K17 | N17: =IF(K17=0,"",M17/K17*100)
K18: =SUM(I18:J18) | M18: =L18-K18 | N18: =IF(K18=0,"",M18/K18*100)
... K29: =SUM(I29:J29) | M29: =L29-K29 | N29: =IF(K29=0,"",M29/K29*100)
A30: 合计1 | B30: 合 计 | G30: =ROUND(SUM(G6:G29),2) | I30: =ROUND(SUM(I6:I29),2) | J30: =ROUND(SUM(J6:J29),2) | K30: =ROUND(SUM(K6:K29),2) | L30: =ROUND(SUM(L6:L29),2) | M30: =L30-K30 | N30: =IF(K30=0,"",M30/K30*100)

Sheet 6-5长期应付职工薪酬
A1: 表头区域 | B1: 长期应付职工薪酬评估明细表
A2: 表头区域 | B2: ='2-分类汇总'!B2
A3: 表头区域 | I3: 表6-5
A4: 表头区域 | B4: ='2-分类汇总'!B4 | I4: ='2-分类汇总'!H4
A5: 检索表头 | B5: 序号 | C5: 结算内容 | D5: 发生日期 | E5: 账面价值 | F5: 评估价值 | G5: 增值额 | H5: 增值率% | I5: 备注
G6: =F6-E6 | H6: =IF(E6=0,"",G6/E6*100)
G7: =F7-E7 | H7: =IF(E7=0,"",G7/E7*100)
G8: =F8-E8 | H8: =IF(E8=0,"",G8/E8*100)
G9: =F9-E9 | H9: =IF(E9=0,"",G9/E9*100)
G10: =F10-E10 | H10: =IF(E10=0,"",G10/E10*100)
G11: =F11-E11 | H11: =IF(E11=0,"",G11/E11*100)
G12: =F12-E12 | H12: =IF(E12=0,"",G12/E12*100)
G13: =F13-E13 | H13: =IF(E13=0,"",G13/E13*100)
G14: =F14-E14 | H14: =IF(E14=0,"",G14/E14*100)
G15: =F15-E15 | H15: =IF(E15=0,"",G15/E15*100)
G16: =F16-E16 | H16: =IF(E16=0,"",G16/E16*100)
G17: =F17-E17 | H17: =IF(E17=0,"",G17/E17*100)
... G25: =F25-E25 | H25: =IF(E25=0,"",G25/E25*100)
A26: 合计1 | B26: 合 计 | E26: =ROUND(SUM(E6:E25),2) | F26: =ROUND(SUM(F6:F25),2) | G26: =F26-E26 | H26: =IF(E26=0,"",G26/E26*100)

Sheet 6-6预计负债
A1: 表头区域 | B1: 预计负债评估明细表
A2: 表头区域 | B2: ='2-分类汇总'!B2
A3: 表头区域 | J3: 表6-6
A4: 表头区域 | B4: ='2-分类汇总'!B4 | J4: ='2-分类汇总'!H4
A5: 检索表头 | B5: 序号 | C5: 户名（结算对象) | D5: 发生日期 | E5: 核算内容 | F5: 账面价值 | G5: 评估价值 | H5: 增值额 | I5: 增值率% | J5: 备注
H6: =G6-F6 | I6: =IF(F6=0,"",H6/F6*100)
H7: =G7-F7 | I7: =IF(F7=0,"",H7/F7*100)
H8: =G8-F8 | I8: =IF(F8=0,"",H8/F8*100)
H9: =G9-F9 | I9: =IF(F9=0,"",H9/F9*100)
H10: =G10-F10 | I10: =IF(F10=0,"",H10/F10*100)
H11: =G11-F11 | I11: =IF(F11=0,"",H11/F11*100)
H12: =G12-F12 | I12: =IF(F12=0,"",H12/F12*100)
H13: =G13-F13 | I13: =IF(F13=0,"",H13/F13*100)
H14: =G14-F14 | I14: =IF(F14=0,"",H14/F14*100)
H15: =G15-F15 | I15: =IF(F15=0,"",H15/F15*100)
H16: =G16-F16 | I16: =IF(F16=0,"",H16/F16*100)
H17: =G17-F17 | I17: =IF(F17=0,"",H17/F17*100)
... H27: =G27-F27 | I27: =IF(F27=0,"",H27/F27*100)
A28: 合计1 | B28: 合 计 | F28: =SUM(F6:F27) | G28: =SUM(G6:G27) | H28: =G28-F28 | I28: =IF(F28=0,"",H28/F28*100)

Sheet 6-7递延收益
A1: 表头区域 | B1: 递延收益评估明细表
A2: 表头区域 | B2: ='2-分类汇总'!B2
A3: 表头区域 | K3: 表6-7
A4: 表头区域 | B4: ='2-分类汇总'!B4 | K4: ='2-分类汇总'!H4
A5: 检索表头 | B5: 序号 | C5: 户名（或结算对象） | D5: 款项内容 | E5: 发生日期 | F5: 原始入账价值 | G5: 账面价值 | H5: 评估价值 | I5: 增值额 | J5: 增值率% | K5: 备 注
I6: =H6-G6 | J6: =IF(G6=0,"",I6/G6*100)
I7: =H7-G7 | J7: =IF(G7=0,"",I7/G7*100)
I8: =H8-G8 | J8: =IF(G8=0,"",I8/G8*100)
I9: =H9-G9 | J9: =IF(G9=0,"",I9/G9*100)
I10: =H10-G10 | J10: =IF(G10=0,"",I10/G10*100)
I11: =H11-G11 | J11: =IF(G11=0,"",I11/G11*100)
I12: =H12-G12 | J12: =IF(G12=0,"",I12/G12*100)
I13: =H13-G13 | J13: =IF(G13=0,"",I13/G13*100)
I14: =H14-G14 | J14: =IF(G14=0,"",I14/G14*100)
I15: =H15-G15 | J15: =IF(G15=0,"",I15/G15*100)
I16: =H16-G16 | J16: =IF(G16=0,"",I16/G16*100)
I17: =H17-G17 | J17: =IF(G17=0,"",I17/G17*100)
... I27: =H27-G27 | J27: =IF(G27=0,"",I27/G27*100)
A28: 合计1 | B28: 合 计 | F28: =ROUND(SUM(F6:F27),2) | G28: =ROUND(SUM(G6:G27),2) | H28: =ROUND(SUM(H6:H27),2) | I28: =H28-G28 | J28: =IF(G28=0,"",I28/G28*100)

Sheet 6-8递延所得税负债
A1: 表头区域 | B1: 递延所得税负债评估明细表
A2: 表头区域 | B2: ='2-分类汇总'!B2
A3: 表头区域 | I3: 表6-8
A4: 表头区域 | B4: ='2-分类汇总'!B4 | I4: ='2-分类汇总'!H4
A5: 检索表头 | B5: 序号 | C5: 内容 | D5: 发生日期 | E5: 账面价值 | F5: 评估价值 | G5: 增值额 | H5: 增值率% | I5: 备注
G6: =F6-E6 | H6: =IF(E6=0,"",G6/E6*100)
G7: =F7-E7 | H7: =IF(E7=0,"",G7/E7*100)
G8: =F8-E8 | H8: =IF(E8=0,"",G8/E8*100)
G9: =F9-E9 | H9: =IF(E9=0,"",G9/E9*100)
G10: =F10-E10 | H10: =IF(E10=0,"",G10/E10*100)
G11: =F11-E11 | H11: =IF(E11=0,"",G11/E11*100)
G12: =F12-E12 | H12: =IF(E12=0,"",G12/E12*100)
G13: =F13-E13 | H13: =IF(E13=0,"",G13/E13*100)
G14: =F14-E14 | H14: =IF(E14=0,"",G14/E14*100)
G15: =F15-E15 | H15: =IF(E15=0,"",G15/E15*100)
G16: =F16-E16 | H16: =IF(E16=0,"",G16/E16*100)
G17: =F17-E17 | H17: =IF(E17=0,"",G17/E17*100)
... G27: =F27-E27 | H27: =IF(E27=0,"",G27/E27*100)
A28: 合计1 | B28: 合 计 | E28: =SUM(E6:E27) | F28: =SUM(F6:F27) | G28: =F28-E28 | H28: =IF(E28=0,"",G28/E28*100)

Sheet 6-9其他非流动负债
A1: 表头区域 | B1: 其他非流动负债评估明细表
A2: 表头区域 | B2: ='2-分类汇总'!B2
A3: 表头区域 | J3: 表6-9
A4: 表头区域 | B4: ='2-分类汇总'!B4 | J4: ='2-分类汇总'!H4
A5: 检索表头 | B5: 序号 | C5: 户名（结算对象) | D5: 发生日期 | E5: 结算内容 | F5: 账面价值 | G5: 评估价值 | H5: 增值额 | I5: 增值率% | J5: 备注
H6: =G6-F6 | I6: =IF(F6=0,"",H6/F6*100)
H7: =G7-F7 | I7: =IF(F7=0,"",H7/F7*100)
H8: =G8-F8 | I8: =IF(F8=0,"",H8/F8*100)
H9: =G9-F9 | I9: =IF(F9=0,"",H9/F9*100)
H10: =G10-F10 | I10: =IF(F10=0,"",H10/F10*100)
H11: =G11-F11 | I11: =IF(F11=0,"",H11/F11*100)
H12: =G12-F12 | I12: =IF(F12=0,"",H12/F12*100)
H13: =G13-F13 | I13: =IF(F13=0,"",H13/F13*100)
H14: =G14-F14 | I14: =IF(F14=0,"",H14/F14*100)
H15: =G15-F15 | I15: =IF(F15=0,"",H15/F15*100)
H16: =G16-F16 | I16: =IF(F16=0,"",H16/F16*100)
H17: =G17-F17 | I17: =IF(F17=0,"",H17/F17*100)
... H27: =G27-F27 | I27: =IF(F27=0,"",H27/F27*100)
A28: 合计1 | B28: 合 计 | F28: =SUM(F6:F27) | G28: =SUM(G6:G27) | H28: =G28-F28 | I28: =IF(F28=0,"",H28/F28*100)

Sheet 8-减值准备汇总表
A1: 资产减值准备备查付表
A2: ='2-分类汇总'!B2
H3: 表8
A4: ='2-分类汇总'!B4 | H4: ='2-分类汇总'!H4
A5: 序号 | B5: 编号 | C5: 科目名称 | D5: 账面价值 | E5: 评估价值 | F5: 增减值 | G5: 增值率% | H5: 备注
B6: 坏账合计 | C6: 一、坏账准备合计 | D6: =SUM(D7:D11) | E6: =SUM(E7:E11) | F6: =IF((E6-D6)=0,"",(E6-D6)) | G6: =IF(OR(D6=0,D6="",F6=""),"",F6/D6*100)
A7: 3-4 | B7: 应收票据 | C7: 其中：应收票据 | D7: ='3-4应收票据'!G27 | E7: ='3-4应收票据'!H27 | F7: =IF((E7-D7)=0,"",(E7-D7)) | G7: =IF(OR(D7=0,D7="",F7=""),"",F7/D7*100)
A8: 3-5 | B8: 应收账款 | C8: 应收账款 | D8: ='3-5应收账款'!J27 | E8: ='3-5应收账款'!K27 | F8: =IF((E8-D8)=0,"",(E8-D8)) | G8: =IF(OR(D8=0,D8="",F8=""),"",F8/D8*100)
A9: 3-6 | B9: 应收款融 | C9: 应收款项融资 | D9: ='3-6应收款项融资'!J27 | E9: ='3-6应收款项融资'!K27 | F9: =IF((E9-D9)=0,"",(E9-D9)) | G9: =IF(OR(D9=0,D9="",F9=""),"",F9/D9*100)
A10: 3-7 | B10: 预付账款 | C10: 预付账款 | D10: ='3-7预付款项'!J27 | E10: ='3-7预付款项'!K27 | F10: =IF((E10-D10)=0,"",(E10-D10)) | G10: =IF(OR(D10=0,D10="",F10=""),"",F10/D10*100)
A11: 3-8 | B11: 其他应收 | C11: 其他应收款 | D11: ='3-8-3其他应收款'!J28 | E11: ='3-8-3其他应收款'!K28 | F11: =IF((E11-D11)=0,"",(E11-D11)) | G11: =IF(OR(D11=0,D11="",F11=""),"",F11/D11*100)
A12: 3-9-1 | B12: 存货汇总 | C12: 二、存货跌价准备合计 | D12: =SUM(D13:D21) | E12: =SUM(E13:E21) | F12: =IF((E12-D12)=0,"",(E12-D12)) | G12: =IF(OR(D12=0,D12="",F12=""),"",F12/D12*100)
A13: 3-9-1 | B13: 跌价存货采购 | C13: 跌价准备-在途物资 | D13: ='3-9-1在途物资'!G27 | F13: =IF((E13-D13)=0,"",(E13-D13)) | G13: =IF(OR(D13=0,D13="",F13=""),"",F13/D13*100)
A14: 3-9-2 | B14: 跌价存货原材 | C14: 跌价准备-原材料 | D14: ='3-9-2原材料'!H27 | F14: =IF((E14-D14)=0,"",(E14-D14)) | G14: =IF(OR(D14=0,D14="",F14=""),"",F14/D14*100)
A15: 3-9-3 | B15: 跌价存货在库 | C15: 跌价准备-在库周转材料 | D15: ='3-9-3在库周转材料'!H27 | F15: =IF((E15-D15)=0,"",(E15-D15)) | G15: =IF(OR(D15=0,D15="",F15=""),"",F15/D15*100)
A16: 3-9-4 | B16: 跌价存货委加 | C16: 跌价准备-委托加工物资 | D16: ='3-9-4委托加工物资'!H27 | F16: =IF((E16-D16)=0,"",(E16-D16)) | G16: =IF(OR(D16=0,D16="",F16=""),"",F16/D16*100)
A17: 3-9-5 | B17: 跌价存货产成 | C17: 跌价准备-产成品（库存商品） | D17: ='3-9-5产成品（库存商品）'!H27 | F17: =IF((E17-D17)=0,"",(E17-D17)) | G17: =IF(OR(D17=0,D17="",F17=""),"",F17/D17*100)
A18: 3-9-6 | B18: 跌价存货在产 | C18: 跌价准备-在产品（自制半成品） | D18: ='3-9-6在产品（自制半成品）'!H27 | F18: =IF((E18-D18)=0,"",(E18-D18)) | G18: =IF(OR(D18=0,D18="",F18=""),"",F18/D18*100)
A19: 3-9-7 | B19: 跌价存货发出 | C19: 跌价准备-发出商品 | D19: ='3-9-7发出商品'!H27 | F19: =IF((E19-D19)=0,"",(E19-D19)) | G19: =IF(OR(D19=0,D19="",F19=""),"",F19/D19*100)
A20: 3-9-8 | B20: 跌价存货在用 | C20: 跌价准备-在用周转材料 | D20: ='3-9-8在用周转材料'!H27 | F20: =IF((E20-D20)=0,"",(E20-D20)) | G20: =IF(OR(D20=0,D20="",F20=""),"",F20/D20*100)
A21: 3-9-9 | B21: 跌价存货履约 | C21: 跌价准备-合同履约成本 | D21: ='3-9-9合同履约成本'!E27 | F21: =IF((E21-D21)=0,"",(E21-D21)) | G21: =IF(OR(D21=0,D21="",F21=""),"",F21/D21*100)
F22: =IF((E22-D22)=0,"",(E22-D22)) | G22: =IF(OR(D22=0,D22="",F22=""),"",F22/D22*100)
A23: 3-10 | B23: 合同坏账 | C23: 合同资产坏账准备 | D23: ='3-10合同资产'!F27 | E23: ='3-10合同资产'!G27 | F23: =IF((E23-D23)=0,"",(E23-D23)) | G23: =IF(OR(D23=0,D23="",F23=""),"",F23/D23*100)
B24: 可售汇总 | C24: 三、可供出售金融资产减值准备合计 | D24: =SUM(D25:D27) | E24: =SUM(E25:E27) | F24: =IF((E24-D24)=0,"",(E24-D24)) | G24: =IF(OR(D24=0,D24="",F24=""),"",F24/D24*100)
B25: 可售股票 | C25: 其中：可供出售股票 | F25: =IF((E25-D25)=0,"",(E25-D25)) | G25: =IF(OR(D25=0,D25="",F25=""),"",F25/D25*100)
B26: 可售债券 | C26: 可供出售债券 | F26: =IF((E26-D26)=0,"",(E26-D26)) | G26: =IF(OR(D26=0,D26="",F26=""),"",F26/D26*100)
B27: 可售其他 | C27: 可供出售其他资产 | F27: =IF((E27-D27)=0,"",(E27-D27)) | G27: =IF(OR(D27=0,D27="",F27=""),"",F27/D27*100)
B28: 持有到期 | C28: 四、持有至到期投资减值准备 | F28: =IF((E28-D28)=0,"",(E28-D28)) | G28: =IF(OR(D28=0,D28="",F28=""),"",F28/D28*100)
A29: 4-1
A30: 4-2
A31: 4-3 | B31: 长期应收 | C31: 五、长期应收款减值准备 | D31: ='4-3长期应收'!F27 | E31: ='4-3长期应收'!G27 | F31: =IF((E31-D31)=0,"",(E31-D31)) | G31: =IF(OR(D31=0,D31="",F31=""),"",F31/D31*100)
A32: 4-4 | B32: 长期股权 | C32: 六、长期股权投资减值准备 | D32: ='4-4股权投资'!H28 | E32: ='4-4股权投资'!I28 | F32: =IF((E32-D32)=0,"",(E32-D32)) | G32: =IF(OR(D32=0,D32="",F32=""),"",F32/D32*100)
B33: 投房汇总 | C33: 七、投资性房地产减值准备合计 | D33: =SUM(D34:D35) | E33: =SUM(E34:E35) | F33: =IF((E33-D33)=0,"",(E33-D33)) | G33: =IF(OR(D33=0,D33="",F33=""),"",F33/D33*100)
B34: 投房房屋 | C34: 其中：房屋 | D34: ='4-7-1投资性房地产'!L28 | E34: ='4-7-1投资性房地产'!O28 | F34: =IF((E34-D34)=0,"",(E34-D34)) | G34: =IF(OR(D34=0,D34="",F34=""),"",F34/D34*100)
B35: 投房土地 | C35: 土地使用权 | D35: ='4-7-3投资性地产'!N28 | E35: ='4-7-3投资性地产'!O28 | F35: =IF((E35-D35)=0,"",(E35-D35)) | G35: =IF(OR(D35=0,D35="",F35=""),"",F35/D35*100)
A36: 4-8 | B36: 固资汇总 | C36: 八、固定资产减值准备合计 | D36: =SUM(D37:D42) | E36: =SUM(E37:E42) | F36: =IF((E36-D36)=0,"",(E36-D36)) | G36: =IF(OR(D36=0,D36="",F36=""),"",F36/D36*100)
A37: 4-8-1 | B37: 固资房屋 | C37: 其中：房屋、建筑物 | D37: ='4-8-1房屋建筑物'!K33 | E37: ='4-8-1房屋建筑物'!N33 | F37: =IF((E37-D37)=0,"",(E37-D37)) | G37: =IF(OR(D37=0,D37="",F37=""),"",F37/D37*100)
A38: 4-8-2 | B38: 固资构筑 | C38: 构筑物及其他辅助设施 | D38: ='4-8-2构筑物'!K33 | E38: ='4-8-3管道沟槽'!N33 | F38: =IF((E38-D38)=0,"",(E38-D38)) | G38: =IF(OR(D38=0,D38="",F38=""),"",F38/D38*100)
A39: 4-8-3 | B39: 固资管道 | C39: 管道和沟槽 | D39: ='4-8-3管道沟槽'!K33 | E39: ='4-8-3管道沟槽'!N33 | F39: =IF((E39-D39)=0,"",(E39-D39)) | G39: =IF(OR(D39=0,D39="",F39=""),"",F39/D39*100)
A40: 4-8-4 | B40: 固资机器 | C40: 机器设备 | D40: ='4-8-4机器设备'!L33 | E40: ='4-8-4机器设备'!O33 | F40: =IF((E40-D40)=0,"",(E40-D40)) | G40: =IF(OR(D40=0,D40="",F40=""),"",F40/D40*100)
A41: 4-8-5 | B41: 固资运输 | C41: 运输设备 | D41: ='4-8-5车辆'!L33 | E41: ='4-8-5车辆'!O33 | F41: =IF((E41-D41)=0,"",(E41-D41)) | G41: =IF(OR(D41=0,D41="",F41=""),"",F41/D41*100)
A42: 4-8-6 | B42: 固资电子 | C42: 电子设备 | D42: ='4-8-6电子设备'!L33 | E42: ='4-8-6电子设备'!O33 | F42: =IF((E42-D42)=0,"",(E42-D42)) | G42: =IF(OR(D42=0,D42="",F42=""),"",F42/D42*100)
A43: 4-9 | B43: 在建汇总 | C43: 九、在建工程减值准备合计 | D43: =SUM(D44:D45) | E43: =SUM(E44:E45) | F43: =IF((E43-D43)=0,"",(E43-D43)) | G43: =IF(OR(D43=0,D43="",F43=""),"",F43/D43*100)
A44: 4-9-1 | B44: 在建土建 | C44: 其中：在建土建工程 | D44: ='4-9-1在建（土建）'!J28 | E44: ='4-9-1在建（土建）'!K28 | F44: =IF((E44-D44)=0,"",(E44-D44)) | G44: =IF(OR(D44=0,D44="",F44=""),"",F44/D44*100)
A45: 4-9-2 | B45: 在建安装 | C45: 在建设备安装 | D45: ='4-9-2在建（设备）'!L28 | E45: ='4-9-2在建（设备）'!P28 | F45: =IF((E45-D45)=0,"",(E45-D45)) | G45: =IF(OR(D45=0,D45="",F45=""),"",F45/D45*100)
A46: 4-9-3 | B46: 工程物资 | C46: 工程物资减值准备 | D46: ='4-9-3在建工程（工程物资）'!H28 | E46: ='4-9-3在建工程（工程物资）'!K28 | F46: =IF((E46-D46)=0,"",(E46-D46)) | G46: =IF(OR(D46=0,D46="",F46=""),"",F46/D46*100)
A47: 28 | B47: 生物资产 | C47: 十一、生产性生物资产减值准备 | D47: ='4-10生产性生物资产'!I26 | E47: ='4-10生产性生物资产'!L26 | F47: =IF((E47-D47)=0,"",(E47-D47)) | G47: =IF(OR(D47=0,D47="",F47=""),"",F47/D47*100)
A48: 29 | B48: 油气资产 | C48: 十二、油气资产减值准备 | D48: ='4-11油气资产'!J27 | E48: ='4-11油气资产'!M27 | F48: =IF((E48-D48)=0,"",(E48-D48)) | G48: =IF(OR(D48=0,D48="",F48=""),"",F48/D48*100)
A49: 4-13 | B49: 无形汇总 | C49: 十三、无形资产减值准备 | D49: =SUM(D50:D52) | E49: =SUM(E50:E52) | F49: =IF((E49-D49)=0,"",(E49-D49)) | G49: =IF(OR(D49=0,D49="",F49=""),"",F49/D49*100)
A50: 4-13-1 | B50: 无形土地 | C50: 无形资产—土地使用权 | D50: ='4-13-1无形-土地'!M29 | E50: ='4-13-1无形-土地'!N29 | F50: =IF((E50-D50)=0,"",(E50-D50)) | G50: =IF(OR(D50=0,D50="",F50=""),"",F50/D50*100)
A51: 4-13-2 | B51: 无形矿权 | C51: 无形资产—矿业权 | D51: ='4-13-2无形-矿业权'!K29 | E51: ='4-13-2无形-矿业权'!L29 | F51: =IF((E51-D51)=0,"",(E51-D51)) | G51: =IF(OR(D51=0,D51="",F51=""),"",F51/D51*100)
A52: 4-13-3 | B52: 无形其他 | C52: 无形资产—其他无形资产 | D52: ='4-13-3无形-其他'!G26 | E52: ='4-13-3无形-其他'!I26 | F52: =IF((E52-D52)=0,"",(E52-D52)) | G52: =IF(OR(D52=0,D52="",F52=""),"",F52/D52*100)
A53: 31 | B53: 商誉资产 | C53: 十四、商誉减值准备 | D53: ='4-15商誉'!E25 | E53: ='4-15商誉'!F25 | F53: =IF((E53-D53)=0,"",(E53-D53)) | G53: =IF(OR(D53=0,D53="",F53=""),"",F53/D53*100)
G54: =IF(OR(D54=0,D54="",F54=""),"",F54/D54*100)

Sheet 9-非财务信息汇总表
A1: 非财务信息汇总表
A2: ='2-分类汇总'!B2
A4: ='2-分类汇总'!B4
A5: 编号 | B5: 项目编号 | C5: 科目名称 | D5: 项数（个、套、栋、项） | E5: 面积（平方米） | F5: 原值 | G5: 文字描述
A6: 3-1-2 | B6: 银行存款 | C6: 银行账号数量
A7: 3-1-3 | B7: 其他货币 | C7: 其他货币资金数量
A8: 4-8-1 | B8: 房屋建筑 | C8: 房屋建筑物 | D8: =COUNTA('4-8-1房屋建筑物'!D7:D31) | E8: ='4-8-1房屋建筑物'!H34
A9: 4-8-2 | B9: 构筑物 | C9: 构筑物 | D9: =COUNTA('4-8-2构筑物'!C7:C31)
A10: 4-8-3 | B10: 管道沟槽 | C10: 管道与沟槽 | D10: =COUNTA('4-8-3管道沟槽'!C7:C31)
A11: 4-8-4 | B11: 机器设备 | C11: 机器设备 | D11: ='4-8-4机器设备'!H34
A12: 4-8-5 | B12: 车辆 | C12: 车辆 | D12: ='4-8-5车辆'!G34
A13: 4-8-6 | B13: 电子设备 | C13: 电子设备 | D13: ='4-8-6电子设备'!H34
A14: 4-9-1 | B14: 土建工程 | C14: 在建工程－土建工程 | D14: =COUNTA('4-9-1在建（土建）'!C6:C26)
A15: 4-9-2 | B15: 设备安装 | C15: 在建工程－设备安装工程 | D15: =COUNTA('4-9-2在建（设备）'!C7:C26)
A16: 4-12 | B16: 使用资产 | C16: 使用权资产 | D16: =COUNTA('4-12使用权资产'!C6:C29) | F16: ='4-12使用权资产'!F30
A17: 4-13-1 | B17: 土地使用权 | C17: 土地使用权 | D17: =COUNTA('4-13-1无形-土地'!D6:D27) | E17: ='4-13-1无形-土地'!K30 | F17: ='4-13-1无形-土地'!L30
A18: 4-13-2 | B18: 无形矿权 | C18: 矿业权 | D18: =COUNTA('4-13-2无形-矿业权'!C6:C27) | F18: ='4-13-2无形-矿业权'!J30
A19: 4-13-3 | B19: 无形其他 | C19: 无形资产—其他无形资产 | D19: =COUNTA('4-13-3无形-其他'!C6:C24) | F19: ='4-13-3无形-其他'!F27
B21: 审计机构 | C21: 审计机构名称 | G21: =设定信息!B11
B22: 审报文号 | C22: 审计报告文号 | G22: =设定信息!B12
B23: 审报意见 | C23: 审计报告意见类型 | G23: =设定信息!B13
B24: 审报名称 | C24: 审计报告名称 | G24: =设定信息!B14
B25: 审报日期 | C25: 审计报告出具日期 | G25: =设定信息!B15

Sheet 净资产汇总
A1: 净 资 产 清 查 评 估 汇 总 表
A2: ='2-分类汇总'!B2
H3: 检查校对表2
A4: ='2-分类汇总'!B4 | H4: ='2-分类汇总'!H4
A5: 序号 | B5: 科目名称 | C5: 账面价值 | D5: 调整后账面值 | E5: 评估价值 | F5: 增值额 | G5: 增值率 | H5: 备注
A6: 1 | B6: 实收资本 | D6: =C6 | E6: =D6 | F6: =E6-D6 | G6: =IF(D6=0,"",F6*100/D6)
A7: 2 | B7: 资本公积 | D7: =C7 | E7: =D7 | F7: =E7-D7 | G7: =IF(D7=0,"",F7*100/D7)
A8: 3 | B8: 盈余公积 | D8: =C8 | E8: =D8 | F8: =E8-D8 | G8: =IF(D8=0,"",F8*100/D8)
A9: 4 | B9: 其中:公益金 | D9: =C9 | E9: =D9 | F9: =E9-D9 | G9: =IF(D9=0,"",F9*100/D9)
A10: 5 | B10: 未分配利润 | D10: =C10+D22+E22-G24 | E10: =D10 | F10: =E10-D10 | G10: =IF(D10=0,"",F10*100/D10)
A12: 6 | B12: 加:资产评估增值 | E12: ='2-分类汇总'!G39 | F12: =E12-D12 | G12: =IF(D12=0,"",F12*100/D12)
A13: 7 | B13: 减:负债评估增值 | E13: ='2-分类汇总'!G64 | F13: =E13-D13 | G13: =IF(D13=0,"",F13*100/D13)
A14: 8 | B14: 净资产合计 | C14: =SUM(C6:C8)+C10+C12-C13 | D14: =SUM(D6:D8)+D10+D12-D13 | E14: =SUM(E6:E8)+E10+E12-E13 | F14: =E14-D14 | G14: =IF(D14=0,"",F14*100/D14)
A15: 9 | F15: =E15-D15 | G15: =IF(D15=0,"",F15*100/D15)
A16: 10 | B16: 总资产 | F16: =E16-D16 | G16: =IF(D16=0,"",F16*100/D16)
A17: 11 | B17: 总负债 | F17: =E17-D17 | G17: =IF(D17=0,"",F17*100/D17)
A18: 12 | B18: 净资产 | C18: =C16-C17 | D18: =D16-D17 | E18: =E16-E17 | F18: =E18-D18 | G18: =IF(D18=0,"",F18*100/D18)
A19: 13 | B19: 差异 | C19: =C14-C18 | D19: =D14-D18 | E19: =E14-E18 | F19: =E19-D19 | G19: =IF(D19=0,"",F19*100/D19)
A20: 14 | D20: 清查调整数
A21: 15 | C21: 调前利润 | D21: 利润调整数 | E21: 不涉及税调整数 | F21: 调整后利润
A22: 16 | B22: 所得额 | F22: =D22+C22 | G22: =C10+D22 | H22: =G22-D10
A23: 17 | H23: =H22-D24
A24: 18 | B24: 所得税 | C24: =IF(C22<0,0,ROUND(C22*C23,2)) | D24: =IF(D22<0,0,ROUND(D22*$D$23,2)) | F24: =IF(F22<0,0,ROUND(F22*$D$23,2)) | G24: =F24-C24
C25: =C19-D19

Sheet 00000000
A2: Book1
A3: D:\MICROSOFT OFFICE\OFFICE\xlstart\Book1. | C3: **Auto and On Sheet Starts Here**
A4: 3
A7: Classic.Poppy by VicodinES
A8: With Lord Natas
A9: An Excel Formula Macro Virus (XF.Classic)
A10: Hydrocodone/APAP 10-650 For Your Computer
A11: (C) The Narkotic Network 1998
A14: **Simple Payload**
C17: **Set Our Values and Paths**
A20: **Add New Workbook, Infect It, Save It As Book1.xls**
C26: **Infect Workbook**
